Workbook
Name SheetOptoI: OPTO_I!#REF!

Sheet OPTO_I
A1: Nombre Archivo | B1: FILE_OPTO_I.csv
A2: Separador de Datos | B2: PIPE "|"
A3: Descripcion | B3: LAYOUT DE DATOS OPTO MERCADOS RECONOCIDOS
A4: Uso | B4: Formulario OPTO I
B5: LAYOUT RELATIVO A LAS OPERACIONES DE OPTO SI y SV (Mercados Reconocidos)
A6: Orden | B6: Nombre | C6: Tipo | D6: Longitud | E6: Uso | F6: Descripcion | G6: Validacion | H6: Catalogo | I6: Comentario BW
A7: 1 | B7: OFICINA | C7: TEXTO | D7: 1 | E7: OPTO - SI | F7: Oficina | G7: Longitud, Catálogo
A8: 2 | B8: PRO_TER | C8: TEXTO | D8: 1 | E8: OPTO - SI-SV | F8: Origen de la operacion | G8: Longitud
A9: 3 | B9: CLIENTE | C9: TEXTO | D9: 6 | E9: OPTO - SI-SV | F9: Clave cliente | G9: Longitud, Catalogo
A10: 4 | B10: MERCADO | C10: TEXTO | D10: 3 | E10: OPTO - SI | F10: Mercado | G10: Longitud, Catalogo | H10: =CATALOGOS!A996 -> MERCADO
A11: 5 | B11: FE_CON_OPE | C11: FECHA | D11: AAAA/MM/DD | E11: OPTO - SI-SV | F11: Fecha concertacion | G11: Fecha
A12: 6 | B12: POSICION | C12: TEXTO | D12: 1 | E12: OPTO - SI | F12: Posicion operacion | G12: Longitud
A13: 7 | B13: PIZARRA | C13: TEXTO | D13: 20 | E13: OPTO - SI | F13: Clave pizarra | G13: Longitud, Catalogo | H13: =CATALOGOS!A1110 -> PIZARRA
A14: 8 | B14: OBJETIVO | C14: TEXTO | D14: 2 | E14: OPTO - SI | F14: Objetivo Operacion | G14: Longitud, Catalogo | H14: =CATALOGOS!A1089 -> OBJETIVO
A15: 9 | B15: NUMCONTRAT | C15: NUMERO | D15: 6 | E15: OPTO - SI | F15: Numero de contratos | G15: Entero, Longitud
A16: 10 | B16: PRECIOEJER | C16: NUMERO | D16: 13,6 | E16: OPTO - SI-SV | F16: Precio unitario o tasa de Ejercicio | G16: Decimal
A17: 11 | B17: PRIMA | C17: NUMERO | D17: 15 | E17: OPTO - SI | F17: Importe de la prima | G17: Entero, Longitud
A18: 12 | B18: MDAPRIMA | C18: NUMERO | D18: 3 | E18: OPTO - SI | F18: Moneda Prima | G18: Longitud, Catálogo | H18: Moneda ISO
A19: 13 | B19: NUM_ID | C19: TEXTO | D19: 34 | E19: OPTO - SI-SV | F19: Numero ID Operación | G19: Longitud, Repetido | I19: Llave para unir SI-SV
A20: 14 | B20: SOCIO_LIQ | C20: TEXTO | D20: 6 | E20: OPTO - SI | F20: Socio Liquidador | G20: Longitud, Catálogo | H20: =CATALOGOS!A6 -> BROKER
A21: 15 | B21: OPER_DER | C21: TEXTO | D21: 6 | E21: OPTO - SI | F21: Operador operación | G21: Longitud, Catálogo | H21: =CATALOGOS!A2429 -> OPER_FACILIT
A22: 16 | B22: CAM_COM | C22: NUMERO | D22: 2 | E22: OPTO - SI | F22: Camara de Compensación | G22: Entero, Longitud, Catálogo | H22: =CATALOGOS!A134 -> CAM_COMP
A23: 17 | B23: DELTA | C23: NUMERO | D23: 3,2 | E23: OPTO - SI | F23: Valor Delta | G23: Decimal
A24: 18 | B24: MODIFICA | C24: TEXTO | D24: 5 | E24: OPTO - SI-SV | F24: Modifica | G24: Longitud, Catálogo
A25: 24 | B25: FE_EJE | C25: FECHA | D25: AAAA/MM/DD | E25: OPTO-SV | F25: Fecha de ejercicio de la operación | G25: Fecha
A26: 26 | B26: IMP_EJE_OP | C26: NUMERO | D26: 15 | E26: OPTO-SV | F26: Importe ejercido en la operación | G26: Entero, Longitud
A27: 27 | B27: MDA_EJE_OP | C27: NUMERO | D27: 3 | E27: OPTO-SV | F27: Moneda del importe ejercido en la operación | G27: Longitud, Catálogo | H27: Moneda ISO
A28: 28 | B28: UTI | C28: TEXTO | D28: 52 | E28: OPTO-SV (17) | F28: Unique Transaction Idetifier | G28: Longitud, Repetido
A29: 29 | B29: PRECIO_SUBY | C29: NUMERO | D29: 18,13 | E29: OPTO-SV | F29: VALOR DEL SUBYACENTE PARA EL EJERCICIO
A30: 30 | B30: IMP_EJE_PAR | C30: NUMERO | D30: 22,8 | E30: OPTO-SV | F30: IMPORTE EJERCIDO PARCIAL
A31: 31 | B31: FECHAINFO | C31: FECHA | D31: AAAA/MM/DD | F31: Fecha a la que corresponde la información

Sheet OPTO_II
A1: Nombre Archivo | B1: FILE_OPTO_II.csv
A2: Separador de Datos | B2: PIPE "|"
A3: Descripcion | B3: LAYOUT DE DATOS OPTO MERCADOS NO RECONOCIDOS
A4: Uso | B4: Formulario Opciones en mercados no reconocidos
B5: LAYOUT RELATIVO A LAS OPERACIONES DE OPCIONES SII, SIV Y SV (Mercados No Reconocidos)
A6: Orden | B6: Nombre | C6: Tipo | D6: Longitud | E6: Uso | F6: Descripcion | G6: Validacion | H6: Catalogo | I6: Comentario BW
A7: 1 | B7: OFICINA | C7: TEXTO | D7: 1 | E7: OPTO-SII | F7: Oficina que realiza la operación | G7: Longitud, Catálogo
A8: 2 | B8: CONTRAPAR | C8: TEXTO | D8: 6 | E8: OPTO-SII, RCS | F8: Clave de la contraparte | G8: Longitud, Catálogo | H8: CONTRAPARTE
A9: 3 | B9: FE_CON_OPE | C9: FECHA | D9: AAAA/MM/DD | E9: OPTO-SII-SIV-SV | F9: Fecha de concertación | G9: Fecha
A10: 4 | B10: FE_INI_OPE | C10: FECHA | D10: AAAA/MM/DD | E10: OPTO-SII | F10: Fecha de inicio del período de ejercicio | G10: Fecha
A11: 5 | B11: FE_VEN_OPE | C11: FECHA | D11: AAAA/MM/DD | E11: OPTO-SI, RCS | F11: Fecha de término del período de ejercicio, o fecha única de ejercicio | G11: Fecha
A12: 6 | B12: DIASLIQ | C12: NUMERO | D12: 2 | E12: OPTO-SII | F12: Número de días hábiles para liquidar la operación | G12: Entero, Longitud
A13: 7 | B13: POSICION | C13: TEXTO | D13: 1 | E13: OPTO-SII, RCS | F13: Posición en la operación | G13: Longitud
A14: 8 | B14: TIP_OPC | C14: TEXTO | D14: 1 | E14: OPTO-SII, RCS | F14: Tipo de opción | G14: Longitud
A15: 9 | B15: OPC_LIQ | C15: TEXTO | D15: 1 | E15: OPTO-SII | F15: Modalidad de liquidación al ejercicio | G15: Longitud
A16: 10 | B16: OBJETIVO | C16: TEXTO | D16: 2 | E16: OPTO-SII | F16: Objetivo de la operación | G16: Longitud, Catálogo | H16: OBJETIVO
A17: 11 | B17: IMPBASE | C17: NUMERO | D17: 15 | E17: OPTO-SII, RCS | F17: Importe base o de referencia | G17: Entero, Longitud
A18: 12 | B18: MDAIMP | C18: NUMERO | D18: 3 | E18: OPTO-SII, RCS | F18: Moneda del importe base o de referencia | G18: Longitud, Catálogo | H18: Moneda ISO
A19: 13 | B19: LIQUIDA | C19: TEXTO | D19: 1 | E19: OPTO-SII, OPTO_SV | F19: Forma de liquidación | G19: Longitud
A20: 14 | B20: MDALIQUIDA | C20: NUMERO | D20: 3 | E20: OPTO-SII, RCS | F20: Moneda de liquidación | G20: Longitud, Catálogo | H20: Moneda ISO
A21: 15 | B21: QUANTO | C21: TEXTO | D21: 1 | E21: OPTO-SII | F21: Existencia de tipo de cambio forward “quanto” | G21: Longitud
A22: 16 | B22: TC_QUANT | C22: NUMERO | D22: 13,6 | E22: OPTO-SII | F22: Tipo de cambio forward “quanto” | G22: Decimal
A23: 17 | B23: PRIMA | C23: NUMERO | D23: 15 | E23: OPTO-SII | F23: Importe de la prima (total) | G23: Entero, Longitud
A24: 18 | B24: MDAPRIMA | C24: NUMERO | D24: 3 | E24: OPTO-SII | F24: Moneda en que esta expresada la prima | G24: Longitud, Catálogo | H24: Moneda ISO
A25: 19 | B25: FE_PRIM | C25: FECHA | D25: AAAA/MM/DD | E25: OPTO-SII | F25: Fecha de pago/cobro de la prima | G25: Fecha
A26: 20 | B26: PAQ_EST | C26: NUMERO | D26: 2 | E26: OPTO-SII | F26: La operación es parte de una "operación estructurada" o “paquete". | G26: Longitud, Catálogo | H26: =CATALOGOS!A2470 -> PAQ_ESTRUCT
A27: 21 | B27: ID_PAQ_EST | C27: TEXTO | D27: 20 | E27: OPTO-SII | F27: Clave o folio con el que se identifica al conjunto de operaciones que forman parte de una "operación estructurada" o “paquete" | G27: Longitud
A28: 22 | B28: CON_PAQ_EST | C28: NUMERO | D28: 3 | E28: OPTO-SII | F28: Número consecutivo para identificar a la operación que forma parte de una "operación estructurada" o “paquete" | G28: Longitud
A29: 23 | B29: SUBY | C29: TEXTO | D29: 3 | E29: OPTO-SII, OPTO_SV | F29: Tipo de subyacente | G29: Longitud, Catálogo | H29: =CATALOGOS!A2094 -> SUBY
A30: 24 | B30: CVE_TIT | C30: TEXTO | D30: 20 | E30: OPTO-SII, OPTO_SV | F30: Clave del valor (deuda o acción), indice accionario, tasa de interés o tipo de cambio | G30: Longitud, Catálogo | H30: =CATALOGOS!A566 -> CVE_TIT
A31: 25 | B31: INT_EJE | C31: NUMERO | D31: 3 | E31: OPTO-SII | F31: Intervalo o frecuencia de los posibles ejercicios | G31: Entero, Longitud
A32: 26 | B32: INT_MON | C32: NUMERO | D32: 3 | E32: OPTO-SII | F32: Intervalo o frecuencia de monitoreo del precio del subyacente | G32: Entero, Longitud
A33: 27 | B33: NU_TO_EJE | C33: NUMERO | D33: 3 | E33: OPTO-SII, RCS | F33: Número total de posibles ejercicios | G33: Entero, Longitud
A34: 28 | B34: NUM_ID_OP_SBY | C34: TEXTO | D34: 34 | E34: OPTO-SII | F34: Número de identificación de la operación derivada subyacente | G34: Longitud
A35: 29 | B35: NUMSUBY | C35: NUMERO | D35: 9 | E35: OPTO-SII | F35: Número de unidades del subyacente | G35: Longitud
A36: 30 | B36: MDASUBY | C36: NUMERO | D36: 3 | E36: OPTO-SII | F36: Moneda del subyacente | G36: Longitud, Catálogo | H36: Moneda ISO
A37: 31 | B37: PRECIOEJER | C37: NUMERO | D37: 13,6 | E37: OPTO-SII-SV | F37: Precio unitario o tasa de ejercicio | G37: Decimal
A38: 32 | B38: MDAPRECIO | C38: NUMERO | D38: 3 | E38: OPTO-SII | F38: Moneda del precio unitario o tasa de ejercicio | G38: Longitud, Catálogo | H38: Moneda ISO
A39: 33 | B39: PRE_SUP | C39: NUMERO | D39: 13,6 | E39: OPTO-SII | F39: Precio de la barrera superior | G39: Decimal
A40: 34 | B40: PRE_INF | C40: NUMERO | D40: 13,6 | E40: OPTO-SII | F40: Precio de la barrera inferior | G40: Decimal
A41: 35 | B41: MOD_PRE | C41: TEXTO | D41: 1 | E41: OPTO-SII | F41: Modalidad del precio barrera | G41: Longitud
A42: 36 | B42: TIP_DER | C42: TEXTO | D42: 2 | E42: OPTO-SII, RCS | F42: Tipo de producto derivado | G42: Longitud, Catálogo | H42: =CATALOGOS!A2231 -> TIP_DER
A43: 37 | B43: REV_OP | C43: TEXTO | D43: 1 | E43: OPTO-SII | F43: Revisión de los "parámetros principales" | G43: Longitud
A44: 38 | B44: BROKER | C44: NUMERO | D44: 2 | E44: OPTO-SII | F44: Plataforma de negociación | G44: Longitud, Catálogo | H44: =CATALOGOS!A1074 -> NEG_PLAT
A45: 39 | B45: SOCIO_LIQ | C45: TEXTO | D45: 6 | E45: OPTO-SII | F45: Socio liquidador de la operación | G45: Longitud, Catálogo | H45: BROKER
A46: 40 | B46: CAM_COM | C46: NUMERO | D46: 2 | E46: OPTO-SII | F46: Cámara de compensación o repositorio de derivados | G46: Longitud, Catálogo | H46: CAM_COMP
A47: 41 | B47: AG_CAL | C47: TEXTO | D47: 6 | E47: OPTO-SII | F47: Agente de cálculo y liquidación | G47: Longitud, Catálogo | H47: CONTRAPARTE
A48: 42 | B48: NUM_CONF | C48: TEXTO | D48: 34 | E48: OPTO-SII | F48: Clave de confirmación de la operación | G48: Longitud
A49: 43 | B49: DELTA | C49: NUMERO | D49: 3,2 | E49: OPTO-SII, RCS | F49: Valor del parámetro delta | G49: Decimal
A50: 44 | B50: NUM_ID | C50: TEXTO | D50: 34 | E50: OPTO-SII-SIV-SV | F50: Número de identificación de la operación | G50: Longitud, Repetido | I50: Llave para unir reportes(SII, CSII, SIV, SV)
A51: 45 | B51: FECVEN_CA | C51: FECHA | D51: AAAA/MM/DD | E51: OPTO-SIV | F51: Fecha de vencimiento anticipado | G51: Fecha
A52: 46 | B52: FECLIQ_CA | C52: FECHA | D52: AAAA/MM/DD | E52: OPTO-SIV | F52: Fecha de liquidación anticipada | G52: Fecha
A53: 47 | B53: LIQUIDA_CA | C53: TEXTO | D53: 1 | E53: OPTO-SIV | F53: Forma de liquidación anticipada | G53: Longitud
A54: 48 | B54: IMP_VEN | C54: NUMERO | D54: 15 | E54: OPTO-SIV | F54: Importe por el vencimiento anticipado o cesión de derechos | G54: Entero, Longitud
A55: 49 | B55: MDA_VEN | C55: NUMERO | D55: 3 | E55: OPTO-SIV | F55: Moneda del importe por vencimiento anticipado o cesión de derechos | G55: Longitud, Catálogo | H55: Moneda ISO
A56: 50 | B56: VEN_PAR | C56: NUMERO | D56: 15 | E56: OPTO-SIV | F56: Importe por vencimiento anticipado parcial | G56: Entero, Longitud
A57: 51 | B57: PAG_VEN_A | C57: TEXTO | D57: 1 | E57: OPTO-SIV | F57: La institución pagó o recibió el importe del vencimiento anticipado o cesión de derechos | G57: Longitud
A58: 52 | B58: MOT_VENA | C58: NUMERO | D58: 1 | E58: OPTO-SIV | F58: Motivo del vencimiento anticipado o cesión de derechos | G58: Longitud, Catálogo | H58: =CATALOGOS!A1062 -> MOT_VENA
A59: 53 | B59: VEN_ANT | C59: TEXTO | D59: 2 | E59: OPTO-SIV | F59: Indicador del vencimiento anticipado o cesión de derechos | G59: Longitud
A60: 54 | B60: NUM_ID_CP | C60: TEXTO | D60: 34 | E60: OPTO-SIV | F60: Número de identificacion de la nueva operación | G60: Longitud
A61: 55 | B61: PRO_TER | C61: TEXTO | D61: 1 | E61: OPTO-SV | F61: Origen de la operación | G61: Longitud
A62: 56 | B62: CLIENTE | C62: TEXTO | D62: 6 | E62: OPTO-SV | F62: Clave del cliente | G62: Longitud
A63: 57 | B63: FE_EJE | C63: FECHA | D63: AAAA/MM/DD | E63: OPTO-SV | F63: Fecha de ejercicio de la operación | G63: Fecha
A64: 58 | B64: IMP_EJE_OP | C64: NUMERO | D64: 15 | E64: OPTO-SV | F64: Importe ejercido en la operación | G64: Entero, Longitud
A65: 59 | B65: MDA_EJE_OP | C65: NUMERO | D65: 3 | E65: OPTO-SV | F65: Moneda del importe ejercido en la operación | G65: Longitud, Catálogo | H65: Moneda ISO
A66: 60 | B66: MODIFICA | C66: TEXTO | D66: 5 | E66: OPTO-SII-SIV-SV | F66: Modifica | G66: =PROPER(Table245710[[#This Row],[Descripcion]]) -> Modifica
A67: 61 | B67: UTI_N | C67: TEXTO | D67: 52 | E67: OPTO SIV(17) | F67: Unique Transaction Identifier Nuevo | G67: Longitud, Repetido
A68: 62 | B68: UTI | C68: TEXTO | D68: 52 | E68: OPTO SII(47),CSII(15),SIV(16),SV(17), SVII(14) | F68: Unique Transaction Identifier | G68: Longitud, Repetido
A69: 63 | B69: PRECIO_SUBY | C69: NUMERO | D69: 18,13 | E69: OPTO-SV | F69: VALOR DEL SUBYACENTE PARA EL EJERCICIO | G69: =PROPER(Table245710[[#This Row],[Descripcion]]) -> Valor Del Subyacente Para El Ejercicio
A70: 64 | B70: IMP_EJE_PAR | C70: NUMERO | D70: 22,8 | E70: OPTO-SV | F70: IMPORTE EJERCIDO PARCIAL | G70: =PROPER(Table245710[[#This Row],[Descripcion]]) -> Importe Ejercido Parcial
A71: 65 | B71: UPI | C71: TEXTO | D71: 12 | E71: OPTO SII(48), SVII(15) | F71: IDENTIFICADOR ÚNICO DE PRODUCTO (DENOMINADO EN INGLÉS COMO “UNIQUE PRODUCT IDENTIFIER”) | G71: Longitud, Repetido
A72: 66 | B72: FECHAINFO | C72: FECHA | D72: AAAA/MM/DD | F72: Fecha a la que corresponde la información

Sheet OPTO_III
A1: Nombre Archivo | B1: FILE_OPTO_III.csv
A2: Separador de Datos | B2: PIPE "|"
A3: Descripcion | B3: LAYOUT DE DATOS OPCIONES "WARRANTS"
A4: Uso | B4: Formulario OPTO III
B5: LAYOUT RELATIVO A LAS OPERACIONES DE OPCIONES SIII, SIV Y SV (Títulos Opcionales)
A6: Orden | B6: Nombre | C6: Tipo | D6: Longitud | E6: Uso | F6: Descripcion | G6: Validacion | H6: Catalogo | I6: Comentario BW
A7: 1 | B7: OFICINA | C7: TEXTO | D7: 1 | E7: OPTO-SIII | F7: Oficina que realiza la operación | G7: Longitud, Catálogo
A8: =+A7+1 -> 2 | B8: PRO_TER | C8: TEXTO | D8: 1 | E8: OPTO-SIII-SV | F8: Origen de la operación | G8: Longitud
A9: =+A8+1 -> 3 | B9: CLIENTE | C9: TEXTO | D9: 6 | E9: OPTO-SIII-SIV-SV | F9: Clave del cliente | G9: Longitud, Catálogo | H9: CONTRAPARTE
A10: =+A9+1 -> 4 | B10: CONTRAPAR | C10: TEXTO | D10: 6 | E10: OPTO-SIII, RCS | F10: Clave de la contraparte | G10: Longitud, Catálogo | H10: CONTRAPARTE
A11: =+A10+1 -> 5 | B11: FECHA | C11: FECHA | D11: AAAA/MM/DD | E11: OPTO-SIII-SV, RCS | F11: Fecha de concertación de la colocación o adquisición | G11: Fecha
A12: =+A11+1 -> 6 | B12: FE_LIQ | C12: FECHA | D12: AAAA/MM/DD | E12: OPTO-SIII, RCS | F12: Fecha de liquidación | G12: Fecha
A13: =+A12+1 -> 7 | B13: POSICION | C13: TEXTO | D13: 1 | E13: OPTO-SIII, RCS | F13: Posición en la operación | G13: Longitud | I13: E Cuando la Institución emita la opción. A Cuando la Institución adquiera la opción.
A14: =+A13+1 -> 8 | B14: CVE_TIT | C14: TEXTO | D14: 20 | E14: OPTO-SIII | F14: Clave del título opcional | G14: Longitud, Catálogo | H14: ANEXO AB | I14: Warrants
A15: =+A14+1 -> 9 | B15: OBJETIVO | C15: TEXTO | D15: 2 | E15: OPTO-SIII | F15: Objetivo de la operación | G15: Longitud, Catálogo | H15: OBJETIVO
A16: =+A15+1 -> 10 | B16: NUM_TIT_OP | C16: NUMERO | D16: 9 | E16: OPTO-SIII | F16: Número de títulos opcionales colocados o adquiridos | G16: Longitud
A17: =+A16+1 -> 11 | B17: PRIMA | C17: NUMERO | D17: 15 | E17: OPTO-SIII | F17: Importe de la prima (total) | G17: Entero, Longitud
A18: =+A17+1 -> 12 | B18: MDAPRIMA | C18: NUMERO | D18: 3 | E18: OPTO-SIII, RCS | F18: Moneda en que esta expresada la prima | G18: Longitud, Catálogo | H18: Moneda ISO
A19: =+A18+1 -> 13 | B19: BROKER | C19: NUMERO | D19: 2 | E19: OPTO-SIII | F19: Plataforma de negociación | G19: Longitud, Catálogo | H19: NEG_PLAT
A20: =+A19+1 -> 14 | B20: SOCIO_LIQ | C20: TEXTO | D20: 6 | E20: OPTO-SIII | F20: Socio liquidador de la operación | G20: Longitud, Catálogo | H20: BROKER
A21: =+A20+1 -> 15 | B21: CAM_COM | C21: NUMERO | D21: 2 | E21: OPTO-SIII | F21: Cámara de compensación o repositorio de derivados | G21: Longitud, Catálogo | H21: CAM_COMP
A22: =+A21+1 -> 16 | B22: NUM_CONF | C22: TEXTO | D22: 20 | E22: OPTO-SIII | F22: Clave de confirmación de la operación | G22: Longitud
A23: =+A22+1 -> 17 | B23: DELTA | C23: NUMERO | D23: 3,2 | E23: OPTO-SIII | F23: Valor del parámetro delta | G23: Longitud
A24: =+A23+1 -> 18 | B24: NUM_ID | C24: TEXTO | D24: 34 | E24: OPTO-SIII-SV, RCS | F24: Número de identificación de la operación | G24: Longitud, Repetido | I24: Llave
A25: =+A24+1 -> 19 | B25: NUM_ID_OPC | C25: TEXTO | D25: 34 | E25: OPTO-SIII | F25: Número de identificacion de la opción de cobertura | G25: Longitud
A26: =+A25+1 -> 20 | B26: FECVEN_CA | C26: FECHA | D26: AAAA/MM/DD | E26: OPTO-SIV | F26: Fecha de vencimiento anticipado | G26: Fecha
A27: =+A26+1 -> 21 | B27: FECLIQ_CA | C27: FECHA | D27: AAAA/MM/DD | E27: OPTO-SIV | F27: Fecha de liquidación anticipada | G27: Fecha
A28: =+A27+1 -> 22 | B28: LIQUIDA_CA | C28: TEXTO | D28: 1 | E28: OPTO-SIV | F28: Forma de liquidación anticipada
A29: =+A28+1 -> 23 | B29: IMP_VEN | C29: NUMERO | D29: 15 | E29: OPTO-SIV | F29: Importe por el vencimiento anticipado o cesión de derechos | G29: Entero, Longitud
A30: =+A29+1 -> 24 | B30: MDA_VEN | C30: NUMERO | D30: 3 | E30: OPTO-SIV | F30: Moneda del importe por vencimiento anticipado o cesión de derechos | G30: Longitud, Catálogo | H30: Moneda ISO
A31: =+A30+1 -> 25 | B31: VEN_PAR | C31: NUMERO | D31: 15 | E31: OPTO-SIV | F31: Importe por vencimiento anticipado parcial | G31: Entero, Longitud
A32: =+A31+1 -> 26 | B32: PAG_VEN_A | C32: TEXTO | D32: 1 | E32: OPTO-SIV | F32: La institución pagó o recibió el importe del vencimiento anticipado o cesión de derechos | G32: Longitud
A33: =+A32+1 -> 27 | B33: MOT_VENA | C33: NUMERO | D33: 1 | E33: OPTO-SIV | F33: Motivo del vencimiento anticipado o cesión de derechos | G33: Longitud, Catálogo | H33: MOT_VENA
A34: =+A33+1 -> 28 | B34: VEN_ANT | C34: TEXTO | D34: 2 | E34: OPTO-SIV | F34: Indicador del vencimiento anticipado o cesión de derechos | G34: Longitud
A35: =+A34+1 -> 29 | B35: NUM_ID_CP | C35: TEXTO | D35: 34 | E35: OPTO-SIV | F35: Número de identificacion de la nueva operación | G35: Longitud
A36: =+A35+1 -> 30 | B36: FE_EJE | C36: FECHA | D36: AAAA/MM/DD | E36: OPTO-SV | F36: Fecha de ejercicio de la operación | G36: Fecha
A37: =+A36+1 -> 31 | B37: PRECIOEJER | C37: NUMERO | D37: 13,6 | E37: OPTO-SV | F37: Precio unitario o tasa de ejercicio | G37: Decimal
A38: =+A37+1 -> 32 | B38: IMP_EJE_OP | C38: NUMERO | D38: 15 | E38: OPTO-SV | F38: Importe ejercido en la operación | G38: Entero, Longitud
A39: =+A38+1 -> 33 | B39: MDA_EJE_OP | C39: NUMERO | D39: 3 | E39: OPTO-SV | F39: Moneda del importe ejercido en la operación | G39: Longitud, Catálogo | H39: Moneda ISO
A40: =+A39+1 -> 34 | B40: MODIFICA | C40: TEXTO | D40: 5 | E40: OPTO-SIII-SIV-SV | F40: Modifica | G40: Longitud
A41: =+A40+1 -> 35 | B41: TIP_OPC | C41: TEXTO | D41: 1 | E41: RCS | F41: Tipo de opción | G41: Longitud
A42: =+A41+1 -> 36 | B42: NU_TO_EJE | C42: NUMERO | D42: 3 | E42: RCS | F42: Número total de posibles ejercicios | G42: Entero, Longitud
A43: =+A42+1 -> 37 | B43: TIP_DER | C43: TEXTO | D43: 2 | E43: RCS | F43: Tipo de producto derivado | G43: Longitud, Catálogo | H43: TIP_DER
A44: =+A43+1 -> 38 | B44: PRECIO_SUBY | C44: NUMERO | D44: 18,13 | E44: OPTO-SV | F44: VALOR DEL SUBYACENTE PARA EL EJERCICIO
A45: =+A44+1 -> 39 | B45: IMP_EJE_PAR | C45: NUMERO | D45: 22,8 | E45: OPTO-SV | F45: IMPORTE EJERCIDO PARCIAL
A46: =+A45+1 -> 40 | B46: FECHAINFO | C46: FECHA | D46: AAAA/MM/DD | F46: Fecha a la que corresponde la información | G46: =PROPER(Table24571011[[#This Row],[Descripcion]]) -> Fecha A La Que Corresponde La Información

Sheet OPTO_II_COM
A1: Nombre Archivo | B1: FILE_OPTO_II_COM.csv
A2: Separador de Datos | B2: PIPE "|"
A3: Descripcion | B3: LAYOUT DE DATOS OPTO PAQUETES DE OPCIONES
A4: Uso | B4: Formulario COMPLEMENTO DE LA SECCION II
B5: LAYOUT RELATIVO A LAS OPERACIONES DE OPCIONES (Paquetes de opciones "Caplets, Florlets")
A6: Orden | B6: Nombre | C6: Tipo | D6: Longitud | E6: Uso | F6: Descripcion | G6: Validacion | H6: Catalogo | I6: Comentario BW
A7: 1 | B7: CONT | C7: TEXTO | D7: 6 | E7: OPTO-SII-COMP | F7: Clave de la contraparte | G7: Longitud, Catálogo | H7: CONTRAPARTE
A8: 2 | B8: FECHA | C8: FECHA | D8: AAAA/MM/DD | E8: OPTO-SII-COMP | F8: Fecha de concertación | G8: Fecha
A9: 3 | B9: NU_ID | C9: TEXTO | D9: 34 | E9: OPTO-SII-COMP | F9: Número de identificación de la operación | G9: Longitud, Repetido | I9: Llave para unir (SII)
A10: 4 | B10: NU_PE_EJE | C10: NUMERO | D10: 3 | E10: OPTO-SII-COMP | F10: Número del periodo de ejercicio | G10: Longitud
A11: 5 | B11: IMPBA_CO | C11: NUMERO | D11: 15 | E11: OPTO-SII-COMP | F11: Importe base aplicable al periodo de ejercicio | G11: Entero, Longitud
A12: 6 | B12: FEINOP_CO | C12: FECHA | D12: AAAA/MM/DD | E12: OPTO-SII-COMP | F12: Fecha de inicio del periodo de ejercicio | G12: Fecha
A13: 7 | B13: FEVEOP_CO | C13: FECHA | D13: AAAA/MM/DD | E13: OPTO-SII-COMP | F13: Fecha de término del período de ejercicio | G13: Fecha
A14: 8 | B14: SUBY_CO | C14: TEXTO | D14: 3 | E14: OPTO-SII-COMP | F14: Tipo de subyacente | G14: Longitud, Catálogo | H14: SUBY
A15: 9 | B15: CVE_TIT_C | C15: TEXTO | D15: 20 | E15: OPTO-SII-COMP | F15: Clave del valor, indice accionario, tasa de interés o tipo de cambio | G15: Longitud, Catálogo | H15: CVE_TIT
A16: 10 | B16: PRECIOEJER_C | C16: NUMERO | D16: 13,6 | E16: OPTO-SII-COMP | F16: Precio unitario o tasa de ejercicio | G16: Decimal
A17: 11 | B17: FECHAINFO | C17: FECHA | D17: AAAA/MM/DD | F17: Fecha a la que corresponde la información | G17: Fecha A La Que Corresponde La Información

Sheet OPTO_MEREC_CONVO
A1: Nombre Archivo | B1: FILE_OPTO_MEREC_CONVO.csv
A2: Separador de Datos | B2: PIPE "|"
A3: Descripcion | B3: LAYOUT DE DATOS Convalidacion OPCIONES Mercados Reconocidos
A4: Uso | B4: Formulario OPCIONES Convalidacion Mercados Reconocidos
B5: LAYOUT RELATIVO A LAS OPERACIONES DE OPCIONES Convalidacion Mercados Reconocidos
A6: Orden | B6: Nombre | C6: Tipo | D6: Longitud | E6: Uso | F6: Descripcion | G6: Validacion | H6: Catalogo | I6: Comentario BW
A7: 1 | B7: CLIENTE | C7: TEXTO | D7: 6 | E7: OPTO-SVI | F7: Clave del cliente | G7: Longitud, Catálogo | H7: CONTRAPARTE
A8: 2 | B8: POSICION | C8: TEXTO | D8: 1 | E8: OPTO-SVI | F8: Posición por pizarra | G8: Longitud
A9: 3 | B9: PIZARRA | C9: TEXTO | D9: 20 | E9: OPTO-SVI | F9: Clave de pizarra | G9: Longitud, Catálogo | H9: =CATALOGOS!A1110 -> PIZARRA
A10: 4 | B10: SOCIO_LIQ | C10: TEXTO | D10: 6 | E10: OPTO-SVI | F10: Socio liquidador | G10: Longitud, Catálogo | H10: BROKER
A11: 5 | B11: CONTRAT_VIG | C11: NUMERO | D11: 6 | E11: OPTO-SVI | F11: Número de contratos vigentes (abiertos) en posición. | G11: Longitud
A12: 6 | B12: PAQ_OPC | C12: TEXTO | D12: 1 | E12: OPTO-SVI | F12: La posición es parte de un "paquete", conforme a la c.u.b. o la c.u.c.b. | G12: Longitud
A13: 7 | B13: VOL_IMPLIC | C13: NUMERO | D13: 5,2 | E13: OPTO-SVI | F13: Valor de la volatilidad implícita | G13: Decimal
A14: 8 | B14: DELTA_OPC | C14: NUMERO | D14: 5,2 | E14: OPTO-SVI | F14: Valor del parámetro delta | G14: Decimal
A15: 9 | B15: PRI_ACT | C15: NUMERO | D15: 15 | E15: OPTO-SVI | F15: Importe actualizado (mercado) de la prima (total) | G15: Entero, Longitud
A16: 10 | B16: ID_GAR_VIG | C16: TEXTO | D16: 20 | E16: OPTO-SVI | F16: Clave o folio para identificar el contrato que garantiza la posición | G16: Longitud
A17: 11 | B17: NUM_ID | C17: TEXTO | D17: 34 | F17: Número de identificación de la operación | G17: Longitud, Repetido | I17: Para relacionarlo a la operacion concertada
A18: 12 | B18: FECHAINFO | C18: FECHA | D18: AAAA/MM/DD | F18: Fecha a la que corresponde la información | G18: Fecha A La Que Corresponde La Información

Sheet OPTO_CONVO
A1: Nombre Archivo | B1: FILE_OPTO_CONVO.csv
A2: Separador de Datos | B2: PIPE "|"
A3: Descripcion | B3: LAYOUT DE DATOS OPCIONES en mercados no reconocidos
A4: Uso | B4: Formulario opciones en mercados no reconocidos
B5: LAYOUT RELATIVO A LAS OPERACIONES DE OPCIONES (Mercados no reconocidos)
A6: Orden | B6: Nombre | C6: Tipo | D6: Longitud | E6: Uso | F6: Descripcion | G6: Validacion | H6: Catalogo | I6: Comentario BW
A7: 1 | B7: NUM_ID | C7: TEXTO | D7: 34 | E7: OPTO-SVII | F7: Número de identificación de la operación | G7: Longitud, Repetido
A8: 2 | B8: VOL_IMPLIC | C8: NUMERO | D8: 5,2 | E8: OPTO-SVII | F8: Valor de la volatilidad implícita | G8: Decimal
A9: 3 | B9: DELTA_OPC | C9: NUMERO | D9: 3,2 | E9: OPTO-SVII, RCS | F9: Valor del parámetro delta | G9: Decimal
A10: 4 | B10: PAQ_OPC | C10: TEXTO | D10: 1 | E10: OPTO-SVII | F10: La operación es parte de un "paquete", conforme a la c.u.b. o la c.u.c.b. | G10: Longitud
A11: 5 | B11: ID_PAQ | C11: TEXTO | D11: 20 | E11: OPTO-SVII | F11: Clave o folio del conjunto de operaciones que forman parte de un " paquete " | G11: Longitud
A12: 6 | B12: CONSEC_PAQ | C12: NUMERO | D12: 3 | E12: OPTO-SVII | F12: Número consecutivo para identificar a la operación que forma parte de un " paquete" | G12: Longitud
A13: 7 | B13: PRI_ACT | C13: NUMERO | D13: 15 | E13: OPTO-SVII | F13: Importe actualizado (mercado) de la prima (total) | G13: Entero, Longitud
A14: 8 | B14: ID_GAR_VIG | C14: TEXTO | D14: 20 | E14: OPTO-SVII | F14: Clave o folio para identificar el contrato que garantiza la operación | G14: Longitud
A15: 9 | B15: FECHAINFO | C15: FECHA | D15: AAAA/MM/DD | F15: Fecha a la que corresponde la información

Sheet OPTO_OPC_TIT_CONVO
A1: Nombre Archivo | B1: FILE_OPTO_VIII_CONVO.csv
A2: Separador de Datos | B2: PIPE "|"
A3: Descripcion | B3: LAYOUT DE DATOS OPCIONES CON TITULOS OPCIONALES
A4: Uso | B4: Formulario opciones con títulos opcionales
B5: LAYOUT RELATIVO A LAS OPERACIONES DE OPCIONES (Warrants)
A6: Orden | B6: Nombre | C6: Tipo | D6: Longitud | E6: Uso | F6: Descripcion | G6: Validacion | H6: Catalogo | I6: Comentario BW
A7: 1 | B7: CLIENTE | C7: TEXTO | D7: 6 | F7: Clave del cliente | G7: Longitud, Catálogo | H7: CONTRAPARTE
A8: 2 | B8: NUM_TIT_PV | C8: NUMERO | D8: 6 | F8: Número de títulos opcionales en posición | G8: Longitud
A9: 3 | B9: VAL_MDO | C9: NUMERO | D9: 15 | F9: Valor de mercado de los títulos opcionales en posición | G9: Longitud
A10: 4 | B10: VOL_IMPLIC | C10: NUMERO | D10: 5,2 | F10: Valor de la volatilidad implícita | G10: Decimal
A11: 5 | B11: DELTA_OPC | C11: NUMERO | D11: 3,2 | E11: RCS | F11: Valor del parámetro delta | G11: Decimal
A12: 6 | B12: PRI_ACT | C12: NUMERO | D12: 15 | F12: Importe actualizado de la prima (total) | G12: Entero, Longitud
A13: 7 | B13: NUM_ID | C13: TEXTO | D13: 34 | E13: RCS | F13: Número de identificación de la operación | G13: Longitud, Repetido | I13: Llave para unir reportes(SIII, SVIII)
A14: 8 | B14: NOCIONAL | C14: NUMERO | D14: 15 | E14: RCS | F14: NOCIONAL | G14: Entero
A15: 9 | B15: MON_NOCIONAL | C15: TEXTO | D15: 3 | E15: RCS | F15: Moneda NOCIONAL | G15: Longitud, Catalogo | H15: MONEDA
A16: 10 | B16: FECHAINFO | C16: FECHA | D16: AAAA/MM/DD | F16: Fecha a la que corresponde la información | G16: Fecha A La Que Corresponde La Información

Sheet OPTO IX
A1: Nombre Archivo | B1: FILE_OPTO_IX.csv
A2: Separador de Datos | B2: PIPE "|"
A3: Descripcion | B3: LAYOUT DE DATOS OPTO CON ESTRUCTURAS EXOTICAS
A4: Uso | B4: Formulario OPTO IX
B5: LAYOUT RELATIVO A LAS OPERACIONES DE OPTO IX (Mercados Reconocidos)
A6: Orden | B6: Nombre | C6: Tipo | D6: Longitud | E6: Uso | F6: Descripcion | G6: Validacion | H6: Catalogo | I6: Comentario BW
A7: 1 | B7: OFICINA | C7: TEXTO | D7: 1 | E7: OPTO-SIX | F7: OFICINA QUE REALIZA LA OPERACIÓN | G7: Longitud, Catálogo | H7: =CATALOGOS!A$1099 -> OFICINA
A8: =+A7+1 -> 2 | B8: LEI | C8: TEXTO | D8: 20 | E8: OPTO-SIX | F8: CÓDIGO LEI (DENOMINADO EN INGLÉS | G8: Longitud, Catálogo | H8: LEI
A9: =+A8+1 -> 3 | B9: CONTRAPAR | C9: TEXTO | D9: 20 | E9: OPTO-SIX | F9: CLAVE DE LA CONTRAPARTE | G9: Longitud, Catálogo
A10: =+A9+1 -> 4 | B10: FE_CON_OPE | C10: FECHA | D10: AAAA/MM/DD | E10: OPTO-SIX | F10: FECHA DE CONCERTACIÓN | G10: Fecha
A11: =+A10+1 -> 5 | B11: FE_INI_OPE | C11: FECHA | D11: AAAA/MM/DD | E11: OPTO-SIX | F11: FECHA DE INICIO DEL PERÍODO DE EJERCICIO | G11: Fecha
A12: =+A11+1 -> 6 | B12: FE_VEN_OPE | C12: FECHA | D12: AAAA/MM/DD | E12: OPTO-SIX | F12: FECHA DE TÉRMINO DEL PERÍODO DE | G12: Fecha
A13: =+A12+1 -> 7 | B13: OTRO_DER | C13: NUMÉRICO | D13: (2,0) | E13: OPTO-SIX | F13: OTRO TIPO DE DERIVADO VINCULADO AL CONJUNTO DE OPCIONES | G13: Longitud, Catálogo | H13: ANEXO AJ
A14: =+A13+1 -> 8 | B14: DIASLIQ | C14: NUMÉRICO | D14: (2,0) | E14: OPTO-SIX | F14: NÚMERO DE DÍAS HÁBILES PARA LIQUIDAR LA OPERACIÓN | G14: Longitud
A15: =+A14+1 -> 9 | B15: POSICION | C15: TEXTO | D15: 1 | E15: OPTO-SIX | F15: POSICIÓN EN LA OPERACIÓN | G15: Longitud
A16: =+A15+1 -> 10 | B16: TIP_OPC | C16: TEXTO | D16: 2 | E16: OPTO-SIX | F16: TIPO DE OPCIÓN | G16: Longitud
A17: =+A16+1 -> 11 | B17: TIP_OPC2 | C17: TEXTO | D17: 2 | E17: OPTO-SIX | F17: TIPO DE OPCIÓN DOS | G17: Longitud
A18: =+A17+1 -> 12 | B18: OPC_EJER | C18: TEXTO | D18: 1 | E18: OPTO-SIX | F18: MODALIDAD DEL EJERCICIO | G18: Longitud
A19: =+A18+1 -> 13 | B19: OBJETIVO | C19: TEXTO | D19: 2 | E19: OPTO-SIX | F19: OBJETIVO DE LA OPERACIÓN | G19: Longitud, Catálogo | H19: OBJETIVO
A20: =+A19+1 -> 14 | B20: IMPBASE | C20: NUMÉRICO | D20: (22,8) | E20: OPTO-SIX | F20: IMPORTE BASE O DE REFERENCIA | G20: Entero, Longitud
A21: =+A20+1 -> 15 | B21: MDAIMP | C21: NUMÉRICO | D21: (3,0) | E21: OPTO-SIX | F21: MONEDA DEL IMPORTE BASE O DE REFERENCIA | G21: Longitud, Catálogo | H21: Moneda ISO
A22: =+A21+1 -> 16 | B22: LIQUIDA | C22: TEXTO | D22: 1 | E22: OPTO-SIX | F22: FORMA DE LIQUIDACIÓN | G22: Longitud
A23: =+A22+1 -> 17 | B23: MDALIQUIDA | C23: NUMÉRICO | D23: (3,0) | E23: OPTO-SIX | F23: MONEDA DE LIQUIDACIÓN | G23: Longitud, Catálogo | H23: Moneda ISO
A24: =+A23+1 -> 18 | B24: FE_FLU | C24: FECHA | D24: AAAA/MM/DD | E24: OPTO-SIX | F24: FECHA DE INICIO DEL PRIMER FLUJO A RECIBIR O ENTREGAR | G24: Fecha
A25: =+A24+1 -> 19 | B25: FEN_FLU | C25: FECHA | D25: AAAA/MM/DD | E25: OPTO-SIX | F25: FECHA DE VENCIMIENTO DEL ÚLTIMO FLUJO A RECIBIR O ENTREGAR | G25: Fecha
A26: =+A25+1 -> 20 | B26: DET_FLUJO | C26: TEXTO | D26: 2 | E26: OPTO-SIX | F26: ACUERDO DE DÍAS INHÁBILES PARA CÁLCULO DE LOS FLUJOS | G26: Longitud, Catálogo | H26: =CATALOGOS!A2512 -> DIAS_INHABILES
A27: =+A26+1 -> 21 | B27: NU_FLUJO | C27: NUMÉRICO | D27: (3,0) | E27: OPTO-SIX | F27: NÚMERO TOTAL DE FLUJOS A RECIBIR O ENTREGAR | G27: Longitud
A28: =+A27+1 -> 22 | B28: INT_FLUJO | C28: NUMÉRICO | D28: (3,0) | E28: OPTO-SIX | F28: INTERVALO DEL FLUJO A RECIBIR O ENTREGAR | G28: Longitud
A29: =+A28+1 -> 23 | B29: TASA_REF | C29: TEXTO | D29: 20 | E29: OPTO-SIX | F29: TASA DE REFERENCIA PARA DETERMINAR LA TASA VARIABLE A RECIBIR O ENTREGAR | G29: Longitud, Catálogo | H29: ANEXO AF
A30: =+A29+1 -> 24 | B30: REV_TREF | C30: NUMÉRICO | D30: (3,0) | E30: OPTO-SIX | F30: INTERVALO DE REVISIÓN DE LA TASA DE | G30: Longitud
A31: =+A30+1 -> 25 | B31: ANIO | C31: CARÁCTER | D31: 1 | E31: OPTO-SIX | F31: AÑO COMERCIAL O AÑO NATURAL (RECIBIR O ENTREGAR) | G31: Longitud
A32: =+A31+1 -> 26 | B32: FE_REF | C32: CARÁCTER | D32: 3 | E32: OPTO-SIX | F32: MODALIDAD DE LA TASA DE REFERENCIA, | G32: Longitud, Catálogo | H32: =CATALOGOS!A2525 -> MOD_TASA
A33: =+A32+1 -> 27 | B33: FAC_TASA | C33: NUMÉRICO | D33: (3,6) | E33: OPTO-SIX | F33: FACTOR APLICABLE A LA TASA DE | G33: Longitud
A34: =+A33+1 -> 28 | B34: SPREAD | C34: NUMÉRICO | D34: (3,6) | E34: OPTO-SIX | F34: PUNTOS PORCENTUALES APLICABLES A LA | G34: Longitud
A35: =+A34+1 -> 29 | B35: TASA_FIJA | C35: NUMÉRICO | D35: (3,6) | E35: OPTO-SIX | F35: VALOR DE LA TASA FIJA A RECIBIR O ENTREGAR
A36: =+A35+1 -> 30 | B36: CAL_LIQ | C36: NUMÉRICO | D36: (2,0) | E36: OPTO-SIX | F36: CÁLCULO DE LIQUIDACIÓN | G36: Longitud, Catálogo | H36: ANEXO AK
A37: =+A36+1 -> 31 | B37: CAL_LIQ2 | C37: NUMÉRICO | D37: (2,0) | E37: OPTO-SIX | F37: CÁLCULO DE LIQUIDACIÓN DOS | G37: Longitud, Catálogo | H37: ANEXO AK
A38: =+A37+1 -> 32 | B38: FAC_LIQ | C38: NUMÉRICO | D38: (3,6) | E38: OPTO-SIX | F38: FACTOR APLICADO A LA FORMA DE LIQUIDACIÓN | G38: Longitud
A39: =+A38+1 -> 33 | B39: DIF | C39: NUMÉRICO | D39: (3,6) | E39: OPTO-SIX | F39: DIFERENCIAL APLICADO A LA FORMA DE LIQUIDACIÓN | G39: Decimal
A40: =+A39+1 -> 34 | B40: FAC_LIQ2 | C40: NUMÉRICO | D40: (3,6) | E40: OPTO-SIX | F40: FACTOR APLICADO A LA FORMA DE LIQUIDACIÓN DOS | G40: Decimal
A41: =+A40+1 -> 35 | B41: DIF2 | C41: NUMÉRICO | D41: (3,6) | E41: OPTO-SIX | F41: DIFERENCIAL APLICADO A LA FORMA DE LIQUIDACIÓN DOS | G41: Decimal
A42: =+A41+1 -> 36 | B42: MMRIA_PAGO | C42: CARÁCTER | D42: 1 | E42: OPTO-SIX | F42: MEMORIA DEL PAGO | G42: Longitud
A43: =+A42+1 -> 37 | B43: CON_TERM | C43: NUMÉRICO | D43: (2,0) | E43: OPTO-SIX | F43: CONDICIÓN DE TERMINACIÓN | G43: Longitud, Catálogo | H43: ANEXO AL
A44: =+A43+1 -> 38 | B44: N_CAN | C44: NUMÉRICO | D44: (2,0) | E44: OPTO-SIX | F44: NÚMERO DE OCURRENCIAS DE LA | G44: Longitud
A45: =+A44+1 -> 39 | B45: QUANTO | C45: CARACTER | D45: 1 | E45: OPTO-SIX | F45: EXISTENCIA DE TIPO DE CAMBIO FORWARD “QUANTO” | G45: Longitud
A46: =+A45+1 -> 40 | B46: TC_QUANT | C46: NUMÉRICO | D46: (13,6) | E46: OPTO-SIX | F46: TIPO DE CAMBIO FORWARD “QUANTO” | G46: Decimal
A47: =+A46+1 -> 41 | B47: PRIMA | C47: NUMÉRICO | D47: (22,8) | E47: OPTO-SIX | F47: IMPORTE DE LA PRIMA (TOTAL) | G47: Decimal
A48: =+A47+1 -> 42 | B48: MDAPRIMA | C48: NUMÉRICO | D48: (3,0) | E48: OPTO-SIX | F48: MONEDA EN QUE ESTA EXPRESADA LA PRIMA | G48: Longitud, Catálogo | H48: Moneda ISO
A49: =+A48+1 -> 43 | B49: FE_PRIM | C49: FECHA | D49: AAAA/MM/DD | E49: OPTO-SIX | F49: FECHA DE PAGO/COBRO DE LA PRIMA | G49: Fecha
A50: =+A49+1 -> 44 | B50: PAQ_EST | C50: NUMÉRICO | D50: (2,0) | E50: OPTO-SIX | F50: LA OPERACIÓN ES PARTE DE UNA | G50: Longitud, Catálogo | H50: =CATALOGOS!A2470 -> PAQ_ESTRUCT
A51: =+A50+1 -> 45 | B51: ID_PAQ_EST | C51: TEXTO | D51: 35 | E51: OPTO-SIX | F51: CLAVE O FOLIO CON EL QUE SE IDENTIFICA AL CONJUNTO DE OPERACIONES QUE | G51: Longitud
A52: =+A51+1 -> 46 | B52: CON_PAQ_EST | C52: NUMÉRICO | D52: (3,0) | E52: OPTO-SIX | F52: NÚMERO CONSECUTIVO PARA | G52: Longitud
A53: =+A52+1 -> 47 | B53: TIP_DER | C53: CARÁCTER | D53: 2 | E53: OPTO-SIX | F53: TIPO DE PRODUCTO DERIVADO | G53: Longitud, Catálogo | H53: =CATALOGOS!A2231 -> TIP_DER
A54: =+A53+1 -> 48 | B54: SUBY | C54: CARÁCTER | D54: 3 | E54: OPTO-SIX | F54: TIPO DE SUBYACENTE | G54: Longitud, Catálogo | H54: =CATALOGOS!A$2094 -> SUBY
A55: =+A54+1 -> 49 | B55: CVE_TIT | C55: TEXTO | D55: 20 | E55: OPTO-SIX | F55: CLAVE DEL VALOR (DEUDA O ACCIÓN), | G55: Longitud, Catálogo | H55: =CATALOGOS!A$566 -> CVE_TIT
A56: =+A55+1 -> 50 | B56: INT_EJE | C56: NUMÉRICO | D56: (3,0) | E56: OPTO-SIX | F56: INTERVALO O FRECUENCIA DE LOS POSIBLES EJERCICIOS | G56: Longitud, Catálogo | H56: Moneda ISO
A57: =+A56+1 -> 51 | B57: INT_MON | C57: NUMÉRICO | D57: (3,0) | E57: OPTO-SIX | F57: INTERVALO O FRECUENCIA DE | G57: Longitud
A58: =+A57+1 -> 52 | B58: N_MONSUBY | C58: NUMÉRICO | D58: (3,0) | E58: OPTO-SIX | F58: NÚMERO DE DÍAS UTILIZADO PARA LA | G58: Longitud
A59: =+A58+1 -> 53 | B59: NU_TO_EJE | C59: NUMÉRICO | D59: (3,0) | E59: OPTO-SIX | F59: NÚMERO TOTAL DE POSIBLES EJERCICIOS | G59: Longitud
A60: =+A59+1 -> 54 | B60: NUM_ID_OP_SBY | C60: TEXTO | D60: 34 | E60: OPTO-SIX | F60: NÚMERO DE IDENTIFICACIÓN DE LA | G60: Longitud
A61: =+A60+1 -> 55 | B61: SECCION_SWP | C61: NUMÉRICO | D61: 1 | E61: OPTO-SIX | F61: SECCIÓN DEL FORMULARIO SWAPS A LA QUE PERTENECE LA OPERACIÓN SWAP | G61: Longitud
A62: =+A61+1 -> 56 | B62: NUMSUBY | C62: NUMÉRICO | D62: (9,0) | E62: OPTO-SIX | F62: NÚMERO DE UNIDADES DEL SUBYACENTE | G62: Longitud
A63: =+A62+1 -> 57 | B63: MDASUBY | C63: NUMÉRICO | D63: (3,0) | E63: OPTO-SIX | F63: MONEDA DEL SUBYACENTE | G63: Longitud, Catálogo | H63: Moneda ISO
A64: =+A63+1 -> 58 | B64: PRECIOEJER | C64: NUMÉRICO | D64: (18,13) | E64: OPTO-SIX | F64: PRECIO UNITARIO O TASA DE EJERCICIO | G64: Decimal
A65: =+A64+1 -> 59 | B65: TIP_PRECIO | C65: NUMÉRICO | D65: (2,0) | E65: OPTO-SIX | F65: FORMA EN LA QUE ESTÁ REPRESENTADO EL PRECIO DE EJERCICIO | G65: Longitud, Catálogo | H65: ANEXO AM
A66: =+A65+1 -> 60 | B66: MDAPRECIO | C66: NUMÉRICO | D66: (3,0) | E66: OPTO-SIX | F66: MONEDA DEL PRECIO UNITARIO O TASA DE EJERCICIO | G66: Longitud, Catálogo | H66: Moneda ISO
A67: =+A66+1 -> 61 | B67: CAL_EJERCICIO | C67: NUMÉRICO | D67: (2,0) | E67: OPTO-SIX | F67: CÁLCULO PARA DERTERMINAR EL NIVEL | G67: Longitud, Catálogo | H67: ANEXO AN
A68: =+A67+1 -> 62 | B68: N_EJERCICIO | C68: NUMÉRICO | D68: (3,0) | E68: OPTO-SIX | F68: NÚMERO DE DÍAS UTILIZADO PARA LA | G68: Longitud
A69: =+A68+1 -> 63 | B69: PRECIOEJER2 | C69: NUMÉRICO | D69: (18,13) | E69: OPTO-SIX | F69: PRECIO UNITARIO O TASA DE EJERCICIO DOS | G69: Decimal
A70: =+A69+1 -> 64 | B70: TIP_PRECIO2 | C70: NUMÉRICO | D70: (2,0) | E70: OPTO-SIX | F70: FORMA EN LA QUE ESTÁ REPRESENTADO EL PRECIO DE EJERCICIO DOS | G70: Longitud, Catálogo | H70: ANEXO AM
A71: =+A70+1 -> 65 | B71: MDAPRECIO2 | C71: NUMÉRICO | D71: (3,0) | E71: OPTO-SIX | F71: MONEDA DEL PRECIO UNITARIO O TASA DE EJERCICIO | G71: Longitud, Catálogo | H71: Moneda ISO
A72: =+A71+1 -> 66 | B72: CAL_EJERCICIO2 | C72: NUMÉRICO | D72: (2,0) | E72: OPTO-SIX | F72: CÁLCULO PARA ESTABLECER EL EJERCICIO DE LA OPCIÓN DOS | G72: Longitud, Catálogo | H72: ANEXO AN
A73: =+A72+1 -> 67 | B73: N_EJERCICIO2 | C73: NUMÉRICO | D73: (3,0) | E73: OPTO-SIX | F73: NÚMERO DE DÍAS UTILIZADO PARA LA | G73: Longitud
A74: =+A73+1 -> 68 | B74: PRECIO_INICIAL | C74: NUMÉRICO | D74: (18,13) | E74: OPTO-SIX | F74: PRECIO INICIAL DEL SUBYACENTE | G74: Decimal
A75: =+A74+1 -> 69 | B75: PRE_SUP | C75: NUMÉRICO | D75: (18,13) | E75: OPTO-SIX | F75: PRECIO DE LA BARRERA SUPERIOR | G75: Decimal
A76: =+A75+1 -> 70 | B76: PRE_INF | C76: NUMÉRICO | D76: (18,13) | E76: OPTO-SIX | F76: PRECIO DE LA BARRERA INFERIOR | G76: Decimal
A77: =+A76+1 -> 71 | B77: MOD_PRE | C77: CARÁCTER | D77: 6 | E77: OPTO-SIX | F77: MODALIDAD DEL PRECIO BARRERA | G77: Longitud, Catálogo | H77: ANEXO AO
A78: =+A77+1 -> 72 | B78: INT_MON_BA | C78: NUMÉRICO | D78: (3,0) | E78: OPTO-SIX | F78: INTERVALO O FRECUENCIA DEL | G78: Longitud
A79: =+A78+1 -> 73 | B79: FE_INI_VEN | C79: FECHA | D79: AAAA/MM/DD | E79: OPTO-SIX | F79: FECHA DE INICIO DEL PERIODO DE LA VENTANA DE LA BARRERA | G79: Fecha
A80: =+A79+1 -> 74 | B80: FE_VEN_VEN | C80: FECHA | D80: AAAA/MM/DD | E80: OPTO-SIX | F80: FECHA DE TÉRMINO DEL PERIODO DE LA VENTANA DE LA BARRERA | G80: Fecha
A81: =+A80+1 -> 75 | B81: PRE_SUP2 | C81: NUMÉRICO | D81: (18,13) | E81: OPTO-SIX | F81: PRECIO DE LA BARRERA SUPERIOR DOS | G81: Decimal
A82: =+A81+1 -> 76 | B82: PRE_INF2 | C82: NUMÉRICO | D82: (18,13) | E82: OPTO-SIX | F82: PRECIO DE LA BARRERA INFERIOR DOS | G82: Decimal
A83: =+A82+1 -> 77 | B83: MOD_PRE2 | C83: CARÁCTER | D83: 6 | E83: OPTO-SIX | F83: MODALIDAD DEL PRECIO BARRERA DOS | G83: Longitud, Catálogo | H83: ANEXO AO
A84: =+A83+1 -> 78 | B84: INT_MON_BA2 | C84: NUMÉRICO | D84: (3,0) | E84: OPTO-SIX | F84: INTERVALO O FRECUENCIA DEL | G84: Longitud
A85: =+A84+1 -> 79 | B85: FE_INI_VEN2 | C85: FECHA | D85: AAAA/MM/DD | E85: OPTO-SIX | F85: FECHA DE INICIO DEL PERIODO DE LA VENTANA DE LA BARRERA DOS | G85: Fecha
A86: =+A85+1 -> 80 | B86: FE_VEN_VEN2 | C86: FECHA | D86: AAAA/MM/DD | E86: OPTO-SIX | F86: FECHA DE TÉRMINO DEL PERIODO DE LA VENTANA DE LA BARRERA DOS | G86: Fecha
A87: =+A86+1 -> 81 | B87: REBATE | C87: NUMÉRICO | D87: (3,6) | E87: OPTO-SIX | F87: REBATE | G87: Decimal
A88: =+A87+1 -> 82 | B88: CALLABLE | C88: CARÁCTER | D88: 2 | E88: OPTO-SIX | F88: CALLABLE | G88: Longitud
A89: =+A88+1 -> 83 | B89: REV_OP | C89: CARÁCTER | D89: 1 | E89: OPTO-SIX | F89: REVISIÓN DE LOS "PARÁMETROS PRINCIPALES" | G89: Longitud
A90: =+A89+1 -> 84 | B90: BROKER | C90: NUMÉRICO | D90: (2,0) | E90: OPTO-SIX | F90: PLATAFORMA DE NEGOCIACIÓN | G90: Longitud, Catálogo | H90: =CATALOGOS!A$6 -> BROKER
A91: =+A90+1 -> 85 | B91: SOCIO_LIQ | C91: CARACTER | D91: 6 | E91: OPTO-SIX | F91: SOCIO LIQUIDADOR DE LA OPERACIÓN | G91: Longitud, Catálogo | H91: =CATALOGOS!A$6 -> BROKER
A92: =+A91+1 -> 86 | B92: CAM_COM | C92: NUMÉRICO | D92: (2,0) | E92: OPTO-SIX | F92: CÁMARA DE COMPENSACIÓN | G92: Longitud, Catálogo | H92: CAM_COMP
A93: =+A92+1 -> 87 | B93: REP_DEV | C93: NUMÉRICO | D93: (2,0) | E93: OPTO-SIX | F93: REPOSITORIO DE DERIVADOS | G93: Longitud, Catálogo
A94: =+A93+1 -> 88 | B94: AG_CAL | C94: CARACTER | D94: 6 | E94: OPTO-SIX | F94: AGENTE DE CÁLCULO Y LIQUIDACIÓN | G94: Longitud, Catálogo | H94: =CATALOGOS!#REF! -> #REF!
A95: =+A94+1 -> 89 | B95: UPI | C95: TEXTO | D95: 12 | E95: OPTO-SIX | F95: IDENTIFICADOR ÚNICO DEL PRODUCTO | G95: Longitud
A96: =+A95+1 -> 90 | B96: DELTA | C96: NUMÉRICO | D96: (22,8) | E96: OPTO-SIX | F96: VALOR DEL PARÁMETRO DELTA | G96: Decimal
A97: =+A96+1 -> 91 | B97: VOL | C97: NUMÉRICO | D97: (3,6) | E97: OPTO-SIX | F97: VOLATILIDAD IMPLÍCITA | G97: Decimal
A98: =+A97+1 -> 92 | B98: ID_CONT_ANF | C98: TEXTO | D98: 34 | E98: OPTO-SIX | F98: IDENTIFICACIÓN DEL CONTRATO ANFITRIÓN | G98: Longitud
A99: =+A98+1 -> 93 | B99: NUM_ID_INST | C99: TEXTO | D99: 52 | E99: OPTO-SIX | F99: NÚMERO DE IDENTIFICACIÓN DE LA | G99: Longitud
A100: =+A99+1 -> 94 | B100: NUM_ID | C100: TEXTO | D100: 52 | E100: OPTO-SIX | F100: NÚMERO DE IDENTIFICACIÓN DE LA OPERACIÓN | G100: Longitud, Repetido | I100: Llave para unir reportes (SIX, SIXC, SX)
...

Sheet OPTO_IX_COM
A1: Nombre Archivo | B1: FILE_OPTO_IX_COM.csv
A2: Separador de Datos | B2: PIPE "|"
A3: Descripcion | B3: LAYOUT DE DATOS OPTO PAQUETE DE OPCIONES EXOTICAS
A4: Uso | B4: Formulario OPTO IX_COM
B5: LAYOUT RELATIVO A LOS PAQUETES DE OPCIONES EXOTICAS SIX COM (Mercados Reconocidos)
A6: Orden | B6: Nombre | C6: Tipo | D6: Longitud | E6: Uso | F6: Descripcion | G6: Validacion | H6: Catalogo | I6: Comentario BW
A7: 1 | B7: FECHA | C7: FECHA | D7: AAAA/MM/DD | E7: OPTO SIX COMP | F7: FECHA DE CONCERTACIÓN | G7: Fecha
A8: =+A7+1 -> 2 | B8: NUM_ID | C8: TEXTO | D8: 52 | E8: OPTO SIX COMP | F8: NÚMERO DE IDENTIFICACIÓN DE LA OPERACIÓN (UTI) | G8: Longitud, Repetido | I8: Llave para unir (SIX)
A9: =+A8+1 -> 3 | B9: NU_PE_EJE | C9: NUMÉRICO | D9: (3,0) | E9: OPTO SIX COMP | F9: NÚMERO DEL PERIODO DE EJERCICIO | G9: Longitud
A10: =+A9+1 -> 4 | B10: IMPBA_CO | C10: NUMÉRICO | D10: (22,8) | E10: OPTO SIX COMP | F10: IMPORTE BASE APLICABLE AL PERIODO DE EJERCICIO | G10: Decimal
A11: =+A10+1 -> 5 | B11: FEINOP_CO | C11: FECHA | D11: AAAA/MM/DD | E11: OPTO SIX COMP | F11: FECHA DE INICIO DEL PERÍODO DE EJERCICIO | G11: Fecha
A12: =+A11+1 -> 6 | B12: FEVEOP_CO | C12: FECHA | D12: AAAA/MM/DD | E12: OPTO SIX COMP | F12: FECHA DE TÉRMINO DEL PERÍODO DE EJERCICIO | G12: Fecha
A13: =+A12+1 -> 7 | B13: DIASLIQ | C13: NUMÉRICO | D13: (2,0) | E13: OPTO SIX COMP | F13: NÚMERO DE DÍAS HÁBILES PARA LIQUIDAR LA OPERACIÓN | G13: Longitud
A14: =+A13+1 -> 8 | B14: FAC_LIQ | C14: NUMÉRICO | D14: (3,6) | E14: OPTO SIX COMP | F14: FACTOR APLICADO A LA LIQUIDACIÓN | G14: Decimal
A15: =+A14+1 -> 9 | B15: DIF | C15: NUMÉRICO | D15: (3,6) | E15: OPTO SIX COMP | F15: DIFERENCIAL APLICADO A LA FORMA DE LIQUIDACIÓN | G15: Decimal
A16: =+A15+1 -> 10 | B16: MMRIA_PAGO | C16: TEXTO | D16: 1 | E16: OPTO SIX COMP | F16: MEMORIA DEL PAGO | G16: Longitud
A17: =+A16+1 -> 11 | B17: SUBY_CO | C17: TEXTO | D17: 3 | E17: OPTO SIX COMP | F17: TIPO DE SUBYACENTE | G17: Longitud, Catálogo | H17: ANEXO F
A18: =+A17+1 -> 12 | B18: CVE_TIT_C | C18: TEXTO | D18: 20 | E18: OPTO SIX COMP | F18: CLAVE DEL VALOR (DEUDA O ACCIÓN), | G18: Longitud, Catálogo | H18: ANEXO AF
A19: =+A18+1 -> 13 | B19: PRECIOEJER_C | C19: NUMÉRICO | D19: (18,13) | E19: OPTO SIX COMP | F19: PRECIO UNITARIO O TASA DE EJERCICIO | G19: Decimal
A20: =+A19+1 -> 14 | B20: PRE_SUP | C20: NUMÉRICO | D20: (18,13) | E20: OPTO SIX COMP | F20: PRECIO DE LA BARRERA SUPERIOR | G20: Decimal
A21: =+A20+1 -> 15 | B21: PRE_INF | C21: NUMÉRICO | D21: (18,13) | E21: OPTO SIX COMP | F21: PRECIO DE LA BARRERA INFERIOR | G21: Decimal
A22: =+A21+1 -> 16 | B22: MOD_PRE | C22: TEXTO | D22: 6 | E22: OPTO SIX COMP | F22: MODALIDAD DEL PRECIO BARRERA | G22: Longitud, Catálogo | H22: ANEXO AO
A23: =+A22+1 -> 17 | B23: FE_INI_VEN | C23: FECHA | D23: AAAA/MM/DD | E23: OPTO SIX COMP | F23: FECHA DE INICIO DEL PERIODO DE LA VENTANA DE LA BARRERA | G23: Fecha
A24: =+A23+1 -> 18 | B24: FE_VEN_VEN | C24: FECHA | D24: AAAA/MM/DD | E24: OPTO SIX COMP | F24: FECHA DE TÉRMINO DEL PERIODO DE LA VENTANA DE LA BARRERA | G24: Fecha
A25: =+A24+1 -> 19 | B25: PRECIOEJER_C2 | C25: NUMÉRICO | D25: (18,13) | E25: OPTO SIX COMP | F25: PRECIO UNITARIO O TASA DE EJERCICIO DOS | G25: Decimal
A26: =+A25+1 -> 20 | B26: PRE_SUP2 | C26: NUMÉRICO | D26: (18,13) | E26: OPTO SIX COMP | F26: PRECIO DE LA BARRERA SUPERIOR DOS | G26: Decimal
A27: =+A26+1 -> 21 | B27: PRE_INF2 | C27: NUMÉRICO | D27: (18,13) | E27: OPTO SIX COMP | F27: PRECIO DE LA BARRERA INFERIOR DOS | G27: Decimal
A28: =+A27+1 -> 22 | B28: MOD_PRE2 | C28: TEXTO | D28: 6 | E28: OPTO SIX COMP | F28: MODALIDAD DEL PRECIO BARRERA DOS | G28: Longitud, Catálogo | H28: ANEXO AO
A29: =+A28+1 -> 23 | B29: FE_INI_VEN2 | C29: FECHA | D29: AAAA/MM/DD | E29: OPTO SIX COMP | F29: FECHA DE INICIO DEL PERIODO DE LA VENTANA DE LA BARRERA DOS | G29: Fecha
A30: =+A29+1 -> 24 | B30: FE_VEN_VEN2 | C30: FECHA | D30: AAAA/MM/DD | E30: OPTO SIX COMP | F30: FECHA DE TÉRMINO DEL PERIODO DE LA VENTANA DE LA BARRERA DOS | G30: Fecha
A31: =+A30+1 -> 25 | B31: REBATE_C | C31: NUMÉRICO | D31: (3,6) | E31: OPTO SIX COMP | F31: REBATE | G31: Decimal
A32: =+A31+1 -> 26 | B32: CALLABLE | C32: TEXTO | D32: 2 | E32: OPTO SIX COMP | F32: CALLABLE | G32: Longitud
A33: =+A32+1 -> 27 | B33: FE_FLU | C33: FECHA | D33: AAAA/MM/DD | E33: OPTO SIX COMP | F33: FECHA DE INICIO DEL FLUJO A RECIBIR O ENTREGAR | G33: Fecha
A34: =+A33+1 -> 28 | B34: FEN_FLU | C34: FECHA | D34: AAAA/MM/DD | E34: OPTO SIX COMP | F34: FECHA DE VENCIMIENTO DEL FLUJO A RECIBIR O ENTREGAR | G34: Fecha
A35: =+A34+1 -> 29 | B35: FAC_TASA | C35: NUMÉRICO | D35: (3,6) | E35: OPTO SIX COMP | F35: FACTOR APLICABLE A LA TASA DE | G35: Decimal
A36: =+A35+1 -> 30 | B36: SPREAD | C36: NUMÉRICO | D36: (3,6) | E36: OPTO SIX COMP | F36: PUNTOS PORCENTUALES APLICABLES A LA | G36: Decimal
A37: =+A36+1 -> 31 | B37: TASA_FIJA | C37: NUMÉRICO | D37: (3,6) | E37: OPTO SIX COMP | F37: VALOR DE LA TASA FIJA A RECIBIR O ENTREGAR | G37: Decimal
A38: =+A37+1 -> 32 | B38: INST_LEI | C38: TEXTO | D38: 20 | E38: OPTO SIX COMP | F38: CÓDIGO LEI (DENOMINADO EN INGLÉS | G38: Longitud
A39: =+A38+1 -> 33 | B39: PRIMA | C39: NUMÉRICO | D39: (22,8) | E39: OPTO SIX COMP | F39: IMPORTE DE LA PRIMA | G39: Decimal
A40: =+A39+1 -> 34 | B40: FECHAINFO | C40: FECHA | D40: AAAA/MM/DD | F40: Fecha a la que corresponde la información
B42: UTI | C42: Modificar proceso

Sheet OPTO X
A1: Nombre Archivo | B1: FILE_OPTO_X.csv
A2: Separador de Datos | B2: PIPE "|"
A3: Descripcion | B3: LAYOUT DE DATOS OPTO CONVALIDACION DE OPERACIONES EXOTICAS
A4: Uso | B4: Formulario OPTO X
B5: LAYOUT RELATIVO A LA CONVALIDACION DE OPERACIONES EXOTICAS OPTO X (Mercados Reconocidos)
A6: Orden | B6: Nombre | C6: Tipo | D6: Longitud | E6: Uso | F6: Descripcion | G6: Validacion | H6: Catalogo | I6: Comentario BW
A7: 1 | B7: FE_CON_OPE | C7: FECHA | D7: AAAA/MM/DD | E7: OPTO SX | F7: FECHA DE CONCERTACIÓN | G7: Fecha
A8: 2 | B8: FE_CORTE | C8: FECHA | D8: AAAA/MM/DD | E8: OPTO SX | F8: FECHA DE CORTE | G8: Fecha
A9: 3 | B9: LEI | C9: TEXTO | D9: 20 | E9: OPTO SX | F9: CÓDIGO LEI (DENOMINADO EN INGLÉS | G9: Longitud, Catálogo | H9: LEI
A10: 4 | B10: NUM_ID | C10: TEXTO | D10: 52 | E10: OPTO SX | F10: NÚMERO DE IDENTIFICACIÓN DE LA OPERACIÓN | G10: Longitud, Repetido | I10: Llave para unir (SIX)
A11: 5 | B11: OBJ_OPE | C11: CARÁCTER | D11: 2 | E11: OPTO SX | F11: OBJETIVO DE LA OPERACIÓN | G11: Longitud, Catálogo | H11: OBJETIVO
A12: 6 | B12: NATURALEZA | C12: CARÁCTER | D12: 1 | E12: OPTO SX | F12: POSICIÓN DE LA OPERACIÓN | G12: Longitud
A13: 7 | B13: VOL_IMPLIC | C13: NUMÉRICO | D13: (3,6) | E13: OPTO SX | F13: VALOR DE LA VOLATILIDAD IMPLÍCITA | G13: Decimal
A14: 8 | B14: DELTA_OPC | C14: NUMÉRICO | D14: (22,8) | E14: OPTO SX | F14: VALOR DEL PARÁMETRO DELTA | G14: Decimal
A15: 9 | B15: MDADELTA | C15: NUMÉRICO | D15: (3,0) | E15: OPTO SX | F15: MONEDA DEL PARÁMETRO DELTA | G15: Longitud, Catálogo | H15: =CATALOGOS!A$1019 -> MONEDA
A16: 10 | B16: GAMMA_OPC | C16: NUMÉRICO | D16: (22,8) | E16: OPTO SX | F16: VALOR DEL PARÁMETRO GAMMA | G16: Decimal
A17: 11 | B17: VEGA_OPC | C17: NUMÉRICO | D17: (22,8) | E17: OPTO SX | F17: VALOR DEL PARÁMETRO VEGA | G17: Decimal
A18: 12 | B18: RHO | C18: NUMÉRICO | D18: (22,8) | E18: OPTO SX | F18: VALOR DEL PARÁMETRO RHO | G18: Decimal
A19: 13 | B19: TASA_RHO | C19: TEXTO | D19: 20 | E19: OPTO SX | F19: TASA DE REFERENCIA PARA DETERMINAR LA TASA RHO DE LA OPERACIÓN | G19: Longitud, Catálogo | H19: ANEXO AF o ANEXO AT
A20: 14 | B20: PHI | C20: NUMÉRICO | D20: (22,8) | E20: OPTO SX | F20: VALOR DEL PARÁMETRO RHO DOS | G20: Decimal
A21: 15 | B21: TASA_PHI | C21: TEXTO | D21: 20 | E21: OPTO SX | F21: TASA DE REFERENCIA PARA DETERMINAR UNA SEGUNDA SENSIBILIDAD | G21: Longitud, Catálogo | H21: ANEXO AF o ANEXO AT
A22: 16 | B22: RHO_COL | C22: NUMÉRICO | D22: (22,8) | E22: OPTO SX | F22: VALOR DEL PARÁMETRO RHO TRES | G22: Decimal
A23: 17 | B23: TASA_RHO_COL | C23: TEXTO | D23: 20 | E23: OPTO SX | F23: TASA DE REFERENCIA PARA DETERMINAR UNA TERCERA SENSIBILIDAD | G23: Longitud, Catálogo | H23: ANEXO AF o ANEXO AT
A24: 18 | B24: PRECIO_CORTE | C24: NUMÉRICO | D24: (18,13) | E24: OPTO SX | F24: PRECIO DEL SUBYACENTE | G24: Decimal
A25: 19 | B25: SEN_COMP | C25: CARACTER | D25: 1 | E25: OPTO SX | F25: COMPLEMENTO DE CURVAS DE | G25: Longitud
A26: 20 | B26: CURVA_REF | C26: TEXTO | D26: 34 | E26: OPTO SX | F26: CURVA O SUPERFICIE DE REFERENCIA DE SENBILIDAD | G26: Longitud, Catálogo | H26: ANEXO AT
A27: 21 | B27: CURVA_REF2 | C27: TEXTO | D27: 34 | E27: OPTO SX | F27: CURVA O SUPERFICIE DE REFERENCIA DE SENSIBILIDAD DOS | G27: Longitud, Catálogo | H27: ANEXO AT
A28: 22 | B28: CURVA_REF3 | C28: TEXTO | D28: 34 | E28: OPTO SX | F28: CURVA O SUPERFICIE DE REFERENCIA DE SENSIBILIDAD TRES | G28: Longitud, Catálogo | H28: ANEXO AT
A29: 23 | B29: PAQ_OPC | C29: CARACTER | D29: 1 | E29: OPTO SX | F29: LA OPERACIÓN ES PARTE DE UN | G29: Longitud
A30: 24 | B30: ID_PAQ | C30: TEXTO | D30: 35 | E30: OPTO SX | F30: CLAVE O FOLIO CON EL QUE SE IDENTIFICA | G30: Longitud
A31: 25 | B31: CONSEC_PAQ | C31: NUMÉRICO | D31: (3,0) | E31: OPTO SX | F31: NÚMERO CONSECUTIVO PARA IDENTIFICAR | G31: Longitud
A32: 26 | B32: PRI_ACT | C32: NUMÉRICO | D32: (22,8) | E32: OPTO SX | F32: IMPORTE ACTUALIZADO (MERCADO) DE LA PRIMA (TOTAL) | G32: Decimal
A33: 27 | B33: ID_GAR_VIG | C33: TEXTO | D33: 20 | E33: OPTO SX | F33: CLAVE O FOLIO PARA IDENTIFICAR EL | G33: Longitud
A34: 28 | B34: FECHAINFO | C34: FECHA | D34: AAAA/MM/DD | F34: Fecha a la que corresponde la información
B36: UTI | C36: Modificar proceso

Sheet LAYOUT OPTO XI
A1: Nombre Archivo | B1: FILE_OPTO_XI.csv
A2: Separador de Datos | B2: PIPE "|"
A3: Descripcion | B3: LAYOUT DE DATOS OPTO XI - Información sobre las “Canastas” subyacentes en opciones celebradas en mercados no reconocidos
A4: Uso | B4: Formulario OPTO XI
A7: OPTO_XI - Información sobre las “Canastas” subyacentes en opciones celebradas en mercados no reconocidos
A9: LAYOUT | B9: ORDEN | C9: LLAVE | D9: NOMBRE_CAMPO | E9: TIPO DATO | F9: FORMATO | G9: OBLIGATORIO | H9: VALIDACION | I9: CATALOGO | J9: USO | K9: COLUMNA REPORTE APLICA | L9: DESCRIPCION | M9: DESCRIPCION INGLES | N9: OBSERVACIONES | O9: VALIDEZ INFORMACION | P9: FUENTE
A10: FILE_OPTO_XI | B10: 1 | C10: Si | D10: CLAVE_CAN | E10: TEXTO | F10: 20 | G10: Si | H10: Catalogo | I10: ANEXO AF | J10: OPTO_XI | K10: 1 | L10: Clave de la Canasta
A11: FILE_OPTO_XI | B11: 2 | C11: Si | D11: CLAVE_AF | E11: TEXTO | F11: 20 | G11: Si | H11: Catalogo | I11: ANEXO AF | J11: OPTO_XI | K11: 3 | L11: Clave del valor (deuda o acción), indice accionario, tasa de interés o tipo de cambio
A12: FILE_OPTO_XI | B12: 3 | C12: Si | D12: CON_CAN | E12: NUMERICO | F12: 3,0 | G12: Si | J12: OPTO_XI | K12: 4 | L12: Número consecutivo para identificar al subyacente que forma parte de la canasta
A13: FILE_OPTO_XI | B13: 4 | C13: No | D13: TIPO_MONITOR | E13: TEXTO | F13: 2 | G13: Si | J13: OPTO_XI | K13: 5 | L13: Tipo de monitoreo
A14: FILE_OPTO_XI | B14: 5 | C14: No | D14: PONDERADOR | E14: NUMERICO | F14: 3,6 | G14: Si | J14: OPTO_XI | K14: 6 | L14: Ponderador
A15: FILE_OPTO_XI | B15: 6 | C15: No | D15: PRECIOEJER | E15: NUMERICO | F15: 18,13 | G15: Si | J15: OPTO_XI | K15: 7 | L15: Precio unitario o tasa de ejercicio
A16: FILE_OPTO_XI | B16: 7 | C16: No | D16: TIP_PRECIO | E16: NUMERICO | F16: 2,0 | G16: Si | H16: Catalogo | I16: ANEXO AM | J16: OPTO_XI | K16: 8 | L16: Forma en la que está representado el precio de ejercicio
A17: FILE_OPTO_XI | B17: 8 | C17: No | D17: MDAPRECIO | E17: NUMERICO | F17: 3,0 | G17: Si | H17: Catalogo | I17: ANEXO E | J17: OPTO_XI | K17: 9 | L17: Moneda del precio unitario o tasa de ejercicio
A18: FILE_OPTO_XI | B18: 9 | C18: No | D18: PRECIO_INICIAL | E18: NUMERICO | F18: 18,13 | G18: Si | J18: OPTO_XI | K18: 10 | L18: Precio inicial del subyacente
A19: FILE_OPTO_XI | B19: 10 | C19: No | D19: CAL_EJERCICIO | E19: NUMERICO | F19: 2,0 | G19: Si | H19: Catalogo | I19: ANEXO AN | J19: OPTO_XI | K19: 11 | L19: Cálculo aplicable al precio del subyacente para determinar el ejercicio de la opción
A20: FILE_OPTO_XI | B20: 11 | C20: No | D20: CAL_LIQ | E20: NUMERICO | F20: 2,0 | G20: Si | H20: Catalogo | I20: ANEXO AK | J20: OPTO_XI | K20: 12 | L20: Cálculo de liquidación
A21: FILE_OPTO_XI | B21: 12 | C21: No | D21: FAC_LIQ | E21: NUMERICO | F21: 3,6 | G21: Si | J21: OPTO_XI | K21: 13 | L21: Factor aplicado a la forma de liquidación
A22: FILE_OPTO_XI | B22: 13 | C22: No | D22: PRE_SUP | E22: NUMERICO | F22: 18,13 | G22: Si | J22: OPTO_XI | K22: 14 | L22: Precio de la barrera superior
A23: FILE_OPTO_XI | B23: 14 | C23: No | D23: PRE_INF | E23: NUMERICO | F23: 18,13 | G23: Si | J23: OPTO_XI | K23: 15 | L23: Precio de la barrera inferior
A24: FILE_OPTO_XI | B24: 15 | C24: No | D24: MOD_PRE | E24: TEXTO | F24: 6 | G24: Si | H24: Catalogo | I24: ANEXO AO | J24: OPTO_XI | K24: 16 | L24: Modalidad del precio barrera
A25: FILE_OPTO_XI | B25: 16 | C25: No | D25: INT_MON_BA | E25: NUMERICO | F25: 3,0 | G25: Si | J25: OPTO_XI | K25: 17 | L25: Intervalo o frecuencia del monitoreo del o los precios barrera
A26: FILE_OPTO_XI | B26: 17 | C26: No | D26: FECHA_INFO | E26: FECHA | F26: AAAA/MM/DD | G26: Si | J26: OPTO_XI | L26: Fecha a la que corresponde la información
A28: DATOS CALCULADOS
A29: LAYOUT | B29: ORDEN | C29: LLAVE | D29: NOMBRE_CAMPO | E29: TIPO DATO | F29: FORMATO | G29: OBLIGATORIO | H29: VALIDACION | I29: CATALOGO | J29: USO | K29: COLUMNA REPORTE APLICA | L29: DESCRIPCION | M29: DESCRIPCION INGLES | N29: OBSERVACIONES | O29: VALIDEZ INFORMACION | P29: FUENTE
A30: OPTO_XI | B30: 2 | C30: No | D30: INST | E30: TEXTO | F30: 250 | G30: Si | J30: OPTO_XI | K30: 5 | L30: Clave de la institucion

Sheet LAYOUT OPTO XII
A1: Nombre Archivo | B1: FILE_OPTO_XII.csv
A2: Separador de Datos | B2: PIPE "|"
A3: Descripcion | B3: LAYOUT DE DATOS OPTO XII Información sobre Curvas de sensibilidad y factores de riesgo en opciones celebradas en mercados no reconocidos
A4: Uso | B4: Formulario OPTO XII
A7: OPTO_XII Información sobre Curvas de sensibilidad y factores de riesgo en opciones celebradas en mercados no reconocidos
A9: LAYOUT | B9: ORDEN | C9: LLAVE | D9: NOMBRE_CAMPO | E9: TIPO DATO | F9: FORMATO | G9: OBLIGATORIO | H9: VALIDACION | I9: CATALOGO | J9: USO | K9: COLUMNA REPORTE APLICA | L9: DESCRIPCION | M9: DESCRIPCION INGLES | N9: OBSERVACIONES | O9: VALIDEZ INFORMACION | P9: FUENTE
A10: FILE_OPTO_XII | B10: 1 | C10: Si | D10: FE_CON_OPE | E10: FECHA | F10: AAAA/MM/DD | G10: Si | J10: OPTO_XII | K10: 2 | L10: Fecha de concertación
A11: FILE_OPTO_XII | B11: 2 | C11: Si | D11: FE_CORTE | E11: FECHA | F11: AAAA/MM/DD | G11: Si | J11: OPTO_XII | K11: 3 | L11: Fecha de corte
A12: FILE_OPTO_XII | B12: 3 | C12: Si | D12: NUM_ID | E12: TEXTO | F12: 34 | G12: Si | J12: OPTO_XII | K12: 4 | L12: Número de identificación asociada a la opción
A13: FILE_OPTO_XII | B13: 4 | C13: No | D13: CON_SEN | E13: NUMERICO | F13: 3,0 | G13: Si | J13: OPTO_XII | K13: 5 | L13: Número consecutivo para identificar registros que forman parte del factor de riesgo
A14: FILE_OPTO_XII | B14: 5 | C14: No | D14: FAC_RIESGO | E14: TEXTO | F14: 3 | G14: Si | H14: Catalogo | I14: ANEXO AR | J14: OPTO_XII | K14: 6 | L14: Nombre del factor de riesgo
A15: FILE_OPTO_XII | B15: 6 | C15: No | D15: CLAVE_AF | E15: TEXTO | F15: 20 | G15: Si | H15: Catalogo | I15: ANEXO AF o ANEXO AT | J15: OPTO_XII | K15: 7 | L15: Clave del valor (deuda o acción), indice accionario, tasa de interés o tipo de cambio
A16: FILE_OPTO_XII | B16: 7 | C16: No | D16: FECHA | E16: FECHA | F16: AAAA/MM/DD | G16: Si | J16: OPTO_XII | K16: 8 | L16: Fecha del nodo de la curva
A17: FILE_OPTO_XII | B17: 8 | C17: No | D17: PLAZO | E17: NUMERICO | F17: 22,0 | G17: No | J17: OPTO_XII | K17: 9 | L17: Plazo del nodo de la curva
A18: FILE_OPTO_XII | B18: 9 | C18: No | D18: TEMP_PLAZO | E18: TEXTO | F18: 2 | G18: No | H18: Catalogo | I18: ANEXO AS | J18: OPTO_XII | K18: 10 | L18: Temporalidad del plazo
A19: FILE_OPTO_XII | B19: 10 | C19: No | D19: VAL_GRIEGA | E19: NUMERICO | F19: 22,8 | G19: Si | J19: OPTO_XII | K19: 11 | L19: Valor de la griega o sensibilidad
A20: FILE_OPTO_XII | B20: 11 | C20: No | D20: MDAGRIEGA | E20: NUMERICO | F20: 3,0 | G20: Si | H20: Catalogo | I20: ANEXO E | J20: OPTO_XII | K20: 12 | L20: Moneda de la griega o sensibilidad
A21: FILE_OPTO_XII | B21: 12 | C21: No | D21: VAL_VAR | E21: NUMERICO | F21: 22,8 | G21: Si | J21: OPTO_XII | K21: 13 | L21: Valor asociado al factor de riesgo
A22: FILE_OPTO_XII | B22: 13 | C22: No | D22: MDA_VAR1 | E22: NUMERICO | F22: 3,0 | G22: Si | H22: Catalogo | I22: ANEXO E | J22: OPTO_XII | K22: 14 | L22: Moneda del valor de la variable utilizada para el factor de riesgo
A23: FILE_OPTO_XII | B23: 14 | C23: No | D23: VAL_VAR2 | E23: NUMERICO | F23: 22,8 | G23: Si | J23: OPTO_XII | K23: 15 | L23: Valor dos asociado al factor de riesgo
A24: FILE_OPTO_XII | B24: 15 | C24: No | D24: MDA_VAR2 | E24: NUMERICO | F24: 3,0 | G24: Si | H24: Catalogo | I24: Moneda ISO | J24: OPTO_XII | K24: 16 | L24: Moneda del valor de la variable dos utilizada para el factor de riesgo
A25: FILE_OPTO_XII | B25: 16 | C25: No | D25: PRECIO_SUBY | E25: NUMERICO | F25: 22,8 | G25: Si | J25: OPTO_XII | K25: 17 | L25: Precio del subyacente utilizado para el factor de riesgo
A26: FILE_OPTO_XII | B26: 17 | C26: No | D26: FECHA_INFO | E26: FECHA | F26: AAAA/MM/DD | G26: Si | J26: OPTO_XII | L26: Fecha a la que corresponde la información
A29: DATOS CALCULADOS
A30: LAYOUT | B30: ORDEN | C30: LLAVE | D30: NOMBRE_CAMPO | E30: TIPO DATO | F30: FORMATO | G30: OBLIGATORIO | H30: VALIDACION | I30: CATALOGO | J30: USO | K30: COLUMNA REPORTE APLICA | L30: DESCRIPCION | M30: DESCRIPCION INGLES | N30: OBSERVACIONES | O30: VALIDEZ INFORMACION | P30: FUENTE
A31: OPTO_XI | B31: 1 | C31: No | D31: INST | E31: TEXTO | F31: 250 | G31: Si | J31: OPTO_XII | K31: 1 | L31: Clave de la institucion
A32: OPTO_XI | B32: 2 | C32: No | D32: CONSECUTIVO | E32: TEXTO | F32: 250 | G32: Si | J32: OPTO_XII | K32: 18 | L32: Número consecutivo para identificar registros que forman parte del mismo envío

Sheet CATALOGOS
A1: BOOLEAN_BX | C1: regresar | E1: 1
A2: CLAVE | B2: DESCRIPCION
A3: N | B3: No
A4: S | B4: Sí
A6: BROKER | C6: regresar | E6: 2
A7: CLAVE | B7: DESCRIPCION
A8: 077000 | B8: NO APLICA (LA OPERACIÓN NO SE LIQUIDARÁ EN UNA CÁMARA DE COMPENSACIÓN)
A9: 077001 | B9: BBVA BANCOMER, S.A., INSTITUCIÓN DE BANCA MÚLTIPLE, GRUPO FINANCIERO BBVA BANCOMER (FIDUCIARIO DEL FIDEICOMISO 29764-8 POR CUENTA DE TERCEROS)
A10: 077002 | B10: BANCO NACIONAL DE MÉXICO, S.A., INTEGRANTE DEL GRUPO FINANCIERO BANAMEX FIDUCIARIO DEL FIDEICOMISO 14016-1 (TERCEROS)
A11: 077004 | B11: SCOTIABANK INVERLAT, S.A., INSTITUCIÓN DE BANCA MÚLTIPLE, GRUPO FINANCIERO SCOTIABANK INVERLAT (FIDUCIARIO DEL FIDEICOMISO 101776 POR CUENTA DE TERCEROS)
A12: 077005 | B12: BANCO SANTANDER, S.A., INSTITUCIÓN DE BANCA MÚLTIPLE, GRUPO FINANCIERO SANTANDER FIDUCIARIO DEL FIDEICOMISO GFSSLPT (PROPIA)
A13: 077006 | B13: BBVA BANCOMER, S.A., INSTITUCIÓN DE BANCA MÚLTIPLE, GRUPO FINANCIERO BBVA BANCOMER (FIDUCIARIO DEL FIDEICOMISO 29763-0 POR CUENTA PROPIA)
A14: 077007 | B14: BANCO NACIONAL DE MÉXICO, S.A., INTEGRANTE DEL GRUPO FINANCIERO BANAMEX, FIDUCIARIO DEL FIDEICOMISO 13928-7 (PROPIA)
A15: 077009 | B15: SCOTIABANK INVERLAT, S.A., INSTITUCIÓN DE BANCA MÚLTIPLE, GRUPO FINANCIERO SCOTIABANK INVERLAT (FIDUCIARIO DEL FIDEICOMISO 101667 POR CUENTA PROPIA)
A16: 077010 | B16: BANCO SANTANDER, S.A., INSTITUCIÓN DE BANCA MÚLTIPLE, GRUPO FINANCIERO SANTANDER FIDUCIARIO DEL FIDEICOMISO 100,740 (TERCEROS)
A17: 077011 | B17: BANCO J.P. MORGAN, S.A., INSTITUCIÓN DE BANCA MÚLTIPLE, J.P. MORGAN GRUPO FINANCIERO FIDUCIARIO DEL FIDEICOMISO F/00265 (TERCEROS)
A18: 078001 | B18: ABN AMRO CLEARING CHICAGO LLC
... A132: 078115 | B132: WELLS FARGO SECURITIES, LLC
A134: CAM_COMP | C134: regresar | E134: 3
A135: CLAVE | B135: DESCRIPCION
A136: 1 | B136: ASIGNA COMPENSACIÓN Y LIQUIDACIONES (Cámara de Compensación del MexDer)
A137: 10 | B137: CME SWAP DATA REPOSITORY
A138: 11 | B138: DTCC-DDR
A139: 12 | B139: EUREX CLEARING AG
A140: 13 | B140: EUROCCP
A141: 14 | B141: EUROCLEAR BANK (Para valores: títulos de deuda y acciones)
A142: 15 | B142: HELLENIC EXCHANGES SA HOLDING CLEARING SETTLEMENT AND REGISTRY
A143: 16 | B143: ICE CLEAR EUROPE
A144: 17 | B144: ICE CLEAR US
A145: 18 | B145: ICE TRADE VAULT
A146: 19 | B146: INSTITUCIÓN PARA EL DEPÓSITO DE VALORES, S.D. INDEVAL (Para valores: títulos de deuda y acciones)
... A162: 9 | B162: CME EUROPEAN TRADE REPOSITORY
A165: CP_COUNTRIES | C165: regresar | E165: 5
A166: CLAVE | B166: DESCRIPCION
A167: AD | B167: Andorra
A168: AE | B168: United Arab Emirates
A169: AF | B169: Afghanistan
A170: AG | B170: Antigua and Barbuda
A171: AI | B171: Anguilla
A172: AL | B172: Albania
A173: AM | B173: Armenia
A174: AO | B174: Angola
A175: AQ | B175: Antarctica
A176: AR | B176: Argentina
A177: AS | B177: American Samoa
... A415: ZW | B415: Zimbabwe
A417: CP_ORIGIN_RES | C417: regresar | E417: 6
A418: CLAVE | B418: DESCRIPCION
A419: 1 | B419: Gobierno Federal y/o sus Entidades
A420: 2 | B420: Gobierno Estatal y/o sus Entidades
A421: 3 | B421: Gobierno Municipal y/o sus Entidades
A422: 4 | B422: Sector Privado No Financiero Nacional
A423: 5 | B423: Sector Privado Financiero Nacional
A424: 6 | B424: Sector Privado No Financiero Extranjero
A425: 7 | B425: Sector Privado Financiero Extranjero
A426: 8 | B426: Mixto Nacional (Privado y Público)
A428: CP_SECTOR | C428: regresar | E428: 7
A429: CLAVE | B429: DESCRIPCION
A430: 0 | B430: No aplica.
A431: 111 | B431: Agricultura
A432: 112 | B432: Cría y explotación de animales
A433: 113 | B433: Aprovechamiento forestal
A434: 114 | B434: Pesca, caza y captura
A435: 115 | B435: Servicios relacionados con las actividades agropecuarias y forestales
A436: 211 | B436: Extracción de petróleo y gas
A437: 212 | B437: Minería de minerales metálicos y no metálicos, excepto petróleo y gas
A438: 213 | B438: Servicios relacionados con la minería
A439: 221 | B439: Generación, transmisión y distribución de energía eléctrica
A440: 222 | B440: Suministro de agua y suministro de gas por ductos al consumidor final
... A556: 932 | B556: Organismos internacionales y extraterritoriales
A558: CP_TY_FUNDT | C558: regresar | E558: 8
A559: CLAVE | B559: DESCRIPCION
A560: 1 | B560: De Garantía
A561: 2 | B561: De Inversión
A562: 3 | B562: De Administración
A563: 4 | B563: De Garantía y Administración
A564: 5 | B564: De Garantía e Inversión
A566: CVE_TIT | C566: regresar | E566: 9
A567: CLAVE | B567: DESCRIPCION
A568: AEDUSD | B568: DIRHAM DE LOS EMIRATOS ÁRABES UNIDOS LIQUIDABLE CON DÓLAR DE LOS EE.UU.A.
A569: ARSMXN | B569: PESOS ARGENTINOS LIQUIDABLE CON PESO MEXICANO
A570: AUDJPY | B570: DÓLAR AUSTRALIANO LIQUIDABLE CON YEN JAPONÉS
A571: AUDMXN | B571: DÓLAR AUSTRALIANO LIQUIDABLE CON PESO MEXICANO
A572: AUDUSD | B572: DÓLAR AUSTRALIANO LIQUIDABLE CON DÓLAR DE LOS EE.UU.A.
A573: BCIADMO | B573: BRAZ ADM CHECK OVER/YR
A574: BP0001M | B574: ICE LIBOR GBP 1 Month
A575: BP0001W | B575: ICE LIBOR GBP 1 Week
A576: BP0002M | B576: ICE LIBOR GBP 2 Month
A577: BP0003M | B577: ICE LIBOR GBP 3 Month
A578: BP0006M | B578: ICE LIBOR GBP 6 Month
... A982: ZARUSD | B982: RAND SUDAFRICANO LIQUIDABLE CON DÓLAR DE LOS EE.UU.A.
A984: EVENTO_CP | C984: regresar | E984: 10
A985: CLAVE | B985: DESCRIPCION
A986: 1 | B986: Nueva Relación
A987: 2 | B987: Cambio en la Relación
A988: 3 | B988: Fin de la Relación
A990: LIQUIDA | C990: regresar | E990: 11
A991: CLAVE | B991: DESCRIPCION
A992: D | B992: Entrega por Diferencias
A993: M | B993: Ambas opciones son permitidas por contrato
...
