Workbook
Name Owner: [1]Catalogos!$B$2:$B$9
Name Owner: Catalogos!$B$2:$B$9
Name Sts_2: [1]Catalogos!$G$2:$G$6
Name Sts_2: Catalogos!$G$2:$G$6
Name StsAct: [1]Catalogos!$D$2:$D$11
Name StsAct: Catalogos!$D$2:$D$11

Sheet pendientes27102025
B2: Area | C2: Reporte | D2: Pendiente | E2: Observaciones
B3: Riesgos | C3: CFEN | D3: Mapeo | E3: Reunión oct 27
C4: R35
C5: PORCENTAJE_GARANTIA_PERSONAL | D5: Validación campos | E5: Pendiente
C6: PORCENTAJE_GARANTIA
C7: PRELACION_GAR
C8: R-0419 | D8: Revisión | E8: Generar reunión Contabilidad para definir responsable
B9: Contabilidad | C9: R-0420 | D9: Mapeo | E9: Operaciones recabó información falta solicitar info a Contabilidad*
C10: IPAB | E10: Pendiente de recibir el mapeo del layout
C11: ACM II_ADIC | D11: Validacion Usuario | E11: Pendiente de recibir retroalimentación sobre layouts desarrollados
C12: ACM II-Mapeo
C13: CATALOGO MINIMO
C14: CONCILIACIONES
C15: INVERSIONES PERMANENTES

Sheet Detalle1
A1: Detalles para Rprts - Azure: 03. DESARROLLO
A3: Carpeta | B3: Area | C3: Responsable | D3: Azure | E3: Pestañas | F3: Layout | G3: Estatus | H3: Comentarios | I3: Revision VoBo Usuario | J3: Actualizacion | K3: EstatusAct | L3: Sts2 | M3: Desarrollo | N3: AreaApoyo | O3: Obs Add | P3: Obs Add2 | Q3: NO APLICA | R3: MOTIVO
A4: Cartera | B4: Operaciones Captacion y credito | C4: Luis Alberto | D4: 03. DESARROLLO | E4: CLIENTES_POR_PRODUCTO | F4: R2450_51_52_CLIENTES POR PRODUCTO_V0.5 -- R2450 - R2451 - R2452 (CREDITO) (1) | G4: Listo | H4: Ntt, ya se reviso txt por usuario VoBo | I4: Estructura | K4: DES-Desarrollo Txt | L4: Validar | M4: Interno | N4: TI | O4: 2a vuelta US | P4: Integrar en un layout captación y crédito
A5: Cartera | B5: Operaciones Credito | C5: Luis Alberto | D5: 03. DESARROLLO | E5: CONSUMO | F5: V1.05_Credito_IFRS9_Consumo_Completo VF (2) | G5: Listo | H5: Se tiene la estructura construida y se integraron los datos con los que se cuenta, aun no se cuenta con todo el universo(Fuentes externas | I5: Estructura | K5: DES-Desarrollo Txt | M5: Interno | N5: TI
A6: Cartera | B6: Operaciones Credito | C6: Luis Alberto | D6: 03. DESARROLLO | E6: CREDITO | F6: V1.05_Layouts CREDITO Bancos IFRS (Comercial) (1) | G6: Listo | H6: Se tiene la estructura construida y se integraron los datos con los que se cuenta, aun no se cuenta con todo el universo(Fuentes externas | I6: Estructura | K6: DES-Desarrollo Txt | M6: Interno | N6: TI
A7: Operativos | B7: Operaciones Captacion | C7: Luis Alberto | D7: 03. DESARROLLO | E7: TITULARES GARANTIZADOS | F7: R2423_IFRS9_Titulares_Garantizados_V0.4 -- R2423 | G7: No mapeado | H7: NTT | K7: DES-Desarrollo Txt | L7: Ext NTT | M7: Externo | N7: Operaciones
A8: Cartera | B8: Operaciones Credito | C8: Luis Alberto | D8: 03. DESARROLLO | E8: CREDITO_GARANTIA | F8: V1.05_Layouts CREDITO Bancos IFRS (Comercial) (1) | G8: Listo | H8: Se tiene la estructura construida y se integraron los datos con los que se cuenta, aun no se cuenta con todo el universo(Fuentes externas | I8: Estructura | J8: PORCENTAJE_GARANTIA | Tiene Un campo x validar Riesgos | K8: DES-Desarrollo Txt | M8: Interno | N8: Riesgos
A9: Cartera | B9: Operaciones Credito | C9: Luis Alberto | D9: 03. DESARROLLO | E9: CREDITO_GARANTIA_PERSONAL | F9: V1.05_Layouts CREDITO Bancos IFRS (Comercial) (1) | G9: Listo | H9: Se tiene la estructura construida y se integraron los datos con los que se cuenta, aun no se cuenta con todo el universo(Fuentes externas | I9: Estructura | J9: PORCENTAJE_GARANTIA_PERS | Tiene Un campo x validar Riesgos | K9: DES-Desarrollo Txt | M9: Interno | N9: Riesgos
A10: Captacion | B10: Operaciones Captacion | C10: Luis Alberto | D10: 03. DESARROLLO | E10: ENT_CAJA_CAPTACION | F10: Layout CCV BW -- CCV | G10: Listo | H10: Ntt, ya se reviso txt por usuario VoBo | I10: Estructura y universo | J10: Validar con usuario si aplican | K10: DES-Desarrollo Txt | L10: Ext NTT | M10: Interno | N10: Operaciones | O10: Se menciona a NTT
A11: Captacion | B11: Operaciones Captacion | C11: Luis Alberto | D11: 03. DESARROLLO | E11: FILE_CAPTACION | F11: Layout Captacion_V3 -- CRI - R08 - OCIM_II | G11: Listo | H11: Ntt, ya se reviso txt por usuario VoBo Estructura | I11: Estructura y universo | J11: 20260108 -- NTT franja fronteriza en cero ION reenvió catalogo | K11: DES-Desarrollo Txt | L11: Ext NTT | M11: Interno | N11: TI | O11: Se requiera info actualizada congelando sistema para validacion | P11: Riesgo por aparente error en catálogo de Tipo Operación
A12: Adicionales | B12: Tesorería | C12: Eduardo Cabral | D12: 03. DESARROLLO | E12: FILE_CONTRAPARTES | F12: Layout_CONTRAPARTES_v5 -- CONTRAPARTES | G12: Pendiente | H12: Modulo de tesoreria | I12: NTT | K12: DES-Desarrollo Txt | L12: Ext NTT | M12: Int Tesoreria | N12: Tesoreria
A13: Captacion | B13: Operaciones Captacion | C13: Luis Alberto | D13: 03. DESARROLLO | E13: FILE_OCIM_I | F13: Layout OCIM_Diario_V1 -- OCIMN_I - OCIME_I | G13: NA | H13: NA | J13: Estaba identificado con NA | K13: DES-Desarrollo Txt | L13: Ext NTT | M13: Externo | N13: TI
A14: Captacion | B14: Operaciones Captacion | C14: Luis Alberto | D14: 03. DESARROLLO | E14: FILE_OCIM_II | F14: Layout OCIM_II_Activas_V3 -- OCIMN_II - OCIME_II | G14: NA | H14: NA | J14: Estaba identificado con NA | K14: DES-Desarrollo Txt | L14: Ext NTT | M14: Externo | N14: TI
A15: Captacion | B15: Operaciones Captacion | C15: Luis Alberto | D15: 03. DESARROLLO | E15: FILE_SISPAGOS | F15: Layout SISPAGOS BW -- SISPAGOS | G15: Listo | H15: Ntt, ya se reviso txt por usuario VoBo Estructura | I15: Estructura y universo | K15: DES-Desarrollo Txt | L15: Ext NTT | M15: Interno | N15: TI | O15: Se requiera info actualizada congelando sistema para validacion
A16: Captacion | B16: Operaciones Captacion | C16: Luis Alberto | D16: 03. DESARROLLO | E16: FT_TPA | F16: Layout TPA BW_v2 -- TPA | G16: Pendiente | H16: Modulo de tesoreria | I16: Estructura | J16: VoBo sobre estructura | K16: DES-Desarrollo Txt | L16: Ext NTT | M16: Interno | N16: TI
A17: Cartera | B17: Operaciones Credito | C17: Luis Alberto | D17: 03. DESARROLLO | E17: GARANTIA | F17: V1.05_Layouts CREDITO Bancos IFRS (Comercial) (1) | G17: Listo | H17: Se tiene la estructura construida y se integraron los datos con los que se cuenta, aun no se cuenta con todo el universo(Fuentes externas Pantalla comercial) | I17: Estructura | J17: PRELACION_GAR campo pendiente MAPEO | US revisa info restante | K17: DES-Desarrollo Txt | M17: Interno | N17: Riesgos
A18: Cartera | B18: Operaciones Credito | C18: Luis Alberto | D18: 03. DESARROLLO | E18: HIPOTECARIO | F18: V1.05_Layouts CREDITO Bancos IFRS (Hipotecario Simplificado) (1)- HIPOTECARIO | G18: Listo | H18: Se tiene la estructura construida y se integraron los datos con los que se cuenta, aun no se cuenta con todo el universo(Fuentes externas | I18: Estructura | K18: DES-Desarrollo Txt | M18: Interno | N18: TI
A19: Cartera | B19: Operaciones Credito | C19: Luis Alberto | D19: 03. DESARROLLO | E19: LINEA CREDITO | F19: V1.05_Layouts CREDITO Bancos IFRS (Comercial) (1) | G19: Listo | H19: Se tiene la estructura construida y se integraron los datos con los que se cuenta, aun no se cuenta con todo el universo(Fuentes externas Pantalla comercial) | I19: Estructura | K19: DES-Desarrollo Txt | M19: Interno | N19: TI
A20: Cartera | B20: Operaciones Credito | C20: Luis Alberto | D20: 03. DESARROLLO | E20: PAGOS_EXIGIBLES | F20: V1.05_Credito_IFRS9_Consumo_Completo VF (2) | G20: Listo | H20: Se tiene la estructura construida y se integraron los datos con los que se cuenta, aun no se cuenta con todo el universo(Fuentes externas | I20: Estructura | K20: DES-Desarrollo Txt | M20: Interno | N20: TI
A21: Cartera | B21: Operaciones Credito | C21: Luis Alberto | D21: 03. DESARROLLO | E21: PERSONA | F21: V1.05_Layouts CREDITO Bancos IFRS (Comercial) (1) | G21: Listo | H21: Se tiene la estructura construida y se integraron los datos con los que se cuenta, aun no se cuenta con todo el universo(Fuentes externas Pantalla comercial y cualitativa individual) | I21: Estructura | K21: DES-Desarrollo Txt | M21: Interno | N21: TI
A22: Operativos | B22: Operaciones Captacion | C22: Luis Alberto | D22: 03. DESARROLLO | E22: PRODUCTOS CAPTACION CNBV | F22: R2421_Prod Cap -- R2421 | G22: No mapeado | H22: NTT | K22: DES-Desarrollo Txt | L22: Ext NTT | M22: Externo | N22: Operaciones | O22: Este TXT ya fue entregado por NTT el 28/05 y te pase la guía para bajarlo de Transat el 27/10/25. Aún no lo conectan a ATOM.
A23: Cartera | B23: Contabilidad | C23: Ramon Jaimes | D23: 03. DESARROLLO | E23: R04A_MOV_419 | F23: V1.01_Credito_IFRS9_R04A -- A0411 - A0417 - A0419 - A0420 - A0424 - R04A_MOV_419 | G23: Mapeado incompleto | I23: Estructura y universo | J23: Reasignado a Contabilidad | K23: DES-Desarrollo Txt | M23: Interno | N23: Contabilidad
A24: Cartera | B24: Operaciones Credito | C24: Luis Alberto | D24: 03. DESARROLLO | E24: R04A_SALDOS | F24: V1.01_Credito_IFRS9_R04A -- A0411 - A0417 - A0419 - A0420 - A0424 | G24: Listo | H24: Se tiene la estructura construida y se integraron los datos con los que se cuenta, aun no se cuenta con todo el universo(Fuentes externas | I24: Estructura | K24: DES-Desarrollo Txt | M24: Interno | N24: TI
A25: Operativos | B25: Operaciones Captacion | C25: Luis Alberto | D25: 03. DESARROLLO | E25: R2441_42 | F25: Layout R2441_42_V2 --R2441 - R2442 | G25: No mapeado | H25: NTT | K25: DES-Desarrollo Txt | L25: Ext NTT | M25: Externo | N25: Operaciones | O25: Este TXT ya fue entregado por NTT el 16/06 y te pase la guía para bajarlo de Transat el 27/10/25. Aún no lo conectan a ATOM.
A26: Captacion | B26: Producto | C26: Claudia Barroso | D26: 03. DESARROLLO | E26: RECO | F26: Layout RECO BW -- RECO | G26: Listo | H26: Ntt, ya se reviso txt por usuario VoBo | I26: Estructura y universo | J26: Se reasignó a Prodcuto | estaba identificado como VoBo Usuario | K26: DES-Desarrollo Txt | M26: Interno | N26: TI | O26: Se menciona a NTT | P26: Validar la parte de captación NTT para integrar en un solo reporte

Sheet Tesoreria
A1: LAYOUT | B1: REPORTES | C1: AREA | D1: ESTATUS | E1: BLOQUE
A2: CONTRAPARTES | B2: 1 | C2: Tesorería | D2: Mapeo | E2: Operativos | F2: CONTRAPARTES | G2: NTT Responde no lo va a tener | faltan datos de contrapartes | probablemente manual
A3: CVT | B3: 4 | C3: Tesorería | D3: Mapeo | E3: Operativos | F3: MN ME | I3: LAYOUTs | J3: Sts
A4: OFF | B4: 3 | C4: Tesorería | D4: Mapeo | E4: Operativos | I4: Area | J4: Validacion | K4: Mapeo | L4: OK Estructura | M4: Bajaware | N4: En Cero | O4: Total
A5: OPTO | B5: 10 | C5: Tesorería | D5: Mapeo | E5: Operativos | I5: Contabilidad | K5: 1 | O5: 1
A6: REPORTOS | B6: 7 | C6: Tesorería | D6: Mapeo | E6: Operativos | F6: Reportos CDA | I6: Finanzas | J6: 1 | O6: 1
A7: SWAPS | B7: 8 | C7: Tesorería | D7: Mapeo | E7: Operativos | I7: Operaciones - Captacion | L7: 3 | O7: 3
A8: TENENCIA | B8: 2 | C8: Tesorería | D8: Mapeo | E8: Operativos | I8: Riesgos | J8: 2 | K8: 2 | M8: 1 | O8: 5
A9: GARANTÍAS | B9: 4 | C9: Tesorería | D9: Mapeo | E9: Adicionales | I9: Tesorería | K9: 9 | N9: 1 | O9: 10
A10: LID | B10: 1 | C10: Tesorería | D10: Mapeo | E10: Adicionales | I10: Total | J10: 3 | K10: 12 | L10: 3 | M10: 1 | N10: 1 | O10: 20
A11: OCIMN | B11: 3 | C11: Operaciones - Captacion | D11: OK Estructura | E11: Adicionales
A12: ACLME | B12: 5 | C12: Finanzas | D12: Validacion | E12: Adicionales | I12: REPORTES | J12: Sts
A13: ACM | B13: 2 | C13: Contabilidad | D13: Mapeo | E13: Adicionales | I13: Area | J13: Validacion | K13: Mapeo | L13: OK Estructura | M13: Bajaware | N13: En Cero | O13: Total
A14: CRI | B14: 1 | C14: Operaciones - Captacion | D14: OK Estructura | E14: Adicionales | I14: Contabilidad | K14: 2 | O14: 2
A15: FE | B15: 1 | C15: Riesgos | D15: Mapeo | E15: Adicionales | I15: Finanzas | J15: 5 | O15: 5
A16: GL | B16: 6 | C16: Riesgos | D16: Mapeo | E16: Adicionales | I16: Operaciones - Captacion | L16: 5 | O16: 5
A17: ML | B17: 1 | C17: Riesgos | D17: Mapeo | E17: Adicionales | I17: Riesgos | J17: 7 | K17: 2 | M17: 11 | O17: 20
A18: RC'S | B18: 11 | C18: Riesgos | D18: Bajaware | E18: Adicionales | I18: Tesorería | K18: 40 | N18: 2 | O18: 42
A19: XVA | B19: 1 | C19: Riesgos | D19: Mapeo | E19: Adicionales | I19: Total | J19: 12 | K19: 44 | L19: 5 | M19: 11 | N19: 2 | O19: 74
A20: TPA | B20: 1 | C20: Operaciones - Captacion | D20: OK Estructura | E20: Adicionales
A21: R03 | B21: 2 | C21: Tesorería | D21: En Cero | E21: Adicionales | O21: 27
O22: =+O21+GETPIVOTDATA("REPORTES2",$I$12) -> 101
O23: 3
M24: =20*12 -> 240 | O24: =O22*O23 -> 303 | P24: =O24/2 -> 151.5 | Q24: =O24/4 -> 75.75
O25: =O24-M24 -> 63

Sheet Detalle2
A1: Detalles para Rprts - Azure: 03. DESARROLLO
A3: Carpeta | B3: Area | C3: Responsable | D3: Azure | E3: Pestañas | F3: Layout | G3: Estatus | H3: Comentarios | I3: Revision VoBo Usuario | J3: Actualizacion | K3: EstatusAct | L3: Sts2 | M3: Desarrollo | N3: AreaApoyo | O3: Obs Add | P3: Obs Add2 | Q3: NO APLICA | R3: MOTIVO
A4: Cartera | B4: Operaciones Captacion y credito | C4: Luis Alberto | D4: 03. DESARROLLO | E4: CLIENTES_POR_PRODUCTO | F4: R2450_51_52_CLIENTES POR PRODUCTO_V0.5 -- R2450 - R2451 - R2452 (CREDITO) (1) | G4: Listo | H4: Ntt, ya se reviso txt por usuario VoBo | Gris dará aviso a Claudia para su Validación y VoBo | I4: Estructura | K4: DES-Desarrollo Txt | L4: Validar | M4: Interno | N4: TI | O4: 2a vuelta US | P4: Integrar en un layout captación y crédito
A5: Cartera | B5: Operaciones Credito | C5: Luis Alberto | D5: 03. DESARROLLO | E5: CONSUMO | F5: V1.05_Credito_IFRS9_Consumo_Completo VF (2) | G5: Listo | H5: 0212 Confrimar si se puede descargar de ATOM, para avisar a usuario para su validación Se tiene la estructura construida y se integraron los datos con los que se cuenta, aun no se cuenta con todo el universo(Fuentes externas | I5: Estructura | K5: DES-Desarrollo Txt | M5: Interno | N5: TI
A6: Cartera | B6: Operaciones Credito | C6: Luis Alberto | D6: 03. DESARROLLO | E6: CREDITO | F6: V1.05_Layouts CREDITO Bancos IFRS (Comercial) (1) | G6: Listo | H6: 0212 Confrimar si se puede descargar de ATOM, para avisar a usuario para su validación Se tiene la estructura construida y se integraron los datos con los que se cuenta, aun no se cuenta con todo el universo(Fuentes externas | I6: Estructura | K6: DES-Desarrollo Txt | M6: Interno | N6: TI
A7: Operativos | B7: Operaciones Captacion | C7: Luis Alberto | D7: 03. DESARROLLO | E7: TITULARES GARANTIZADOS | F7: R2423_IFRS9_Titulares_Garantizados_V0.4 -- R2423 | G7: No mapeado | H7: 0212 Se debe revisar estatus correcto ya que no se encuentra en Desarrollo NTT | K7: DES-Desarrollo Txt | L7: Ext NTT | M7: Externo | N7: Operaciones
A8: Cartera | B8: Operaciones Credito | C8: Luis Alberto | D8: 03. DESARROLLO | E8: CREDITO_GARANTIA | F8: V1.05_Layouts CREDITO Bancos IFRS (Comercial) (1) | G8: Listo | H8: 0212 Confrimar si se puede descargar de ATOM, para avisar a usuario para su validación Se tiene la estructura construida y se integraron los datos con los que se cuenta, aun no se cuenta con todo el universo(Fuentes externas | I8: Estructura | J8: PORCENTAJE_GARANTIA | Tiene Un campo x validar Riesgos | K8: DES-Desarrollo Txt | M8: Interno | N8: Riesgos
A9: Cartera | B9: Operaciones Credito | C9: Luis Alberto | D9: 03. DESARROLLO | E9: CREDITO_GARANTIA_PERSONAL | F9: V1.05_Layouts CREDITO Bancos IFRS (Comercial) (1) | G9: Listo | H9: 0212 Confrimar si se puede descargar de ATOM, para avisar a usuario para su validación Se tiene la estructura construida y se integraron los datos con los que se cuenta, aun no se cuenta con todo el universo(Fuentes externas | I9: Estructura | J9: PORCENTAJE_GARANTIA_PERS | Tiene Un campo x validar Riesgos | K9: DES-Desarrollo Txt | M9: Interno | N9: Riesgos
A10: Captacion | B10: Operaciones Captacion | C10: Luis Alberto | D10: 03. DESARROLLO | E10: ENT_CAJA_CAPTACION | F10: Layout CCV BW -- CCV | G10: Listo | H10: 0212 Generar la lista de todos los LayOuts que se requiere llenar con información de NTT ( todo lo que se genere NTT del Bucket para asegurar que se tiene contemplado por desarrllo) Ntt, ya se reviso txt por usuario VoBo | I10: Estructura y universo | J10: Validar con usuario si aplican | K10: DES-Desarrollo Txt | L10: Ext NTT | M10: Interno | N10: Operaciones | O10: Se menciona a NTT
A11: Captacion | B11: Operaciones Captacion | C11: Luis Alberto | D11: 03. DESARROLLO | E11: FILE_CAPTACION | F11: Layout Captacion_V3 -- CRI - R08 - OCIM_II | G11: Listo | H11: Ntt, ya se reviso txt por usuario VoBo Estructura (sólo se consume para guardarlos del lado de desarrollo) | ya se encuentran disponibles en ATOM, si son reportes por periodos. | I11: Estructura y universo | J11: 20260108 -- NTT franja fronteriza en cero ION reenvió catalogo | K11: DES-Desarrollo Txt | L11: Ext NTT | M11: Interno | N11: TI | O11: Se requiera info actualizada congelando sistema para validacion | P11: Riesgo por aparente error en catálogo de Tipo Operación
A12: Adicionales | B12: Tesorería | C12: Eduardo Cabral | D12: 03. DESARROLLO | E12: FILE_CONTRAPARTES | F12: Layout_CONTRAPARTES_v5 -- CONTRAPARTES | G12: Pendiente | H12: Modulo de tesoreria | Se requiere terminar ciclo completo para Usuario pueda realizar las pruebas | I12: NTT | K12: DES-Desarrollo Txt | L12: Ext NTT | M12: Int Tesoreria | N12: Tesoreria
A13: Captacion | B13: Operaciones Captacion | C13: Luis Alberto | D13: 03. DESARROLLO | E13: FILE_OCIM_I | F13: Layout OCIM_Diario_V1 -- OCIMN_I - OCIME_I | G13: Vacío | H13: Gris compartirá LayOut para que se genere la estructura | J13: Estaba identificado con NA | K13: DES-Desarrollo Txt | L13: Ext NTT | M13: Externo | N13: TI
A14: Captacion | B14: Operaciones Captacion | C14: Luis Alberto | D14: 03. DESARROLLO | E14: FILE_OCIM_II | F14: Layout OCIM_II_Activas_V3 -- OCIMN_II - OCIME_II | G14: Vacío | H14: Gris compartirá LayOut para que se genere la estructura | J14: Estaba identificado con NA | K14: DES-Desarrollo Txt | L14: Ext NTT | M14: Externo | N14: TI
A15: Captacion | B15: Operaciones Captacion | C15: Luis Alberto | D15: 03. DESARROLLO | E15: FILE_SISPAGOS | F15: Layout SISPAGOS BW -- SISPAGOS | G15: Listo | H15: Ntt, ya se reviso txt por usuario VoBo Estructura (sólo se consume para guardarlos del lado de desarrollo) | ya se encuentran disponibles en ATOM, si son reportes por periodos. | I15: Estructura y universo | K15: DES-Desarrollo Txt | L15: Ext NTT | M15: Interno | N15: TI | O15: Se requiera info actualizada congelando sistema para validacion
A16: Captacion | B16: Operaciones Captacion | C16: Luis Alberto | D16: 03. DESARROLLO | E16: FT_TPA | F16: Layout TPA BW_v2 -- TPA | G16: Pendiente | H16: Modulo de tesoreria | Gris deberá compartir LayOut a Desarrollo | I16: Estructura | J16: VoBo sobre estructura | K16: DES-Desarrollo Txt | L16: Ext NTT | M16: Interno | N16: TI
A17: Cartera | B17: Operaciones Credito | C17: Luis Alberto | D17: 03. DESARROLLO | E17: GARANTIA | F17: V1.05_Layouts CREDITO Bancos IFRS (Comercial) (1) | G17: Listo | H17: 0212 Se debe vaidar de que fecha se puede hacer la prueba de extración área de Desarrollo | 0213 Se tiene la estructura construida y se integraron los datos con los que se cuenta, aun no se cuenta con todo el universo(Fuentes externas Pantalla comercial) | I17: Estructura | J17: PRELACION_GAR campo pendiente MAPEO | US revisa info restante | K17: DES-Desarrollo Txt | M17: Interno | N17: Riesgos
A18: Cartera | B18: Operaciones Credito | C18: Luis Alberto | D18: 03. DESARROLLO | E18: HIPOTECARIO | F18: V1.05_Layouts CREDITO Bancos IFRS (Hipotecario Simplificado) (1)- HIPOTECARIO | G18: Listo | H18: 0212 Se tiene la estructura construida y se integraron los datos con los que se cuenta, aun no se cuenta con todo el universo(Fuentes externas | I18: Estructura | K18: DES-Desarrollo Txt | M18: Interno | N18: TI
A19: Cartera | B19: Operaciones Credito | C19: Luis Alberto | D19: 03. DESARROLLO | E19: LINEA CREDITO | F19: V1.05_Layouts CREDITO Bancos IFRS (Comercial) (1) | G19: Listo | H19: 0212 Se debe vaidar de que fecha se puede hacer la prueba de extración área de Desarrollo | 0213 Se tiene la estructura construida y se integraron los datos con los que se cuenta, aun no se cuenta con todo el universo(Fuentes externas Pantalla comercial) | I19: Estructura | K19: DES-Desarrollo Txt | M19: Interno | N19: TI
A20: Cartera | B20: Operaciones Credito | C20: Luis Alberto | D20: 03. DESARROLLO | E20: PAGOS_EXIGIBLES | F20: V1.05_Credito_IFRS9_Consumo_Completo VF (2) | G20: Listo | H20: 0212 Confrimar si se puede descargar de ATOM, para avisar a usuario para su validación Se tiene la estructura construida y se integraron los datos con los que se cuenta, aun no se cuenta con todo el universo(Fuentes externas | I20: Estructura | K20: DES-Desarrollo Txt | M20: Interno | N20: TI
A21: Cartera | B21: Operaciones Credito | C21: Luis Alberto | D21: 03. DESARROLLO | E21: PERSONA | F21: V1.05_Layouts CREDITO Bancos IFRS (Comercial) (1) | G21: Listo | H21: 0212 Se debe vaidar de que fecha se puede hacer la prueba de extración área de Desarrollo | 0213 Se tiene la estructura construida y se integraron los datos con los que se cuenta, aun no se cuenta con todo el universo(Fuentes externas Pantalla comercial y cualitativa) | I21: Estructura | K21: DES-Desarrollo Txt | M21: Interno | N21: TI
A22: Operativos | B22: Operaciones Captacion | C22: Luis Alberto | D22: 03. DESARROLLO | E22: PRODUCTOS CAPTACION CNBV | F22: R2421_Prod Cap -- R2421 | G22: No mapeado | H22: 0212 Gris, Revisar con Jenny si NTT ya lo tiene Mapeado NTT | K22: DES-Desarrollo Txt | L22: Ext NTT | M22: Externo | N22: Operaciones | O22: Este TXT ya fue entregado por NTT el 28/05 y te pase la guía para bajarlo de Transat el 27/10/25. Aún no lo conectan a ATOM.
A23: Cartera | B23: Contabilidad | C23: Ramon Jaimes | D23: 03. DESARROLLO | E23: R04A_MOV_419 | F23: V1.01_Credito_IFRS9_R04A -- A0411 - A0417 - A0419 - A0420 - A0424 - R04A_MOV_419 | G23: Mapeado incompleto | H23: 0212 Gris Revisar las notas de Martín para trazabilidad o darselo a Ramón para complemento de Mapeo | Carlo me envía correo de lo que se tiene documentado | I23: Estructura y universo | J23: Reasignado a Contabilidad | K23: DES-Desarrollo Txt | M23: Interno | N23: Contabilidad
A24: Cartera | B24: Operaciones Credito | C24: Luis Alberto | D24: 03. DESARROLLO | E24: R04A_SALDOS | F24: V1.01_Credito_IFRS9_R04A -- A0411 - A0417 - A0419 - A0420 - A0424 | G24: Listo | H24: 0212 Confrimar si se puede descargar de ATOM, para avisar a usuario para su validación Se tiene la estructura construida y se integraron los datos con los que se cuenta, aun no se cuenta con todo el universo (Fuentes externas | I24: Estructura | K24: DES-Desarrollo Txt | M24: Interno | N24: TI
A25: Operativos | B25: Operaciones Captacion | C25: Luis Alberto | D25: 03. DESARROLLO | E25: R2441_42 | F25: Layout R2441_42_V2 --R2441 - R2442 | G25: No mapeado | H25: 0212 Gris, Revisar con Jenny si NTT ya lo tiene Mapeado NTT | K25: DES-Desarrollo Txt | L25: Ext NTT | M25: Externo | N25: Operaciones | O25: Este TXT ya fue entregado por NTT el 16/06 y te pase la guía para bajarlo de Transat el 27/10/25. Aún no lo conectan a ATOM.
A26: Captacion | B26: Producto | C26: Claudia Barroso | D26: 03. DESARROLLO | E26: RECO | F26: Layout RECO BW -- RECO | G26: Listo | H26: Ntt, ya se reviso txt por usuario VoBo la parte de NTT | el complemento interno se Desarrollo trabajará para concluirlo | Deadline ? | Gris asigna tarea en Azure para complementar el LayOut con información de excel proporcionada por Usuario (Claudia) | I26: Estructura y universo | J26: Se reasignó a Prodcuto | estaba identificado como VoBo Usuario | K26: DES-Desarrollo Txt | M26: Interno | N26: TI | O26: Se menciona a NTT | P26: Validar la parte de captación NTT para integrar en un solo reporte

Sheet Detalle3
A1: Detalles de Rprts - Azure: 02. MAPEO
A3: Carpeta | B3: Area | C3: Responsable | D3: Azure | E3: Pestañas | F3: Layout | G3: Estatus | H3: Comentarios | I3: Revision VoBo Usuario | J3: Actualizacion | K3: EstatusAct | L3: Sts2 | M3: Desarrollo | N3: AreaApoyo | O3: Obs Add | P3: Obs Add2 | Q3: NO APLICA | R3: MOTIVO
A4: Adicionales | B4: Tesorería | C4: Eduardo Cabral | D4: 02. MAPEO | E4: VENC_ANT_REPORTOS | F4: Layout_REPORTOS_MN_ME_V7_2024 -- REPORTOS | G4: Pendiente | H4: Modulo de tesoreria | I4: NTT | K4: US-Mapeo | L4: Ext NTT | M4: Int Tesoreria | N4: Tesoreria | O4: Layout_REPORTOS_MN_ME_V7 -- REPORTOS | P4: modif nomb layout
A5: Adicionales | B5: Captacion | C5: Arturo Angeles | D5: 02. MAPEO | E5: USUARIOS NO CLIENTES BE | F5: R1522_USUARIOS NO CLIENTES BE_V0.4 -- R15 1522 | G5: No mapeado | K5: US-Mapeo | M5: Interno | N5: Finanzas
A6: Adicionales | B6: Tesorería | C6: Eduardo Cabral | D6: 02. MAPEO | E6: LAYOUT Seccion A Cat Lineas | F6: LAYOUT LID V4 | H6: Reporte habilitado en 2025 no contemplado en scope original | I6: Estructura y universo | K6: US-Mapeo | L6: Ext NTT | M6: Int Tesoreria Add | N6: Tesoreria
A7: Adicionales | B7: Tesorería | C7: Eduardo Cabral | D7: 02. MAPEO | E7: LAYOUT Seccion 5 Lineas de Cre | F7: LAYOUT LID V4 | H7: Reporte habilitado en 2025 no contemplado en scope original | I7: Estructura y universo | K7: US-Mapeo | L7: Ext NTT | M7: Int Tesoreria Add | N7: Tesoreria
A8: Adicionales | B8: Tesorería | C8: Eduardo Cabral | D8: 02. MAPEO | E8: LAYOUT LID CORRESPONSALES | F8: LAYOUT LID V4 | H8: Reporte habilitado en 2025 no contemplado en scope original | I8: Estructura y universo | K8: US-Mapeo | L8: Ext NTT | M8: Int Tesoreria Add | N8: Tesoreria
A9: Adicionales | B9: Tesorería | C9: Eduardo Cabral | D9: 02. MAPEO | E9: LAYOUT LID LIQUIDACIONES | F9: LAYOUT LID V4 | H9: Reporte habilitado en 2025 no contemplado en scope original | I9: Estructura y universo | K9: US-Mapeo | L9: Ext NTT | M9: Int Tesoreria Add | N9: Tesoreria
A10: Adicionales | B10: Tesorería | C10: Eduardo Cabral | D10: 02. MAPEO | E10: SWAPS | F10: Layout_SWAPS_V9 -- SWAPS | G10: Pendiente | H10: Modulo de tesoreria | I10: NTT | K10: US-Mapeo | L10: Ext NTT | M10: Int Tesoreria | N10: Tesoreria | O10: Layout_SWAPS_V9.1 -- SWAPS | P10: modif nomb layout
A11: Adicionales | B11: Tesorería | C11: Eduardo Cabral | D11: 02. MAPEO | E11: LAYOUT Seccion 1 LDID | F11: LAYOUT LID V4 | H11: Reporte habilitado en 2025 no contemplado en scope original | I11: Estructura y universo | K11: US-Mapeo | L11: Ext NTT | M11: Int Tesoreria Add | N11: Tesoreria
A12: Adicionales | B12: Tesorería | C12: Eduardo Cabral | D12: 02. MAPEO | E12: SWAP_IV_COM | F12: Layout_SWAPS_V9 -- SWAPS | G12: Pendiente | H12: Modulo de tesoreria | I12: NTT | K12: US-Mapeo | L12: Ext NTT | M12: Int Tesoreria | N12: Tesoreria | O12: Layout_SWAPS_V9.1 -- SWAPS | P12: modif nomb layout | Q12: Alex valida con Eduardo
A13: Adicionales | B13: Tesorería | C13: Eduardo Cabral | D13: 02. MAPEO | E13: SWAP_IV | F13: Layout_SWAPS_V9 -- SWAPS | G13: Pendiente | H13: Modulo de tesoreria | I13: NTT | K13: US-Mapeo | L13: Ext NTT | M13: Int Tesoreria | N13: Tesoreria | O13: Layout_SWAPS_V9.1 -- SWAPS | P13: modif nomb layout | Q13: Alex valida con Eduardo
A14: Situacion Finaciera | B14: Contabilidad | C14: Ramon Jaimes | D14: 02. MAPEO | E14: ACM II_ADIC | F14: LAYOUT_ACM_II V0.1 -- R01 | G14: Listo | H14: Revision de txt por parte del usuario | I14: Estructura y universo | J14: Info de credito enviada para Vobo, falta Mapeo Info Tesoreria | K14: US-Mapeo | M14: Interno | N14: Contabilidad
A15: Adicionales | B15: Tesorería | C15: Eduardo Cabral | D15: 02. MAPEO | E15: SWAP_FLUJOS | F15: Layout_SWAPS_V9 -- SWAPS | G15: Pendiente | H15: Modulo de tesoreria | I15: NTT | K15: US-Mapeo | L15: Ext NTT | M15: Int Tesoreria | N15: Tesoreria | O15: Layout_SWAPS_V9.1 -- SWAPS | P15: modif nomb layout
A16: Adicionales | B16: Tesorería | C16: Eduardo Cabral | D16: 02. MAPEO | E16: SWAP_CUOTAS_INT | F16: Layout_SWAPS_V9 -- SWAPS | G16: Pendiente | H16: Modulo de tesoreria | I16: NTT | K16: US-Mapeo | L16: Ext NTT | M16: Int Tesoreria | N16: Tesoreria | O16: Layout_SWAPS_V9.1 -- SWAPS | P16: modif nomb layout
A17: Adicionales | B17: Tesorería | C17: Eduardo Cabral | D17: 02. MAPEO | E17: SWAP_CONVO | F17: Layout_SWAPS_V9 -- SWAPS | G17: Pendiente | H17: Modulo de tesoreria | I17: NTT | K17: US-Mapeo | L17: Ext NTT | M17: Int Tesoreria | N17: Tesoreria | O17: Layout_SWAPS_V9.1 -- SWAPS | P17: modif nomb layout
A18: Situacion Finaciera | B18: Contabilidad | C18: Ramon Jaimes | D18: 02. MAPEO | E18: ACM II-Mapeo | F18: LAYOUT_ACM_II V0.1 -- R01 | G18: Listo | H18: Revision de txt por parte del usuario | I18: Estructura y universo | J18: Info de credito enviada para Vobo, falta Mapeo Info Tesoreria | K18: US-Mapeo | M18: Interno | N18: Contabilidad
A19: Adicionales | B19: Tesorería | C19: Eduardo Cabral | D19: 02. MAPEO | E19: CANASTA_REPORTOS | F19: Layout_REPORTOS_MN_ME_V7_2024 -- REPORTOS | G19: Pendiente | H19: Modulo de tesoreria | I19: NTT | K19: US-Mapeo | L19: Ext NTT | M19: Int Tesoreria | N19: Tesoreria | O19: Layout_REPORTOS_MN_ME_V7 -- REPORTOS | P19: modif nomb layout
A20: Riesgos | B20: Riesgos | C20: Homero Sanchez | D20: 02. MAPEO | E20: CARGA INICIAL IN-MIN | F20: LAYOUT CARGA INICIAL IN_MIN - Calculo Riesgo Operacional | G20: No mapeado | H20: Se reliza una solo carga, indica el usuario se debe relizar hasta la ejecucion con Bajware | J20: Reporte inicial Riesgos integrará 36 meses al momento de reporte | K20: US-Mapeo | L20: Validar | M20: Interno | N20: Riesgos | O20: x | P20: no se necesita mapeo Riesgos emite info completa -- Historico una sola carga, depende funcionalidad al 100. promedio movil | ingresos netos sin dependencias
A21: Riesgos | B21: Riesgos | C21: Homero Sanchez | D21: 02. MAPEO | E21: CARGA INICIAL PI-MIN | F21: LAYOUT CARGA INICIAL PI_MIN - Calculo Riesgo Operacional | G21: No mapeado | H21: Se reliza una solo carga, indica el usuario se debe relizar hasta la ejecucion con Bajware | J21: Reporte inicial Riesgos integrará 36 meses al momento de reporte | K21: US-Mapeo | L21: Validar | M21: Interno | N21: Riesgos | O21: Dep otra Area | P21: dependencia con Conta | perdidas operativas revisa Riesgos/Contabilidad
A22: Liquidez | B22: Tesorería | C22: Eduardo Cabral | D22: 02. MAPEO | E22: CF_ESP | F22: Layout CF_V3 | G22: Pendiente | H22: Modulo de tesoreria | I22: NTT | J22: ** Nota: Bajaware incluye el Layout de CF Concentración de Fondeo y ya no existe en el portal de Banxico, favor de confirmar con ellos, era un reporte semanal y mensual que combina Captación Tradicional e Interbancaria, similar al CRI ** | K22: US-Mapeo | L22: Ext NTT | M22: Int Tesoreria | N22: Tesoreria | O22: Confirma Bajaware que se continua vigente la secc 1 | P22: Cambio Nombre pestaña | Q22: xxx Validar con Captación
A23: Situacion Finaciera | B23: Contabilidad | C23: Ramon Jaimes | D23: 02. MAPEO | E23: ENT_CUOTAS_IPAB_DEF | F23: Layout IPAB_V3 - IPAB | G23: Por iniciar | H23: Se requiere recepcion de requerimiento y Excel. (Usuario) | I23: Estructura y universo | K23: US-Mapeo | M23: Interno | N23: Contabilidad
A24: Adicionales | B24: Finanzas | C24: Arturo Angeles | D24: 02. MAPEO | E24: FILE_ACLME | F24: Layout_ACLME_SECCION_I_V_v3 -- ACLME | G24: Pendiente | H24: Modulo de tesoreria | I24: NTT | K24: US-Mapeo | L24: Ext NTT | M24: Int Tesoreria Add | N24: Finanzas
A25: Adicionales | B25: Finanzas | C25: Arturo Angeles | D25: 02. MAPEO | E25: FILE_ACLME_AJUSTES_DDMMAA | F25: ACLME_Ajustes_V3 -- ACLME | G25: Pendiente | H25: Modulo de tesoreria | I25: NTT | K25: US-Mapeo | L25: Ext NTT | M25: Int Tesoreria Add | N25: Finanzas
A26: Adicionales | B26: Tesorería | C26: Eduardo Cabral | D26: 02. MAPEO | E26: REPORTOS_MNME | F26: Layout_REPORTOS_MN_ME_V7_2024 -- REPORTOS | G26: Pendiente | H26: Modulo de tesoreria | I26: NTT | K26: US-Mapeo | L26: Ext NTT | M26: Int Tesoreria | N26: Tesoreria | O26: Layout_REPORTOS_MN_ME_V7 -- REPORTOS | P26: modif nomb layout
A27: Adicionales | B27: Finanzas | C27: Arturo Angeles | D27: 02. MAPEO | E27: FILE_ACLME_CONCEPTOSFIJOS_DDMMAA | F27: Layout_ACLME_ConceptosFijos_v3 -- ACLME | G27: Pendiente | H27: Modulo de tesoreria | I27: NTT | K27: US-Mapeo | L27: Ext NTT | M27: Int Tesoreria Add | N27: Finanzas
A28: Adicionales | B28: Riesgos | C28: Homero Sanchez | D28: 02. MAPEO | E28: FILE_CFEN | F28: LAYOUT CFEN-3 | G28: No mapeado | H28: Se esta relizando ampeado por parte del usuario | I28: Estructura y universo | J28: Falta info de Contabilidad Anexo 1 O | K28: US-Mapeo | M28: Int Tesoreria Add | N28: Tesoreria/Contabilidad | O28: Dep otra Area
A29: Mercados | B29: Tesorería | C29: Eduardo Cabral | D29: 02. MAPEO | E29: FILE_CVT_TRP | F29: Layout_CVT_TRP_V2 | G29: Pendiente | H29: Modulo de tesoreria | I29: NTT | K29: US-Mapeo | L29: Ext NTT | M29: Int Tesoreria | N29: Tesoreria
A30: Adicionales | B30: Tesorería | C30: Eduardo Cabral | D30: 02. MAPEO | E30: FILE_FUT_CONVAL | F30: Layout OFF_FX_V7 -- OFF | G30: Pendiente | H30: Modulo de tesoreria | I30: NTT | K30: US-Mapeo | L30: Ext NTT | M30: Int Tesoreria | N30: Tesoreria
A31: Adicionales | B31: Tesorería | C31: Eduardo Cabral | D31: 02. MAPEO | E31: FILE_GARANTIAS_II | F31: Layout_Garantias_V1 - GARANTIAS | G31: Pendiente | H31: Modulo de tesoreria | I31: NTT | J31: No es Scope iniical RMC, asignado a Tesoreria | K31: US-Mapeo | L31: Ext NTT | M31: Int Tesoreria Add | N31: Tesoreria
A32: Adicionales | B32: UNE | C32: Martin Roman | D32: 02. MAPEO | E32: RECLAMACIONES | F32: LAYOUT R27_V1 -- R27 - 2701 | G32: No mapeado | K32: US-Mapeo | M32: Interno | N32: UNE
A33: Adicionales | B33: Tesorería | C33: Eduardo Cabral | D33: 02. MAPEO | E33: FILE_GARANTIAS_IV | F33: Layout_Garantias_V1 - GARANTIAS | G33: Pendiente | H33: Modulo de tesoreria | I33: NTT | J33: No es Scope iniical RMC, asignado a Tesoreria | K33: US-Mapeo | L33: Ext NTT | M33: Int Tesoreria Add | N33: Tesoreria
A34: Adicionales | B34: Riesgos | C34: Homero Sanchez | D34: 02. MAPEO | E34: R35_1 | F34: Layout R35_1 -- R35 | G34: No mapeado | H34: Se tiene que realizar una vez migrado a Banco | se puede mapear la cartera de creditos -- Riesgos / Exp Valores Transac -- Tesoreria | I34: Estructura y universo | K34: US-Mapeo | M34: Interno | N34: Riesgos
A35: Liquidez | B35: Riesgos | C35: Homero Sanchez | D35: 02. MAPEO | E35: FILE_ML | F35: Layout ML-4 -- ML | G35: Pendiente | H35: Modulo de tesoreria | I35: NTT | K35: US-Mapeo | L35: Ext NTT | M35: Int Tesoreria Add | N35: Riesgos
A36: Adicionales | B36: Tesorería | C36: Eduardo Cabral | D36: 02. MAPEO | E36: FILE_OFF_CONVAL | F36: Layout OFF_FX_V7 -- OFF | G36: Pendiente | H36: Modulo de tesoreria | I36: NTT | K36: US-Mapeo | L36: Ext NTT | M36: Int Tesoreria | N36: Tesoreria
A37: Adicionales | B37: Tesorería | C37: Eduardo Cabral | D37: 02. MAPEO | E37: FILE_OFF_FX_DDMMAA | F37: Layout OFF_FX_V7 -- OFF | G37: Pendiente | H37: Modulo de tesoreria | I37: NTT | K37: US-Mapeo | L37: Ext NTT | M37: Int Tesoreria | N37: Tesoreria
A38: Adicionales | B38: Tesorería | C38: Eduardo Cabral | D38: 02. MAPEO | E38: FILE_OPTO_CONVO | F38: Layout_OPTO_V3 -- OPTO | G38: Pendiente | H38: Modulo de tesoreria | I38: NTT | K38: US-Mapeo | L38: Ext NTT | M38: Int Tesoreria | N38: Tesoreria | Q38: Alex valida con Eduardo | R38: puede que no se opere como covertura
A39: Adicionales | B39: Tesorería | C39: Eduardo Cabral | D39: 02. MAPEO | E39: FILE_OPTO_II | F39: Layout_OPTO_V3 -- OPTO | G39: Pendiente | H39: Modulo de tesoreria | I39: NTT | K39: US-Mapeo | L39: Ext NTT | M39: Int Tesoreria | N39: Tesoreria
A40: Operativos | B40: Operaciones Captacion | C40: Arturo Angeles | D40: 02. MAPEO | E40: R2431 | F40: Layout R2431_V4 -- R24 C2431 | G40: No mapeado | H40: NTT | J40: • El 18/12/24 le indicamos al PMO que este Layout no correspondía a Operaciones. • Nuevamente en la reunión del 23/07/25 volvimos a pedir que lo asignaran y el acuerdo fue el siguiente: "Contabilidad se lleva a revisar el Layout y si hacen faltan campos se investiga lo que hace falta. Tanto crédito como captación", Sharon le iba a dar seguimiento. • Es urgente que lo asignen, anexo minuta del 23/07/25. | K40: US-Mapeo | L40: Ext NTT | M40: Externo | N40: Finanzas | O40: Asignado a Captación | P40: El Layout R24 Serie C, no le corresponde a Operaciones, solicita información de partes relacionadas que nosotros no tenemos, favor de revisar a fondo y determinar qué área lo debe llenar.
A41: Mercados | B41: Tesorería | C41: Eduardo Cabral | D41: 02. MAPEO | E41: FILE_TENENCIA_PRECIO | F41: CORE_LayoutTenenciaAdicional_v3.2 -- TENENCIA | G41: Pendiente | H41: Modulo de tesoreria | I41: NTT | K41: US-Mapeo | L41: Ext NTT | M41: Int Tesoreria | N41: Tesoreria
A42: Cartera | B42: Operaciones Captacion y credito | C42: Luis Alberto | D42: 02. MAPEO | E42: R04A_MOV_420_24 | F42: V1.01_Credito_IFRS9_R04A -- A0411 - A0417 - A0419 - A0420 - A0424 - R04A_MOV_420_24 | G42: Mapeado incompleto | I42: Estructura y universo | J42: Falta info de Contabilidad | K42: US-Mapeo | M42: Interno | N42: Contabilidad
A43: Adicionales | B43: Finanzas | C43: Arturo Angeles | D43: 02. MAPEO | E43: FILE_TIPOCAMBIO_DIARIO | F43: Layout_Tipos de Cambio Diario_v2 -- ACLME | G43: Pendiente | H43: Modulo de tesoreria | I43: NTT | K43: US-Mapeo | L43: Ext NTT | M43: Int Tesoreria Add | N43: Finanzas
A44: Adicionales | B44: Finanzas | C44: Arturo Angeles | D44: 02. MAPEO | E44: FT_ACLME_X | F44: Layout ACLME_X_V1 -- ACLME | G44: Pendiente | H44: Modulo de tesoreria | I44: NTT | K44: US-Mapeo | L44: Ext NTT | M44: Int Tesoreria Add | N44: Finanzas
A45: Mercados | B45: Tesorería | C45: Eduardo Cabral | D45: 02. MAPEO | E45: FT_CVT | F45: Layout_CVT_MN_ME_V3 -- CVT - RCs - TENENCIA | G45: Pendiente | H45: Modulo de tesoreria | I45: NTT | K45: US-Mapeo | L45: Ext NTT | M45: Int Tesoreria | N45: Tesoreria
A46: Mercados | B46: Tesorería | C46: Eduardo Cabral | D46: 02. MAPEO | E46: FT_CVT_IN | F46: Layout_CVT_IN_V2 -- CVT | G46: Pendiente | H46: Modulo de tesoreria | I46: NTT | K46: US-Mapeo | L46: Ext NTT | M46: Int Tesoreria | N46: Tesoreria
A47: Mercados | B47: Tesorería | C47: Eduardo Cabral | D47: 02. MAPEO | E47: FT_CVT_TR | F47: Layout_CVT_TR_V2 | G47: Pendiente | H47: Modulo de tesoreria | I47: NTT | K47: US-Mapeo | L47: Ext NTT | M47: Int Tesoreria | N47: Tesoreria
A48: Mercados | B48: Tesorería | C48: Eduardo Cabral | D48: 02. MAPEO | E48: FT_REPORTOS | F48: Layout_REPORTOS_MN_ME_V3 | G48: Pendiente | H48: Modulo de tesoreria | I48: NTT | K48: US-Mapeo | L48: Ext NTT | M48: Int Tesoreria | N48: Tesoreria
A49: Mercados | B49: Tesorería | C49: Eduardo Cabral | D49: 02. MAPEO | E49: FT_REPORTOS_CDA | F49: Layout_REPORTOS_CDA -- REPORTOS | G49: Pendiente | H49: Modulo de tesoreria | I49: NTT | J49: Marcados originalmente como NA | K49: US-Mapeo | L49: Ext NTT | M49: Int Tesoreria | N49: Tesoreria
A50: Mercados | B50: Tesorería | C50: Eduardo Cabral | D50: 02. MAPEO | E50: FT_TENENCIA | F50: LayoutTenencia_V2 -- TENENCIA - REPORTOS | G50: Pendiente | H50: Modulo de tesoreria | I50: NTT | K50: US-Mapeo | L50: Ext NTT | M50: Int Tesoreria | N50: Tesoreria
A51: Adicionales | B51: Tesorería | C51: Eduardo Cabral | D51: 02. MAPEO | E51: MODIF_TASAPREMIO | F51: Layout_REPORTOS_MN_ME_V7_2024 -- REPORTOS | G51: Pendiente | H51: Modulo de tesoreria | I51: NTT | K51: US-Mapeo | L51: Ext NTT | M51: Int Tesoreria | N51: Tesoreria | O51: Layout_REPORTOS_MN_ME_V7 -- REPORTOS | P51: modif nomb layout
A52: Adicionales | B52: Captacion | C52: Arturo Angeles | D52: 02. MAPEO | E52: OPERACIONES DE CLIENTES BE | F52: R1523_24_OPERACIONES DE CLIENTES BE_V0.4 -- R15 1523 1524 | G52: No mapeado | K52: US-Mapeo | M52: Interno | N52: Finanzas

Sheet PRESENTACION
A1: Desarrollo | B1: (Varios elementos)
E2: AZURE
A3: Etiquetas de fila | B3: Cuenta de Carpeta
A4: CERRADA | B4: 12 | C4: RCS QUE SI DEBEMOS ENVIAR | E4: 7
A5: 02. MAPEO | B5: 49 | E5: 67
A6: 03. DESARROLLO | B6: 23 | C6: INCLUYE LOS DE NTT | E6: 20
A7: 05. VOBO US | B7: 58 | E7: 2
A8: 06. BW-EJECUCION | B8: 8 | E8: 54
A9: 01. ASIGNA | B9: 6 | C9: LO TRABAJA BAJAWARE
A10: 04. VALIDA US | B10: 1 | H10: ASIGNACION AREA
A11: Total general | B11: 157 | H11: MAPEO
A12: VOBO US BW | H12: DESARROLLO
H13: VALIDACION
H14: VO BO USUARIO
B15: =SUM(B4:B8) -> 150 | C15: SIN TOMAR ENCUENTA BAJAWARE
B16: =GETPIVOTDATA("Carpeta",$A$3,"Azure","VOBO DE USUARIO A LAYOUT GENERADO")/B15 -> #REF!
C21: Val | D21: AreaApoyo
C22: Rprts | M22: Porc | W22: Total Rprts | X22: Total Porc
A23: Azure | B23: EstatusAct | C23: BajaWare | D23: Contabilidad | E23: Finanzas | F23: Operaciones | G23: Producto | H23: Riesgos | I23: Tesoreria | J23: Tesoreria/Contabilidad | K23: TI | L23: UNE | M23: BajaWare | N23: Contabilidad | O23: Finanzas | P23: Operaciones | Q23: Producto | R23: Riesgos | S23: Tesoreria | T23: Tesoreria/Contabilidad | U23: TI | V23: UNE
A24: 02. MAPEO | B24: US-Mapeo | D24: 4 | E24: 8 | H24: 4 | I24: 31 | J24: 1 | L24: 1 | M24: 0 | N24: 0.027586207 | O24: 0.055172414 | P24: 0 | Q24: 0 | R24: 0.027586207 | S24: 0.2137931 | T24: 0.0068965517 | U24: 0 | V24: 0.0068965517 | W24: 49 | X24: 0.33793103
A25: 03. DESARROLLO | B25: DES-Desarrollo Txt | D25: 1 | F25: 4 | H25: 3 | I25: 1 | K25: 14 | M25: 0 | N25: 0.0068965517 | O25: 0 | P25: 0.027586207 | Q25: 0 | R25: 0.020689655 | S25: 0.0068965517 | T25: 0 | U25: 0.096551724 | V25: 0 | W25: 23 | X25: 0.15862069
A26: 05. VOBO US | B26: US-VoBo | D26: 10 | G26: 42 | H26: 6 | M26: 0 | N26: 0.068965517 | O26: 0 | P26: 0 | Q26: 0.28965517 | R26: 0.04137931 | S26: 0 | T26: 0 | U26: 0 | V26: 0 | W26: 58 | X26: 0.4
A27: 06. BW-EJECUCION | B27: BW-Ejecucion | C27: 8 | M27: 0.055172414 | N27: 0 | O27: 0 | P27: 0 | Q27: 0 | R27: 0 | S27: 0 | T27: 0 | U27: 0 | V27: 0 | W27: 8 | X27: 0.055172414
A28: 01. ASIGNA | B28: Valida Areas | H28: 6 | M28: 0 | N28: 0 | O28: 0 | P28: 0 | Q28: 0 | R28: 0.04137931 | S28: 0 | T28: 0 | U28: 0 | V28: 0 | W28: 6 | X28: 0.04137931
A29: 04. VALIDA US | B29: US-Validación Txt | D29: 1 | M29: 0 | N29: 0.0068965517 | O29: 0 | P29: 0 | Q29: 0 | R29: 0 | S29: 0 | T29: 0 | U29: 0 | V29: 0 | W29: 1 | X29: 0.0068965517
A30: Total | C30: 8 | D30: 16 | E30: 8 | F30: 4 | G30: 42 | H30: 19 | I30: 32 | J30: 1 | K30: 14 | L30: 1 | M30: 0.055172414 | N30: 0.11034483 | O30: 0.055172414 | P30: 0.027586207 | Q30: 0.28965517 | R30: 0.13103448 | S30: 0.22068966 | T30: 0.0068965517 | U30: 0.096551724 | V30: 0.0068965517 | W30: 145 | X30: 1
C33: Val
A34: Azure | B34: EstatusAct | C34: Rprts | D34: Porc
A35: 01. ASIGNA | B35: Valida Areas | C35: 6 | D35: 0.04137931
A36: 02. MAPEO | C36: 49 | D36: 0.33793103
A37: 03. DESARROLLO | C37: 23 | D37: 0.15862069
A38: 04. VALIDA US | B38: US-Validación Txt | C38: 1 | D38: 0.0068965517
A39: 05. VOBO US | B39: US-VoBo | C39: 58 | D39: 0.4
A40: 06. BW-EJECUCION | B40: BW-Ejecucion | C40: 8 | D40: 0.055172414
A41: Total | C41: 145 | D41: 1
C43: 27 | D43: envío vacios
C44: 29 | D44: na aplica
C46: =SUM(C41:C44) -> 201
C48: 195
C49: =C46-C48 -> 6

Sheet Resumen Original
H1: Desarrollo | I1: Interno
H3: Distribución | J3: EstatusAct
H4: Responsable | I4: Area | J4: Backlog | K4: Mapeo Usuario | L4: Txt en Desarrollo | M4: Validacion Txt Usuario | N4: VoBo Usuario | O4: Total | P4: % Avance | Q4: % Total
B5: Area | C5: Desarrollo | H5: Claudia Barroso | I5: Producto | L5: 1 | N5: 42 | O5: 43 | P5: =N5/O5 -> 0.97674419 | Q5: =O5/$O$13 -> 21.5
B6: Estatus | C6: Interno | D6: Externo | E6: NA | F6: Total | H6: Eduardo Cabral | I6: Tesorería | L6: 1 | O6: 1 | P6: =N6/O6 -> 0 | Q6: =O6/$O$13 -> 0.5
B7: Contabilidad | C7: 14 | F7: 14 | H7: Homero Sanchez | I7: Riesgos | J7: 2 | K7: 1 | N7: 5 | O7: 8 | P7: =N7/O7 -> 0.625 | Q7: =O7/$O$13 -> 4
B8: Mapeo Usuario | C8: 4 | F8: 4 | H8: Luis Alberto | I8: Operaciones Captacion | L8: 2 | N8: 1 | O8: 3 | P8: =N8/O8 -> 0.33333333 | Q8: =O8/$O$13 -> 1.5
B9: Validacion Txt Usuario | C9: 4 | F9: 4 | I9: Operaciones Captacion y credito | K9: 1 | L9: 1 | O9: 2 | P9: =N9/O9 -> 0 | Q9: =O9/$O$13 -> 1
B10: VoBo Usuario | C10: 4 | F10: 4 | I10: Operaciones Credito | L10: 7 | M10: 3 | O10: 10 | P10: =N10/O10 -> 0 | Q10: =O10/$O$13 -> 5
B11: Txt en Desarrollo | C11: 2 | F11: 2 | H11: Ramon Jaimes | I11: Contabilidad | K11: 2 | M11: 5 | N11: 8 | O11: 15 | P11: =N11/O11 -> 0.53333333 | Q11: =O11/$O$13 -> 7.5
B12: Operaciones Captacion | C12: 4 | D12: 13 | E12: 7 | F12: 24 | H12: Martin Roman | I12: UNE | K12: 1 | O12: 1 | P12: =N12/O12 -> 0 | Q12: =O12/$O$13 -> 0.5
B13: Backlog | D13: 13 | E13: 7 | F13: 20 | H13: Arturo Angeles | I13: Producto | K13: 2 | O13: 2 | P13: =N13/O13 -> 0 | Q13: =SUM(Q5:Q12) -> 41.5
B14: VoBo Usuario | C14: 4 | F14: 4 | H14: Total | J14: 2 | K14: 7 | L14: 12 | M14: 8 | N14: 56 | O14: 85
B15: Operaciones Captacion y credito | C15: 3 | F15: 3 | Q15: =SUM(J15:P15) -> 0
B16: Mapeo Usuario | C16: 2 | F16: 2
B17: Validacion Txt Usuario | C17: 1 | F17: 1
B18: Operaciones Credito | C18: 10 | E18: 6 | F18: 16
B19: Backlog | E19: 6 | F19: 6
B20: Validacion Txt Usuario | C20: 3 | F20: 3
B21: Txt en Desarrollo | C21: 7 | F21: 7
B22: Producto | C22: 7 | E22: 12 | F22: 19
B23: Backlog | E23: 12 | F23: 12
B24: Mapeo Usuario | C24: 2 | F24: 2
B25: VoBo Usuario | C25: 5 | F25: 5
B26: Riesgos | C26: 9 | D26: 12 | F26: 21
B27: Backlog | C27: 2 | D27: 12 | F27: 14
B28: Mapeo Usuario | C28: 2 | F28: 2
B29: Txt en Desarrollo | C29: 5 | F29: 5
B30: Riesgos y tesoreria | D30: 2 | F30: 2
B31: Backlog | D31: 2 | F31: 2
B32: Tesorería | D32: 58 | F32: 58
B33: Backlog | D33: 58 | F33: 58
B34: TBD | C34: 1 | F34: 1
B35: Mapeo Usuario | C35: 1 | F35: 1
B36: Total | C36: 48 | D36: 85 | E36: 25 | F36: 158

Sheet PendContab20260120
B3: Detalles para NumReportes - AreaApoyo: Contabilidad, EstatusAct: US-Validación Txt
B5: Pestañas | C5: Layout | D5: Actualizacion | E5: EstatusAct | F5: Entrega
B6: CATALOGO MINIMO | C6: R01_Catalogo Minimo --R01 - R10 - R12 - R13 | D6: Archivo Txt enviado, comentarios pendientes | E6: US-Validación Txt | F6: miercoles 28
B7: ACM II_ADIC | C7: LAYOUT_ACM_II V0.1 -- R01 | D7: Archivo TXT de Credito enviado, comentarios pendientes Mapeo pendiente cuentas Tesorería | E7: US-Mapeo | F7: lunes 26 rev
B8: ACM II-Mapeo | C8: LAYOUT_ACM_II V0.1 -- R01
B9: ENT_CUOTAS_IPAB_DEF | C9: Layout IPAB_V3 - IPAB | D9: Mapeo Pendiente | F9: viernes 30
B10: R04A_MOV_419 | C10: V1.01_Credito_IFRS9_R04A -- A0411 - A0417 - A0419 - A0420 - A0424 - R04A_MOV_419
B11: R04A_MOV_420_24 | C11: V1.01_Credito_IFRS9_R04A -- A0411 - A0417 - A0419 - A0420 - A0424 - R04A_MOV_420_24 | D11: Falta integrar informacion Contable
B12: FILE_CFEN | C12: LAYOUT CFEN-3 | D12: Contabilidad Falta info Capital FundamentalAnexo 1 O

Sheet Resumen
B2: NumReportes | C2: EstatusAct
B3: AreaApoyo | C3: Valida Areas | D3: US-Mapeo | E3: DES-Desarrollo Txt | F3: US-Validación Txt | G3: US-VoBo | H3: BW-Ejecucion | I3: Envío Vacio | J3: Total general
B4: BajaWare | H4: 8 | J4: 8
B5: Contabilidad | D5: 4 | E5: 1 | F5: 1 | G5: 10 | J5: 16
B6: Finanzas | D6: 8 | J6: 8
B7: Operaciones | E7: 4 | J7: 4
B8: Producto | G8: 42 | J8: 42
B9: Riesgos | C9: 6 | D9: 4 | E9: 3 | G9: 6 | J9: 19
B10: Tesoreria | D10: 31 | E10: 1 | I10: 12 | J10: 44
B11: TI | E11: 14 | J11: 14
B12: UNE | D12: 1 | J12: 1
B13: Tesoreria/Contabilidad | D13: 1 | J13: 1
B14: Total general | C14: 6 | D14: 49 | E14: 23 | F14: 1 | G14: 58 | H14: 8 | I14: 12 | J14: 157
I16: 145 | J16: total en presentacion
I17: =I16+GETPIVOTDATA("Carpeta",$B$2,"EstatusAct","Envío Vacio") -> 157
G18: =H17-E4 -> 0
B19: i: En validacion con BW, si proceden (productos que no se operan y reporte dado de baja en portal BANXICO)
B20: ii: Corresponde a 2 reportes
B21: iii: La mayoria se ataca con el reporte de transacciones | G21: =G17/G18 -> #DIV/0!
B22: iv: 10 generacion automática Bajaware
B23: v: 1 campo en validacion de cada reporte con Riesgos

Sheet Relacion  (2)
U1: ASIGNACION AREA | W1: MAPEO | Y1: DESARROLLO | AA1: VALIDACION US | AC1: VOBO LAYOUT | AE1: EJECUCION BW | AG1: VOBO EJECUCION | AI1: FEBRERO | AM1: MARZO | AQ1: ABRIL | AV1: MAYO
A2: Carpeta | B2: Area | C2: Responsable | D2: Azure | E2: Pestañas | F2: Layout | G2: Estatus | H2: Comentarios | I2: Revision VoBo Usuario | J2: Actualizacion | K2: EstatusAct | L2: Sts2 | M2: Desarrollo | N2: AreaApoyo | O2: Obs Add | P2: Obs Add2 | Q2: NO APLICA | R2: Motivo No APLICA | T2: # | U2: INICIO | V2: FIN | W2: INICIO | X2: FIN | Y2: INICIO | Z2: FIN | AA2: INICIO | AB2: FIN | AC2: INICIO | AD2: FIN | AE2: INICIO | AF2: FIN | AG2: INICIO | AH2: FIN | AI2: 02 - 0 6 | AJ2: 09 - 13 | AK2: 16 - 20 | AL2: 23 - 27 | AM2: 02 - 0 6 | AN2: 09 - 13 | AO2: 16 - 20 | AP2: 23 - 27 | AQ2: 30 - 03 | AR2: 06 - 10 | AS2: 13 - 17 | AT2: 20 - 24 | AU2: 27 - 01 | AV2: 04 - 08 | AW2: 11 - 15 | AX2: 18 - 22 | AY2: 25 - 29
A3: Adicionales | B3: Tesorería | C3: Eduardo Cabral | D3: MAPEO | E3: VENC_ANT_REPORTOS | F3: Layout_REPORTOS_MN_ME_V7_2024 -- REPORTOS | G3: Pendiente | H3: Modulo de tesoreria | I3: NTT | K3: US-Mapeo | L3: Ext NTT | M3: Int Tesoreria | N3: Tesoreria | O3: Layout_REPORTOS_MN_ME_V7 -- REPORTOS | P3: modif nomb layout | T3: 1 | W3: 46056 | X3: 46087 | Y3: 46083 | Z3: 46122 | AA3: 46111 | AB3: 46136 | AC3: 46118 | AD3: 46136 | AE3: 46125 | AF3: 46150 | AG3: 46139 | AH3: 46171
A4: Adicionales | B4: Captacion | C4: Arturo Angeles | D4: MAPEO | E4: USUARIOS NO CLIENTES BE | F4: R1522_USUARIOS NO CLIENTES BE_V0.4 -- R15 1522 | G4: No mapeado | K4: US-Mapeo | M4: Interno | N4: Finanzas | T4: 2 | W4: 46056 | X4: 46080 | Y4: 46083 | Z4: 46108 | AA4: 46111 | AB4: 46122 | AC4: 46121 | AD4: 46122 | AE4: 46125 | AF4: 46143 | AG4: 46146 | AH4: 46157
A5: Operativos | B5: Operaciones Captacion | C5: Luis Alberto | D5: CERRADA | E5: UBICACION DE PUNTOS DE TRANSACC | F5: R2443_Ubicacion - R2443 | G5: No mapeado | H5: NTT | K5: Envío Vacio | L5: NA | M5: NA | N5: NA | O5: Acuerdo con Erika el 18/12/24. No aplica en este momento, porque no tendremos nada de lo que solicita. | Q5: No aplica | R5: Este reporte recaba información respecto a la ubicación geográfica de las sucursales, módulos, cajeros automáticos, terminales punto de venta y comisionistas a través de las cuales los usuarios de los servicios financieros realizan las transacciones. | T5: 3
A6: Operativos | B6: Operaciones Captacion | C6: Luis Alberto | D6: DESARROLLO | E6: TITULARES GARANTIZADOS | F6: R2423_IFRS9_Titulares_Garantizados_V0.4 -- R2423 | G6: No mapeado | H6: NTT | K6: DES-Desarrollo Txt | L6: Ext NTT | M6: Externo | N6: Operaciones | S6: x | T6: 4 | Y6: 46056 | Z6: 46073 | AA6: 46076 | AB6: 46094 | AC6: 46093 | AD6: 46094 | AE6: 46097 | AF6: 46115 | AG6: 46118 | AH6: 46136
A7: Adicionales | B7: Operaciones Captacion | C7: Luis Alberto | E7: TADESCOM_BAJAS | F7: Layout TADESCOM -- TADESCOM | G7: NA | H7: NA | K7: Backlog | L7: NA | M7: NA | N7: NA | T7: 5
A8: Adicionales | B8: Operaciones Captacion | C8: Luis Alberto | E8: TADESCOM_ALTAS | F8: Layout TADESCOM -- TADESCOM | G8: NA | H8: NA | K8: Backlog | L8: NA | M8: NA | N8: NA | T8: 6
A9: Adicionales | B9: Tesorería | C9: Eduardo Cabral | D9: MAPEO | E9: SWAPS | F9: Layout_SWAPS_V9 -- SWAPS | G9: Pendiente | H9: Modulo de tesoreria | I9: NTT | K9: US-Mapeo | L9: Ext NTT | M9: Int Tesoreria | N9: Tesoreria | O9: Layout_SWAPS_V9.1 -- SWAPS | P9: modif nomb layout | T9: 7 | W9: 46056 | X9: 46087 | Y9: 46083 | Z9: 46122 | AA9: 46111 | AB9: 46136 | AC9: 46118 | AD9: 46136 | AE9: 46125 | AF9: 46150 | AG9: 46139 | AH9: 46171
A10: Adicionales | B10: Tesorería | C10: Eduardo Cabral | D10: MAPEO | E10: SWAP_MEREC_CONVO | F10: Layout_SWAPS_V9 -- SWAPS | G10: Pendiente | H10: Modulo de tesoreria | I10: NTT | K10: US-Mapeo | L10: Ext NTT | M10: Int Tesoreria | N10: Tesoreria | O10: Layout_SWAPS_V9.1 -- SWAPS - 1. ENT_SWAP_MEREC_CONVO | P10: modif nomb layout | T10: 8 | W10: 46056 | X10: 46087 | Y10: 46083 | Z10: 46122 | AA10: 46111 | AB10: 46136 | AC10: 46118 | AD10: 46136 | AE10: 46125 | AF10: 46150 | AG10: 46139 | AH10: 46171
A11: Adicionales | B11: Tesorería | C11: Eduardo Cabral | D11: MAPEO | E11: SWAP_IV_COM | F11: Layout_SWAPS_V9 -- SWAPS | G11: Pendiente | H11: Modulo de tesoreria | I11: NTT | K11: US-Mapeo | L11: Ext NTT | M11: Int Tesoreria | N11: Tesoreria | O11: Layout_SWAPS_V9.1 -- SWAPS | P11: modif nomb layout | T11: 9 | W11: 46056 | X11: 46087 | Y11: 46083 | Z11: 46122 | AA11: 46111 | AB11: 46136 | AC11: 46118 | AD11: 46136 | AE11: 46125 | AF11: 46150 | AG11: 46139 | AH11: 46171
A12: Adicionales | B12: Tesorería | C12: Eduardo Cabral | D12: MAPEO | E12: SWAP_IV | F12: Layout_SWAPS_V9 -- SWAPS | G12: Pendiente | H12: Modulo de tesoreria | I12: NTT | K12: US-Mapeo | L12: Ext NTT | M12: Int Tesoreria | N12: Tesoreria | O12: Layout_SWAPS_V9.1 -- SWAPS | P12: modif nomb layout | T12: 10 | W12: 46056 | X12: 46087 | Y12: 46083 | Z12: 46122 | AA12: 46111 | AB12: 46136 | AC12: 46118 | AD12: 46136 | AE12: 46125 | AF12: 46150 | AG12: 46139 | AH12: 46171
A13: Adicionales | B13: Tesorería | C13: Eduardo Cabral | D13: MAPEO | E13: SWAP_I | F13: Layout_SWAPS_V9 -- SWAPS | G13: Pendiente | H13: Modulo de tesoreria | I13: NTT | K13: US-Mapeo | L13: Ext NTT | M13: Int Tesoreria | N13: Tesoreria | O13: Layout_SWAPS_V9.1 -- SWAPS | P13: modif nomb layout | T13: 11 | W13: 46056 | X13: 46087 | Y13: 46083 | Z13: 46122 | AA13: 46111 | AB13: 46136 | AC13: 46118 | AD13: 46136 | AE13: 46125 | AF13: 46150 | AG13: 46139 | AH13: 46171
A14: Adicionales | B14: Tesorería | C14: Eduardo Cabral | D14: MAPEO | E14: SWAP_FLUJOS | F14: Layout_SWAPS_V9 -- SWAPS | G14: Pendiente | H14: Modulo de tesoreria | I14: NTT | K14: US-Mapeo | L14: Ext NTT | M14: Int Tesoreria | N14: Tesoreria | O14: Layout_SWAPS_V9.1 -- SWAPS | P14: modif nomb layout | T14: 12 | W14: 46056 | X14: 46087 | Y14: 46083 | Z14: 46122 | AA14: 46111 | AB14: 46136 | AC14: 46118 | AD14: 46136 | AE14: 46125 | AF14: 46150 | AG14: 46139 | AH14: 46171
A15: Adicionales | B15: Tesorería | C15: Eduardo Cabral | D15: MAPEO | E15: SWAP_CUOTAS_INT | F15: Layout_SWAPS_V9 -- SWAPS | G15: Pendiente | H15: Modulo de tesoreria | I15: NTT | K15: US-Mapeo | L15: Ext NTT | M15: Int Tesoreria | N15: Tesoreria | O15: Layout_SWAPS_V9.1 -- SWAPS | P15: modif nomb layout | T15: 13 | W15: 46056 | X15: 46087 | Y15: 46083 | Z15: 46122 | AA15: 46111 | AB15: 46136 | AC15: 46118 | AD15: 46136 | AE15: 46125 | AF15: 46150 | AG15: 46139 | AH15: 46171
A16: Adicionales | B16: Tesorería | C16: Eduardo Cabral | D16: MAPEO | E16: SWAP_CONVO | F16: Layout_SWAPS_V9 -- SWAPS | G16: Pendiente | H16: Modulo de tesoreria | I16: NTT | K16: US-Mapeo | L16: Ext NTT | M16: Int Tesoreria | N16: Tesoreria | O16: Layout_SWAPS_V9.1 -- SWAPS | P16: modif nomb layout | T16: 14 | W16: 46056 | X16: 46087 | Y16: 46083 | Z16: 46122 | AA16: 46111 | AB16: 46136 | AC16: 46118 | AD16: 46136 | AE16: 46125 | AF16: 46150 | AG16: 46139 | AH16: 46171
A17: Operativos | B17: Operaciones Captacion | C17: Luis Alberto | D17: CERRADA | E17: SUCURSALES | F17: R2422_Sucursales -- R2422 | G17: No mapeado | H17: NTT | K17: Envío Vacio | L17: NA | M17: NA | N17: NA | O17: Acuerdo con Erika el 18/12/24. No aplica en este momento, porque no tendremos nada de lo que solicita. | Q17: No aplica | R17: Se refiere a tarjetas, ATM, TPVs, y No. de personal, no tenemos esos datos actualmente, por lo que consideramos que no nos aplica actualmente, pero debemos cerrarlo en conjunto. | T17: 15
A18: Operativos | B18: Producto | C18: Claudia Barroso | E18: SEGUROS NOMINA Y PERS | F18: CUP -- CUP | G18: NA | H18: NA | K18: Backlog | L18: NA | M18: NA | N18: NA | T18: 16
A19: Adicionales | B19: Tesorería | C19: Eduardo Cabral | D19: CERRADA | E19: SECCION 2E | F19: Layouts Garantias de Liquidez -- GL | G19: Pendiente | H19: Modulo de tesoreria | I19: NTT | K19: Envío Vacio | L19: NA | M19: NA | N19: NA | O19: Calificaciones Otorgadas (No aplica confirma Denisse) | P19: Finanzas | Q19: No aplica | R19: Comentario Bajaware: Si no cuentan con las operaciones a las que se refiere ese layout, no es necesario llenarlo. Sin embargo, si Banxico da de alta el producto en el portal de Espifnet, tendrían que enviarlo vacío. | T19: 17
A20: Adicionales | B20: Tesorería | C20: Eduardo Cabral | D20: CERRADA | E20: SECCION 2D | F20: Layouts Garantias de Liquidez -- GL | G20: Pendiente | H20: Modulo de tesoreria | I20: NTT | K20: Envío Vacio | L20: NA | M20: NA | N20: NA | O20: Inmuebles | P20: Finanzas/Contabilidad/WO | Q20: No aplica | R20: Comentario Bajaware: Si no cuentan con las operaciones a las que se refiere ese layout, no es necesario llenarlo. Sin embargo, si Banxico da de alta el producto en el portal de Espifnet, tendrían que enviarlo vacío. | T20: 18
A21: Adicionales | B21: Tesorería | C21: Eduardo Cabral | D21: CERRADA | E21: SECCION 2C | F21: Layouts Garantias de Liquidez -- GL | G21: Pendiente | H21: Modulo de tesoreria | I21: NTT | K21: Envío Vacio | L21: NA | M21: NA | N21: NA | O21: Acciones | P21: Tesoreria | Q21: No aplica | R21: Comentario Bajaware: Si no cuentan con las operaciones a las que se refiere ese layout, no es necesario llenarlo. Sin embargo, si Banxico da de alta el producto en el portal de Espifnet, tendrían que enviarlo vacío. | T21: 19
A22: Adicionales | B22: Tesorería | C22: Eduardo Cabral | D22: CERRADA | E22: SECCION 2B | F22: Layouts Garantias de Liquidez -- GL | G22: Pendiente | H22: Modulo de tesoreria | I22: NTT | K22: Envío Vacio | L22: NA | M22: NA | N22: NA | O22: Cartera de Créditos | P22: Operaciones | Q22: No aplica | R22: Comentario Bajaware: Si no cuentan con las operaciones a las que se refiere ese layout, no es necesario llenarlo. Sin embargo, si Banxico da de alta el producto en el portal de Espifnet, tendrían que enviarlo vacío. | T22: 20
A23: Adicionales | B23: Tesorería | C23: Eduardo Cabral | D23: CERRADA | E23: SECCION 2A | F23: Layouts Garantias de Liquidez -- GL | G23: Pendiente | H23: Modulo de tesoreria | I23: NTT | K23: Envío Vacio | L23: NA | M23: NA | N23: NA | O23: Cartera de Valores | P23: Tesoreria | Q23: No aplica | R23: Comentario Bajaware: Si no cuentan con las operaciones a las que se refiere ese layout, no es necesario llenarlo. Sin embargo, si Banxico da de alta el producto en el portal de Espifnet, tendrían que enviarlo vacío. | T23: 21
A24: Adicionales | B24: Tesorería | C24: Eduardo Cabral | D24: CERRADA | E24: SECCION 1 | F24: Layouts Garantias de Liquidez -- GL | G24: Pendiente | H24: Modulo de tesoreria | I24: NTT | K24: Envío Vacio | L24: NA | M24: NA | N24: NA | O24: Layouts Garantias de Liquidez | P24: Financiamiento | Q24: No aplica | R24: Comentario Bajaware: Si no cuentan con las operaciones a las que se refiere ese layout, no es necesario llenarlo. Sin embargo, si Banxico da de alta el producto en el portal de Espifnet, tendrían que enviarlo vacío. | T24: 22
A25: Adicionales | B25: Tesorería | C25: Eduardo Cabral | D25: MAPEO | E25: REPORTOS_MNME | F25: Layout_REPORTOS_MN_ME_V7_2024 -- REPORTOS | G25: Pendiente | H25: Modulo de tesoreria | I25: NTT | K25: US-Mapeo | L25: Ext NTT | M25: Int Tesoreria | N25: Tesoreria | O25: Layout_REPORTOS_MN_ME_V7 -- REPORTOS | P25: modif nomb layout | T25: 23 | W25: 46056 | X25: 46087 | Y25: 46083 | Z25: 46122 | AA25: 46111 | AB25: 46136 | AC25: 46118 | AD25: 46136 | AE25: 46125 | AF25: 46150 | AG25: 46139 | AH25: 46171
A26: Cartera | B26: Operaciones Credito | C26: Luis Alberto | E26: REL_CONSUMO_GARANTIA | F26: V1.05_Credito_IFRS9_Consumo_Completo VF (2) | G26: NA | H26: NA | K26: Backlog | L26: NA | M26: NA | N26: NA | T26: 24
A27: Operativos | B27: Producto | C27: Claudia Barroso | D27: VOBO US | E27: Registro Gral Prd | F27: CUP -- CUP | G27: Listo | H27: VoBo Dado por el usuario (No se cuenta con informacion) | I27: Estructura | K27: US-VoBo | M27: Interno | N27: Producto | T27: 25 | AE27: 46076 | AF27: 46101 | AG27: 46104 | AH27: 46129
A28: Captacion | B28: Producto | C28: Claudia Barroso | D28: DESARROLLO | E28: RECO | F28: Layout RECO BW -- RECO | G28: Listo | H28: Ntt, ya se reviso txt por usuario VoBo | I28: Estructura y universo | J28: Se reasignó a Prodcuto | estaba identificado como VoBo Usuario | K28: DES-Desarrollo Txt | M28: Interno | N28: TI | O28: Se menciona a NTT | P28: Validar la parte de captación NTT para integrar en un solo reporte | S28: x | T28: 26 | Y28: 46056 | Z28: 46080 | AA28: 46083 | AB28: 46108 | AC28: 46107 | AD28: 46108 | AE28: 46111 | AF28: 46136 | AG28: 46139 | AH28: 46164
A29: Situacion Finaciera | B29: Contabilidad | C29: Ramon Jaimes | D29: VOBO US | E29: RECLASIFICACIONES | F29: R10_RECLASIFICACIONES -- R10 | G29: Listo | H29: Revision de txt por parte del usuario | I29: Estructura y universo | J29: Duda US ¿Cuál sería la mecánica para la generación de este reporte? | K29: US-VoBo | M29: Interno | N29: Contabilidad | T29: 27 | AE29: 46076 | AF29: 46101 | AG29: 46104 | AH29: 46129
A30: Operativos | B30: Operaciones Captacion | C30: Luis Alberto | D30: CERRADA | E30: RECLAMACIONES BURSATILES BM | F30: R2711_ReclamacionesB_V0.4 | G30: NA | H30: NA | K30: Backlog | L30: NA | M30: NA | N30: NA | O30: Estaba asiugnado a NTT | T30: 28
A31: Adicionales | B31: UNE | C31: Martin Roman | D31: MAPEO | E31: RECLAMACIONES | F31: LAYOUT R27_V1 -- R27 - 2701 | G31: No mapeado | K31: US-Mapeo | M31: Interno | N31: UNE | T31: 29 | W31: 46056 | X31: 46094 | Y31: 46097 | Z31: 46115 | AA31: 46118 | AB31: 46129 | AC31: 46128 | AD31: 46129 | AE31: 46132 | AF31: 46150 | AG31: 46153 | AH31: 46171
A32: Adicionales | B32: Contabilidad | C32: Ramon Jaimes | D32: VOBO US | E32: R36_PAGOS_ANT_CARGOS_DIF | F32: V1.00_R3601_CARGOS_DIF_PAGOS_ANTICIPADOS -- R36 3601 | G32: Por iniciar | H32: Se requiere recepcion de requerimiento y Excel. (Usuario) | K32: US-VoBo | M32: Interno | N32: Contabilidad | T32: 30 | AE32: 46076 | AF32: 46101 | AG32: 46104 | AH32: 46129
A33: Adicionales | B33: Riesgos | C33: Homero Sanchez | D33: MAPEO | E33: R35_1 | F33: Layout R35_1 -- R35 | G33: No mapeado | H33: Se tiene que realizar una vez migrado a Banco | se puede mapear la cartera de creditos -- Riesgos / Exp Valores Transac -- Tesoreria | I33: Estructura y universo | K33: US-Mapeo | M33: Interno | N33: Riesgos | T33: 31 | AE33: 46111 | AF33: 46136 | AG33: 46139 | AH33: 46157
A34: Adicionales | B34: Operaciones Captacion | C34: Luis Alberto | D34: CERRADA | E34: R26OPE | F34: R26 Comisionistas -- R26 2610 2611 2612 2616 | G34: No mapeado | H34: NTT | K34: Envío Vacio | L34: NA | M34: NA | N34: NA | O34: Acuerdo con Erika el 18/12/24. No aplica en este momento, porque no tendremos nada de lo que solicita. | Q34: No aplica | R34: Actualmente no tenemos comisionistas, esta información no se puede generar por el momento, nosotros decimos que no nos aplica, pero debemos cerrarlo en conjunto. | T34: 32
A35: Adicionales | B35: Operaciones Captacion | C35: Luis Alberto | D35: CERRADA | E35: R26_MODULO | F35: R26 Comisionistas -- R26 2610 2611 2612 2615 | G35: No mapeado | H35: NTT | K35: Envío Vacio | L35: NA | M35: NA | N35: NA | O35: Acuerdo con Erika el 18/12/24. No aplica en este momento, porque no tendremos nada de lo que solicita. | Q35: No aplica | R35: Actualmente no tenemos comisionistas, esta información no se puede generar por el momento, nosotros decimos que no nos aplica, pero debemos cerrarlo en conjunto. | T35: 33
A36: Adicionales | B36: Operaciones Captacion | C36: Luis Alberto | D36: CERRADA | E36: R26_COMISIONISTA | F36: R26 Comisionistas -- R26 2610 2611 2612 2614 | G36: No mapeado | H36: NTT | K36: Envío Vacio | L36: NA | M36: NA | N36: NA | O36: Acuerdo con Erika el 18/12/24. No aplica en este momento, porque no tendremos nada de lo que solicita. | Q36: No aplica | R36: Actualmente no tenemos comisionistas, esta información no se puede generar por el momento, nosotros decimos que no nos aplica, pero debemos cerrarlo en conjunto. | T36: 34
A37: Adicionales | B37: Operaciones Captacion | C37: Luis Alberto | D37: CERRADA | E37: R26_ADMINISTRADOR | F37: R26 Comisionistas -- R26 2610 2611 2612 2613 | G37: No mapeado | H37: NTT | K37: Envío Vacio | L37: NA | M37: NA | N37: NA | O37: Acuerdo con Erika el 18/12/24. No aplica en este momento, porque no tendremos nada de lo que solicita. | Q37: No aplica | R37: Actualmente no tenemos comisionistas, esta información no se puede generar por el momento, nosotros decimos que no nos aplica, pero debemos cerrarlo en conjunto. | T37: 35
A38: Operativos | B38: Operaciones Captacion | C38: Luis Alberto | D38: DESARROLLO | E38: R2441_42 | F38: Layout R2441_42_V2 --R2441 - R2442 | G38: No mapeado | H38: NTT | K38: DES-Desarrollo Txt | L38: Ext NTT | M38: Externo | N38: Operaciones | O38: Este TXT ya fue entregado por NTT el 16/06 y te pase la guía para bajarlo de Transat el 27/10/25. Aún no lo conectan a ATOM. | S38: x | T38: 36 | Y38: 46056 | Z38: 46073 | AA38: 46076 | AB38: 46094 | AC38: 46093 | AD38: 46094 | AE38: 46097 | AF38: 46115 | AG38: 46118 | AH38: 46136
A39: Operativos | B39: Operaciones Captacion | C39: Arturo Angeles | D39: MAPEO | E39: R2431 | F39: Layout R2431_V4 -- R24 C2431 | G39: No mapeado | H39: NTT | J39: • El 18/12/24 le indicamos al PMO que este Layout no correspondía a Operaciones. • Nuevamente en la reunión del 23/07/25 volvimos a pedir que lo asignaran y el acuerdo fue el siguiente: "Contabilidad se lleva a revisar el Layout y si hacen faltan campos se investiga lo que hace falta. Tanto crédito como captación", Sharon le iba a dar seguimiento. • Es urgente que lo asignen, anexo minuta del 23/07/25. | K39: US-Mapeo | L39: Ext NTT | M39: Externo | N39: Finanzas | O39: Asignado a Captación | P39: El Layout R24 Serie C, no le corresponde a Operaciones, solicita información de partes relacionadas que nosotros no tenemos, favor de revisar a fondo y determinar qué área lo debe llenar. | S39: x | T39: 37 | W39: 46056 | X39: 46080 | Y39: 46083 | Z39: 46108 | AA39: 46111 | AB39: 46122 | AC39: 46121 | AD39: 46122 | AE39: 46125 | AF39: 46143 | AG39: 46146 | AH39: 46157
A40: Cartera | B40: Operaciones Credito | C40: Luis Alberto | D40: DESARROLLO | E40: R04A_SALDOS | F40: V1.01_Credito_IFRS9_R04A -- A0411 - A0417 - A0419 - A0420 - A0424 | G40: Listo | H40: Se tiene la estructura construida y se integraron los datos con los que se cuenta, aun no se cuenta con todo el universo(Fuentes externas | I40: Estructura | K40: DES-Desarrollo Txt | M40: Interno | N40: TI | T40: 38 | Y40: 46056 | Z40: 46080 | AA40: 46083 | AB40: 46108 | AC40: 46107 | AD40: 46108 | AE40: 46111 | AF40: 46136 | AG40: 46139 | AH40: 46164
A41: Cartera | B41: Operaciones Captacion y credito | C41: Luis Alberto | D41: MAPEO | E41: R04A_MOV_420_24 | F41: V1.01_Credito_IFRS9_R04A -- A0411 - A0417 - A0419 - A0420 - A0424 - R04A_MOV_420_24 | G41: Mapeado incompleto | I41: Estructura y universo | J41: Falta info de Contabilidad | K41: US-Mapeo | M41: Interno | N41: Contabilidad | T41: 39 | W41: 46056 | X41: 46073 | Y41: 46076 | Z41: 46094 | AA41: 46097 | AB41: 46108 | AC41: 46107 | AD41: 46108 | AE41: 46111 | AF41: 46129 | AG41: 46132 | AH41: 46150
A42: Cartera | B42: Contabilidad | C42: Ramon Jaimes | D42: DESARROLLO | E42: R04A_MOV_419 | F42: V1.01_Credito_IFRS9_R04A -- A0411 - A0417 - A0419 - A0420 - A0424 - R04A_MOV_419 | G42: Mapeado incompleto | I42: Estructura y universo | J42: Reasignado a Contabilidad | K42: DES-Desarrollo Txt | M42: Interno | N42: Contabilidad | T42: 40 | Y42: 46056 | Z42: 46080 | AA42: 46083 | AB42: 46108 | AC42: 46107 | AD42: 46108 | AE42: 46111 | AF42: 46136 | AG42: 46139 | AH42: 46164
A43: Adicionales | B43: Tesorería | C43: Eduardo Cabral | D43: CERRADA | E43: R03 E-0305 ÓRDENES | F43: layout R03-0304-0305 E BM -- R04 | G43: Pendiente | H43: Modulo de tesoreria | I43: NTT | K43: Envío Vacio | L43: NA | M43: NA | N43: NA | Q43: No aplica | R43: Hace referencia a operaciones con clientes, las cuales no se llevarán a cabo | T43: 41
A44: Adicionales | B44: Tesorería | C44: Eduardo Cabral | D44: CERRADA | E44: R03 E-0304 ASIGNACIONES BM | F44: layout R03-0304-0305 E BM -- R03 | G44: Pendiente | H44: Modulo de tesoreria | I44: NTT | K44: Envío Vacio | L44: NA | M44: NA | N44: NA | Q44: No aplica | R44: Hace referencia a operaciones con clientes, las cuales no se llevarán a cabo | T44: 42
A45: Operativos | B45: Operaciones Captacion | C45: Luis Alberto | D45: DESARROLLO | E45: PRODUCTOS CAPTACION CNBV | F45: R2421_Prod Cap -- R2421 | G45: No mapeado | H45: NTT | K45: DES-Desarrollo Txt | L45: Ext NTT | M45: Externo | N45: Operaciones | O45: Este TXT ya fue entregado por NTT el 28/05 y te pase la guía para bajarlo de Transat el 27/10/25. Aún no lo conectan a ATOM. | S45: x | T45: 43 | Y45: 46056 | Z45: 46073 | AA45: 46076 | AB45: 46094 | AC45: 46093 | AD45: 46094 | AE45: 46097 | AF45: 46115 | AG45: 46118 | AH45: 46136
A46: Adicionales | B46: Tesorería | C46: Eduardo Cabral | D46: CERRADA | E46: PRESTAMO DE VALORES | F46: PRESTAMO DE VALORES_V0.1 -- PRESTAMOS | G46: Pendiente | H46: Modulo de tesoreria | I46: NTT | K46: Envío Vacio | L46: NA | M46: NA | N46: NA | Q46: No Aplica | R46: No habrá Prestamos en Valores | T46: 44
A47: Cartera | B47: Operaciones Credito | C47: Luis Alberto | D47: DESARROLLO | E47: PERSONA | F47: V1.05_Layouts CREDITO Bancos IFRS (Comercial) (1) | G47: Listo | H47: Se tiene la estructura construida y se integraron los datos con los que se cuenta, aun no se cuenta con todo el universo(Fuentes externas Pantalla comercial y cualitativa individual) | I47: Estructura | K47: DES-Desarrollo Txt | M47: Interno | N47: TI | T47: 45 | Y47: 46056 | Z47: 46080 | AA47: 46083 | AB47: 46108 | AC47: 46107 | AD47: 46108 | AE47: 46111 | AF47: 46136 | AG47: 46139 | AH47: 46164
A48: Operativos | B48: Producto | C48: Claudia Barroso | E48: PENALIZACIONES NOMINA Y PERS | F48: CUP -- CUP | G48: NA | H48: NA | K48: Backlog | L48: NA | M48: NA | N48: NA | T48: 46
A49: Cartera | B49: Operaciones Credito | C49: Luis Alberto | D49: DESARROLLO | E49: PAGOS_EXIGIBLES | F49: V1.05_Credito_IFRS9_Consumo_Completo VF (2) | G49: Listo | H49: Se tiene la estructura construida y se integraron los datos con los que se cuenta, aun no se cuenta con todo el universo(Fuentes externas | I49: Estructura | K49: DES-Desarrollo Txt | M49: Interno | N49: TI | T49: 47 | Y49: 46056 | Z49: 46080 | AA49: 46083 | AB49: 46108 | AC49: 46107 | AD49: 46108 | AE49: 46111 | AF49: 46136 | AG49: 46139 | AH49: 46164
A50: Captacion | B50: Operaciones Captacion | C50: Arturo Angeles | D50: CERRADA | E50: OperacionesOEMN | F50: LayoutOEMN_v3 | G50: No mapeado | H50: NTT | K50: Envío Vacio | L50: NA | M50: NA | N50: NA | O50: No se realizaran operaciones en efectivo | Q50: No aplica | R50: Comentario Bajaware: Con respecto a lo que comentas sobre la falta de operaciones en traslado y manejo de efectivo, no sería necesario enviar el layout; sin embargo, de acuerdo con el artículo 48 de la LIC, éste debe presentarse vacío. | T50: 48
A51: Adicionales | B51: Captacion | C51: Arturo Angeles | D51: MAPEO | E51: OPERACIONES DE CLIENTES BE | F51: R1523_24_OPERACIONES DE CLIENTES BE_V0.4 -- R15 1523 1524 | G51: No mapeado | K51: US-Mapeo | M51: Interno | N51: Finanzas | T51: 49 | W51: 46056 | X51: 46080 | Y51: 46083 | Z51: 46108 | AA51: 46111 | AB51: 46122 | AC51: 46121 | AD51: 46122 | AE51: 46125 | AF51: 46143 | AG51: 46146 | AH51: 46157
A52: Operativos | B52: Producto | C52: Claudia Barroso | E52: Moratoria CNR | F52: CUP -- CUP | G52: NA | H52: NA | K52: Backlog | L52: NA | M52: NA | N52: NA | T52: 50
A53: Adicionales | B53: Tesorería | C53: Eduardo Cabral | D53: MAPEO | E53: MODIF_TASAPREMIO | F53: Layout_REPORTOS_MN_ME_V7_2024 -- REPORTOS | G53: Pendiente | H53: Modulo de tesoreria | I53: NTT | K53: US-Mapeo | L53: Ext NTT | M53: Int Tesoreria | N53: Tesoreria | O53: Layout_REPORTOS_MN_ME_V7 -- REPORTOS | P53: modif nomb layout | T53: 51 | W53: 46056 | X53: 46087 | Y53: 46083 | Z53: 46122 | AA53: 46111 | AB53: 46136 | AC53: 46118 | AD53: 46136 | AE53: 46125 | AF53: 46150 | AG53: 46139 | AH53: 46171
A54: Adicionales | B54: Riesgos y tesoreria | C54: Homero Sanchez | D54: BW-EJECUCION | E54: MERCANCIAS_RC | F54: LAYOUT MERCANCIAS_RCS -- RC17 | G54: No mapeado | H54: Lo trabaja Bajaware | K54: BW-Ejecucion | L54: Ext Bajaware | M54: Externo | N54: BajaWare | T54: 52 | AE54: 46083 | AF54: 46101 | AG54: 46104 | AH54: 46122
A55: Captacion | B55: Producto | C55: Claudia Barroso | D55: VOBO US | E55: MDEF_SUC Y CAJAS GRALES | F55: Layouts MDEF -- MDEF | G55: Listo | H55: VoBo Dado por el usuario (No se cuenta con informacion) | I55: Estructura | K55: US-VoBo | M55: Interno | N55: Producto | T55: 53 | AE55: 46076 | AF55: 46101 | AG55: 46104 | AH55: 46129
A56: Captacion | B56: Producto | C56: Claudia Barroso | E56: MDEF_CAJEROS PROPIOS | F56: Layouts MDEF -- MDEF | G56: NA | H56: NA | K56: Backlog | L56: NA | M56: NA | N56: NA | T56: 54
A57: Captacion | B57: Producto | C57: Claudia Barroso | E57: MDEF_CAJEROS EXTERNOS | F57: Layouts MDEF -- MDEF | G57: NA | H57: NA | K57: Backlog | L57: NA | M57: NA | N57: NA | T57: 55
A58: Captacion | B58: Producto | C58: Claudia Barroso | E58: MDEF_BOVEDAS PROPIAS | F58: Layouts MDEF -- MDEF | G58: NA | H58: NA | K58: Backlog | L58: NA | M58: NA | N58: NA | T58: 56
A59: Captacion | B59: Producto | C59: Claudia Barroso | E59: MDEF_BOVEDAS EXTERNAS | F59: Layouts MDEF -- MDEF | G59: NA | H59: NA | K59: Backlog | L59: NA | M59: NA | N59: NA | T59: 57
A60: Cartera | B60: Operaciones Credito | C60: Luis Alberto | D60: DESARROLLO | E60: LINEA CREDITO | F60: V1.05_Layouts CREDITO Bancos IFRS (Comercial) (1) | G60: Listo | H60: Se tiene la estructura construida y se integraron los datos con los que se cuenta, aun no se cuenta con todo el universo(Fuentes externas Pantalla comercial) | I60: Estructura | K60: DES-Desarrollo Txt | M60: Interno | N60: TI | T60: 58 | Y60: 46056 | Z60: 46080 | AA60: 46083 | AB60: 46108 | AC60: 46107 | AD60: 46108 | AE60: 46111 | AF60: 46136 | AG60: 46139 | AH60: 46164
A61: Situacion Finaciera | B61: Contabilidad | C61: Ramon Jaimes | D61: VOBO US | E61: INVERSIONES PERMANENTES | F61: R1230_Contables_IFRS9_Inversiones_Permanentes_V1 | G61: Por iniciar | H61: Se requiere recepcion de requerimiento y Excel. (Usuario) | J61: Excel confirmado como fuente | K61: US-VoBo | M61: Interno | N61: Contabilidad | O61: Validar estructura de archivos Excel para que sea igual a columnas tablas destino | P61: Complementar archivo cofiguracion Lambda con estructura tablas | T61: 59 | AE61: 46076 | AF61: 46094 | AG61: 46097 | AH61: 46115
A62: Situacion Finaciera | B62: Contabilidad | C62: Ramon Jaimes | D62: VOBO US | E62: INTEGRACION ACCIONARIA | F62: R1411_INT. ACC -- R1411 | G62: Listo | H62: Revision de txt por parte del usuario | I62: Estructura y universo | J62: Falta VoBo ultima Modif decimales col 13 | K62: US-VoBo | M62: Interno | N62: Contabilidad | T62: 60 | AE62: 46076 | AF62: 46101 | AG62: 46104 | AH62: 46129
A63: Adicionales | B63: Operaciones Captacion | C63: Luis Alberto | E63: INFIMP | F63: Layout INFIMP -- INFIMP | G63: NA | H63: NA | K63: Backlog | L63: NA | M63: NA | N63: NA | T63: 61
A64: Situacion Finaciera | B64: Contabilidad | C64: Ramon Jaimes | D64: VOBO US | E64: IMPUESTOS | F64: R07_Imp Dif -- R07 | G64: Listo | H64: Se requiere recepcion de requerimiento y Excel. (Usuario) | J64: Duda US ¿Cuál sería la mecánica para la generación de este reporte? | K64: US-VoBo | M64: Interno | N64: Contabilidad | T64: 62 | AE64: 46076 | AF64: 46101 | AG64: 46104 | AH64: 46129
A65: Cartera | B65: Operaciones Credito | C65: Luis Alberto | D65: DESARROLLO | E65: HIPOTECARIO | F65: V1.05_Layouts CREDITO Bancos IFRS (Hipotecario Simplificado) (1)- HIPOTECARIO | G65: Listo | H65: Se tiene la estructura construida y se integraron los datos con los que se cuenta, aun no se cuenta con todo el universo(Fuentes externas | I65: Estructura | K65: DES-Desarrollo Txt | M65: Interno | N65: TI | T65: 63 | Y65: 46056 | Z65: 46080 | AA65: 46083 | AB65: 46108 | AC65: 46107 | AD65: 46108 | AE65: 46111 | AF65: 46136 | AG65: 46139 | AH65: 46164
A66: Cartera | B66: Operaciones Credito | C66: Luis Alberto | E66: GARANTIA_CONSUMO | F66: V1.05_Credito_IFRS9_Consumo_Completo VF (2) | G66: NA | H66: NA | K66: Backlog | L66: NA | M66: NA | N66: NA | T66: 64
A67: Cartera | B67: Operaciones Credito | C67: Luis Alberto | D67: DESARROLLO | E67: GARANTIA | F67: V1.05_Layouts CREDITO Bancos IFRS (Comercial) (1) | G67: Listo | H67: Se tiene la estructura construida y se integraron los datos con los que se cuenta, aun no se cuenta con todo el universo(Fuentes externas Pantalla comercial) | I67: Estructura | J67: PRELACION_GAR campo pendiente MAPEO | US revisa info restante | K67: DES-Desarrollo Txt | M67: Interno | N67: Riesgos | T67: 65 | Y67: 46062 | Z67: 46073 | AA67: 46076 | AB67: 46087 | AC67: 46086 | AD67: 46087 | AE67: 46090 | AF67: 46108 | AG67: 46111 | AH67: 46129
A68: Adicionales | B68: Riesgos y tesoreria | C68: Homero Sanchez | D68: ASIGNA | E68: GAMMA_VEGA | F68: LAYOUT GAMMA_VEGA_V2 -- RC18 | G68: No mapeado | H68: Lo trabaja Bajaware | K68: Valida Areas | L68: Ext Bajaware | M68: Interno | N68: Riesgos | T68: 66 | U68: 46056 | V68: 46059 | W68: 46062 | X68: 46080 | Y68: 46083 | Z68: 46101 | AA68: 46104 | AB68: 46122 | AC68: 46121 | AD68: 46122 | AE68: 46125 | AF68: 46143 | AG68: 46146 | AH68: 46164
A69: Captacion | B69: Operaciones Captacion | C69: Luis Alberto | D69: DESARROLLO | E69: FT_TPA | F69: Layout TPA BW_v2 -- TPA | G69: Pendiente | H69: Modulo de tesoreria | I69: Estructura | J69: VoBo sobre estructura | K69: DES-Desarrollo Txt | L69: Ext NTT | M69: Interno | N69: TI | S69: x | T69: 67 | Y69: 46056 | Z69: 46073 | AA69: 46076 | AB69: 46094 | AC69: 46093 | AD69: 46094 | AE69: 46097 | AF69: 46115 | AG69: 46118 | AH69: 46136
A70: Mercados | B70: Tesorería | C70: Eduardo Cabral | D70: MAPEO | E70: FT_TENENCIA | F70: LayoutTenencia_V2 -- TENENCIA - REPORTOS | G70: Pendiente | H70: Modulo de tesoreria | I70: NTT | K70: US-Mapeo | L70: Ext NTT | M70: Int Tesoreria | N70: Tesoreria | T70: 68 | W70: 46056 | X70: 46087 | Y70: 46083 | Z70: 46122 | AA70: 46111 | AB70: 46136 | AC70: 46118 | AD70: 46136 | AE70: 46125 | AF70: 46150 | AG70: 46139 | AH70: 46171
A71: Mercados | B71: Tesorería | C71: Eduardo Cabral | D71: MAPEO | E71: FT_REPORTOS_CDA | F71: Layout_REPORTOS_CDA -- REPORTOS | G71: Pendiente | H71: Modulo de tesoreria | I71: NTT | J71: Marcados originalmente como NA | K71: US-Mapeo | L71: Ext NTT | M71: Int Tesoreria | N71: Tesoreria | T71: 69 | W71: 46056 | X71: 46087 | Y71: 46083 | Z71: 46122 | AA71: 46111 | AB71: 46136 | AC71: 46118 | AD71: 46136 | AE71: 46125 | AF71: 46150 | AG71: 46139 | AH71: 46171
A72: Mercados | B72: Tesorería | C72: Eduardo Cabral | D72: MAPEO | E72: FT_REPORTOS | F72: Layout_REPORTOS_MN_ME_V3 | G72: Pendiente | H72: Modulo de tesoreria | I72: NTT | K72: US-Mapeo | L72: Ext NTT | M72: Int Tesoreria | N72: Tesoreria | T72: 70 | W72: 46056 | X72: 46087 | Y72: 46083 | Z72: 46122 | AA72: 46111 | AB72: 46136 | AC72: 46118 | AD72: 46136 | AE72: 46125 | AF72: 46150 | AG72: 46139 | AH72: 46171
A73: Operativos | B73: Operaciones Captacion | C73: Luis Alberto | D73: CERRADA | E73: FT_R2911 | F73: Layout R29 V2 -- R2911 | G73: No mapeado | H73: NTT | K73: Envío Vacio | L73: NA | M73: NA | N73: NA | O73: Acuerdo con Erika el 18/12/24. No aplica en este momento por que este Layout es a la medida, por cada caso, con información de contraloría, en Transact no tendremos nada. | Q73: No aplica | R73: Operaciones señala que este Layout es exclusivo de captación, no entendemos porque lo marcan que aplica para crédito //No trabajado por NTT. No vemos de donde obtener esta información del sistema actual ni futuro. El reporte nos pide la información de requerimientos de aseguramientos solicitados por la autoridad ministerial, hacendaria, fiscal, judicial o laboral; así como los datos del titular y cotitular a quién se aplicará el requerimiento y de la cuenta de nómina, mercado abierto u otra modalidad. Debemos ver en conjunto primero que área tiene los datos y segundo si nos aplicará o no. | S73: x | T73: 71
A74: Mercados | B74: Tesorería | C74: Eduardo Cabral | D74: CERRADA | E74: FT_PAC_II | F74: Layout_PACII_V1 -- PAC | G74: NA | H74: Modulo de tesoreria | I74: NTT | K74: Backlog | L74: NA | M74: NA | N74: NA | O74: Layout_PACII_V1 -- PAC RC05 | P74: nombre layout modifcado | Q74: No Aplica | T74: 72
A75: Mercados | B75: Tesorería | C75: Eduardo Cabral | D75: MAPEO | E75: FT_CVT_TR | F75: Layout_CVT_TR_V2 | G75: Pendiente | H75: Modulo de tesoreria | I75: NTT | K75: US-Mapeo | L75: Ext NTT | M75: Int Tesoreria | N75: Tesoreria | T75: 73 | W75: 46056 | X75: 46087 | Y75: 46083 | Z75: 46122 | AA75: 46111 | AB75: 46136 | AC75: 46118 | AD75: 46136 | AE75: 46125 | AF75: 46150 | AG75: 46139 | AH75: 46171
A76: Mercados | B76: Tesorería | C76: Eduardo Cabral | D76: MAPEO | E76: FT_CVT_IN | F76: Layout_CVT_IN_V2 -- CVT | G76: Pendiente | H76: Modulo de tesoreria | I76: NTT | K76: US-Mapeo | L76: Ext NTT | M76: Int Tesoreria | N76: Tesoreria | T76: 74 | W76: 46056 | X76: 46087 | Y76: 46083 | Z76: 46122 | AA76: 46111 | AB76: 46136 | AC76: 46118 | AD76: 46136 | AE76: 46125 | AF76: 46150 | AG76: 46139 | AH76: 46171
A77: Mercados | B77: Tesorería | C77: Eduardo Cabral | D77: MAPEO | E77: FT_CVT | F77: Layout_CVT_MN_ME_V3 -- CVT - RCs - TENENCIA | G77: Pendiente | H77: Modulo de tesoreria | I77: NTT | K77: US-Mapeo | L77: Ext NTT | M77: Int Tesoreria | N77: Tesoreria | T77: 75 | W77: 46056 | X77: 46087 | Y77: 46083 | Z77: 46122 | AA77: 46111 | AB77: 46136 | AC77: 46118 | AD77: 46136 | AE77: 46125 | AF77: 46150 | AG77: 46139 | AH77: 46171
A78: Adicionales | B78: Finanzas | C78: Arturo Angeles | D78: MAPEO | E78: FT_ACLME_X | F78: Layout ACLME_X_V1 -- ACLME | G78: Pendiente | H78: Modulo de tesoreria | I78: NTT | K78: US-Mapeo | L78: Ext NTT | M78: Int Tesoreria Add | N78: Finanzas | T78: 76 | W78: 46056 | X78: 46094 | Y78: 46097 | Z78: 46122 | AA78: 46125 | AB78: 46136 | AC78: 46135 | AD78: 46136 | AE78: 46139 | AF78: 46157 | AG78: 46160 | AH78: 46171
A79: Situacion Finaciera | B79: Contabilidad | C79: Ramon Jaimes | D79: VOBO US | E79: FLUJOS Y VARIACIONES | F79: R13A_FLUJOS Y VARIACIONES -- R13A | G79: Por iniciar | H79: Se requiere recepcion de requerimiento y Excel. (Usuario) | J79: US envía Difs 20250901 | K79: US-VoBo | M79: Interno | N79: Contabilidad | T79: 77 | AE79: 46076 | AF79: 46101 | AG79: 46104 | AH79: 46129
A80: Riesgos | B80: Riesgos | C80: Homero Sanchez | D80: BW-EJECUCION | E80: FILE_TITULOS_DEUDA | F80: LAYOUTS_RCS_v2 -- RC01 - RC03 - RC04 - RC07 - RC08 - RC02 - RC06A | G80: No mapeado | H80: Lo trabaja Bajaware | K80: BW-Ejecucion | L80: Ext Bajaware | M80: Externo | N80: BajaWare | T80: 78 | AE80: 46083 | AF80: 46101 | AG80: 46104 | AH80: 46122
A81: Adicionales | B81: Finanzas | C81: Arturo Angeles | D81: MAPEO | E81: FILE_TIPOCAMBIO_DIARIO | F81: Layout_Tipos de Cambio Diario_v2 -- ACLME | G81: Pendiente | H81: Modulo de tesoreria | I81: NTT | K81: US-Mapeo | L81: Ext NTT | M81: Int Tesoreria Add | N81: Finanzas | T81: 79 | W81: 46056 | X81: 46094 | Y81: 46097 | Z81: 46122 | AA81: 46125 | AB81: 46136 | AC81: 46135 | AD81: 46136 | AE81: 46139 | AF81: 46157 | AG81: 46160 | AH81: 46171
A82: Mercados | B82: Tesorería | C82: Eduardo Cabral | D82: MAPEO | E82: FILE_TENENCIA_PRECIO | F82: CORE_LayoutTenenciaAdicional_v3.2 -- TENENCIA | G82: Pendiente | H82: Modulo de tesoreria | I82: NTT | K82: US-Mapeo | L82: Ext NTT | M82: Int Tesoreria | N82: Tesoreria | T82: 80 | W82: 46056 | X82: 46087 | Y82: 46083 | Z82: 46122 | AA82: 46111 | AB82: 46136 | AC82: 46118 | AD82: 46136 | AE82: 46125 | AF82: 46150 | AG82: 46139 | AH82: 46171
A83: Captacion | B83: Operaciones Captacion | C83: Luis Alberto | D83: DESARROLLO | E83: FILE_SISPAGOS | F83: Layout SISPAGOS BW -- SISPAGOS | G83: Listo | H83: Ntt, ya se reviso txt por usuario VoBo Estructura | I83: Estructura y universo | K83: DES-Desarrollo Txt | L83: Ext NTT | M83: Interno | N83: TI | O83: Se requiera info actualizada congelando sistema para validacion | S83: x | T83: 81 | Y83: 46056 | Z83: 46073 | AA83: 46076 | AB83: 46094 | AC83: 46093 | AD83: 46094 | AE83: 46097 | AF83: 46115 | AG83: 46118 | AH83: 46136
A84: Riesgos | B84: Riesgos | C84: Homero Sanchez | D84: ASIGNA | E84: FILE_RC19_INSUMO | F84: LAYOUTS_RCS_v2 -- RC01 - RC03 - RC04 - RC07 - RC08 - RC02 - RC06A | G84: No mapeado | H84: Lo trabaja Bajaware | K84: Valida Areas | L84: Ext Bajaware | M84: Interno | N84: Riesgos | T84: 82 | U84: 46056 | V84: 46059 | W84: 46062 | X84: 46080 | Y84: 46083 | Z84: 46101 | AA84: 46104 | AB84: 46122 | AC84: 46121 | AD84: 46122 | AE84: 46125 | AF84: 46143 | AG84: 46146 | AH84: 46164
A85: Riesgos | B85: Riesgos | C85: Homero Sanchez | D85: ASIGNA | E85: FILE_RC08_INT_ACC | F85: LAYOUTS_RCS_v2 -- RC01 - RC03 - RC04 - RC07 - RC08 - RC02 - RC06A | G85: No mapeado | H85: Lo trabaja Bajaware | K85: Valida Areas | L85: Ext Bajaware | M85: Interno | N85: Riesgos | T85: 83 | U85: 46056 | V85: 46059 | W85: 46062 | X85: 46080 | Y85: 46083 | Z85: 46101 | AA85: 46104 | AB85: 46122 | AC85: 46121 | AD85: 46122 | AE85: 46125 | AF85: 46143 | AG85: 46146 | AH85: 46164
A86: Riesgos | B86: Riesgos | C86: Homero Sanchez | D86: BW-EJECUCION | E86: FILE_RC06A_DERIVADOS_TEMP | F86: LAYOUTS_RCS_v2 -- RC01 - RC03 - RC04 - RC07 - RC08 - RC02 - RC06A | G86: No mapeado | H86: Lo trabaja Bajaware | K86: BW-Ejecucion | L86: Ext Bajaware | M86: Externo | N86: BajaWare | T86: 84 | AE86: 46083 | AF86: 46101 | AG86: 46104 | AH86: 46122
A87: Riesgos | B87: Riesgos | C87: Homero Sanchez | D87: ASIGNA | E87: FILE_RC_CTACOB_INSUMO | F87: LAYOUTS_RCS_v2 -- RC01 - RC03 - RC04 - RC07 - RC08 - RC02 - RC06A | G87: No mapeado | H87: Lo trabaja Bajaware | K87: Valida Areas | L87: Ext Bajaware | M87: Interno | N87: Riesgos | T87: 85 | U87: 46056 | V87: 46059 | W87: 46062 | X87: 46080 | Y87: 46083 | Z87: 46101 | AA87: 46104 | AB87: 46122 | AC87: 46121 | AD87: 46122 | AE87: 46125 | AF87: 46143 | AG87: 46146 | AH87: 46164
A88: Adicionales | B88: Riesgos | C88: Homero Sanchez | D88: ASIGNA | E88: FILE_R01_PAGOS_ANT | F88: LAYOUTS_RCS_v5 | G88: No mapeado | H88: Lo trabaja Bajaware | K88: Valida Areas | L88: Ext Bajaware | M88: Interno | N88: Riesgos | T88: 86 | U88: 46056 | V88: 46059 | W88: 46062 | X88: 46080 | Y88: 46083 | Z88: 46101 | AA88: 46104 | AB88: 46122 | AC88: 46121 | AD88: 46122 | AE88: 46125 | AF88: 46143 | AG88: 46146 | AH88: 46164
A89: Mercados | B89: Tesorería | C89: Eduardo Cabral | D89: CERRADA | E89: FILE_PAC_I | F89: Layout_PACI_V2 -- PAC | G89: NA | H89: Modulo de tesoreria | I89: NTT | K89: Backlog | L89: NA | M89: NA | N89: NA | Q89: No Aplica | T89: 87
A90: Adicionales | B90: Tesorería | C90: Eduardo Cabral | D90: MAPEO | E90: FILE_OPTO_X | F90: Layout_OPTO_V3 -- OPTO | G90: Pendiente | H90: Modulo de tesoreria | I90: NTT | J90: Marcados originalmente como NA | K90: US-Mapeo | L90: Ext NTT | M90: Int Tesoreria | N90: Tesoreria | T90: 88 | W90: 46056 | X90: 46087 | Y90: 46083 | Z90: 46122 | AA90: 46111 | AB90: 46136 | AC90: 46118 | AD90: 46136 | AE90: 46125 | AF90: 46150 | AG90: 46139 | AH90: 46171
A91: Adicionales | B91: Tesorería | C91: Eduardo Cabral | D91: MAPEO | E91: FILE_OPTO_VIII_CONVO | F91: Layout_OPTO_V3 -- OPTO | G91: Pendiente | H91: Modulo de tesoreria | I91: NTT | J91: Marcados originalmente como NA | K91: US-Mapeo | L91: Ext NTT | M91: Int Tesoreria | N91: Tesoreria | T91: 89 | W91: 46056 | X91: 46087 | Y91: 46083 | Z91: 46122 | AA91: 46111 | AB91: 46136 | AC91: 46118 | AD91: 46136 | AE91: 46125 | AF91: 46150 | AG91: 46139 | AH91: 46171
A92: Adicionales | B92: Tesorería | C92: Eduardo Cabral | D92: MAPEO | E92: FILE_OPTO_MEREC_CONVO | F92: Layout_OPTO_V3 -- OPTO | G92: Pendiente | H92: Modulo de tesoreria | I92: NTT | K92: US-Mapeo | L92: Ext NTT | M92: Int Tesoreria | N92: Tesoreria | T92: 90 | W92: 46056 | X92: 46087 | Y92: 46083 | Z92: 46122 | AA92: 46111 | AB92: 46136 | AC92: 46118 | AD92: 46136 | AE92: 46125 | AF92: 46150 | AG92: 46139 | AH92: 46171
A93: Adicionales | B93: Tesorería | C93: Eduardo Cabral | D93: MAPEO | E93: FILE_OPTO_IX_COM | F93: Layout_OPTO_V3 -- OPTO | G93: Pendiente | H93: Modulo de tesoreria | I93: NTT | J93: Marcados originalmente como NA | K93: US-Mapeo | L93: Ext NTT | M93: Int Tesoreria | N93: Tesoreria | T93: 91 | W93: 46056 | X93: 46087 | Y93: 46083 | Z93: 46122 | AA93: 46111 | AB93: 46136 | AC93: 46118 | AD93: 46136 | AE93: 46125 | AF93: 46150 | AG93: 46139 | AH93: 46171
A94: Adicionales | B94: Tesorería | C94: Eduardo Cabral | D94: MAPEO | E94: FILE_OPTO_IX | F94: Layout_OPTO_V3 -- OPTO | G94: Pendiente | H94: Modulo de tesoreria | I94: NTT | J94: Marcados originalmente como NA | K94: US-Mapeo | L94: Ext NTT | M94: Int Tesoreria | N94: Tesoreria | T94: 92 | W94: 46056 | X94: 46087 | Y94: 46083 | Z94: 46122 | AA94: 46111 | AB94: 46136 | AC94: 46118 | AD94: 46136 | AE94: 46125 | AF94: 46150 | AG94: 46139 | AH94: 46171
A95: Adicionales | B95: Tesorería | C95: Eduardo Cabral | D95: MAPEO | E95: FILE_OPTO_III | F95: Layout_OPTO_V3 -- OPTO | G95: Pendiente | H95: Modulo de tesoreria | I95: NTT | K95: US-Mapeo | L95: Ext NTT | M95: Int Tesoreria | N95: Tesoreria | T95: 93 | W95: 46056 | X95: 46087 | Y95: 46083 | Z95: 46122 | AA95: 46111 | AB95: 46136 | AC95: 46118 | AD95: 46136 | AE95: 46125 | AF95: 46150 | AG95: 46139 | AH95: 46171
A96: Adicionales | B96: Tesorería | C96: Eduardo Cabral | D96: MAPEO | E96: FILE_OPTO_II_COM | F96: Layout_OPTO_V3 -- OPTO | G96: Pendiente | H96: Modulo de tesoreria | I96: NTT | K96: US-Mapeo | L96: Ext NTT | M96: Int Tesoreria | N96: Tesoreria | T96: 94 | W96: 46056 | X96: 46087 | Y96: 46083 | Z96: 46122 | AA96: 46111 | AB96: 46136 | AC96: 46118 | AD96: 46136 | AE96: 46125 | AF96: 46150 | AG96: 46139 | AH96: 46171
A97: Adicionales | B97: Tesorería | C97: Eduardo Cabral | D97: MAPEO | E97: FILE_OPTO_II | F97: Layout_OPTO_V3 -- OPTO | G97: Pendiente | H97: Modulo de tesoreria | I97: NTT | K97: US-Mapeo | L97: Ext NTT | M97: Int Tesoreria | N97: Tesoreria | T97: 95 | W97: 46056 | X97: 46087 | Y97: 46083 | Z97: 46122 | AA97: 46111 | AB97: 46136 | AC97: 46118 | AD97: 46136 | AE97: 46125 | AF97: 46150 | AG97: 46139 | AH97: 46171
A98: Adicionales | B98: Tesorería | C98: Eduardo Cabral | D98: MAPEO | E98: FILE_OPTO_I | F98: Layout_OPTO_V3 -- OPTO | G98: Pendiente | H98: Modulo de tesoreria | I98: NTT | K98: US-Mapeo | L98: Ext NTT | M98: Int Tesoreria | N98: Tesoreria | T98: 96 | W98: 46056 | X98: 46087 | Y98: 46083 | Z98: 46122 | AA98: 46111 | AB98: 46136 | AC98: 46118 | AD98: 46136 | AE98: 46125 | AF98: 46150 | AG98: 46139 | AH98: 46171
A99: Adicionales | B99: Tesorería | C99: Eduardo Cabral | D99: MAPEO | E99: FILE_OPTO_CONVO | F99: Layout_OPTO_V3 -- OPTO | G99: Pendiente | H99: Modulo de tesoreria | I99: NTT | K99: US-Mapeo | L99: Ext NTT | M99: Int Tesoreria | N99: Tesoreria | T99: 97 | W99: 46056 | X99: 46087 | Y99: 46083 | Z99: 46122 | AA99: 46111 | AB99: 46136 | AC99: 46118 | AD99: 46136 | AE99: 46125 | AF99: 46150 | AG99: 46139 | AH99: 46171
A100: Adicionales | B100: Tesorería | C100: Eduardo Cabral | D100: MAPEO | E100: FILE_OFF_FX_DDMMAA | F100: Layout OFF_FX_V7 -- OFF | G100: Pendiente | H100: Modulo de tesoreria | I100: NTT | K100: US-Mapeo | L100: Ext NTT | M100: Int Tesoreria | N100: Tesoreria | T100: 98 | W100: 46056 | X100: 46087 | Y100: 46083 | Z100: 46122 | AA100: 46111 | AB100: 46136 | AC100: 46118 | AD100: 46136 | AE100: 46125 | AF100: 46150 | AG100: 46139 | AH100: 46171
...

Sheet Relacion  fechas
AK1: ASIGNACION AREA | AM1: MAPEO | AO1: DESARROLLO | AQ1: VALIDACION US | AS1: VOBO LAYOUT | AU1: EJECUCION BW | AW1: VOBO EJECUCION
T2: FEBRERO | X2: MARZO | AB2: ABRIL | AG2: MAYO | AK2: INICIO | AL2: FIN | AM2: INICIO | AN2: FIN | AO2: INICIO | AP2: FIN | AQ2: INICIO | AR2: FIN | AS2: INICIO | AT2: FIN | AU2: INICIO | AV2: FIN | AW2: INICIO | AX2: FIN
A3: Carpeta | B3: Area | C3: Responsable | D3: Azure | E3: Pestañas | F3: Layout | G3: Estatus | H3: Comentarios | I3: Revision VoBo Usuario | J3: Actualizacion | K3: EstatusAct | L3: Sts2 | M3: Desarrollo | N3: AreaApoyo | O3: Obs Add | P3: Obs Add2 | Q3: NO APLICA | R3: Motivo No APLICA | T3: 02 - 0 6 | U3: 09 - 13 | V3: 16 - 20 | W3: 23 - 27 | X3: 02 - 0 6 | Y3: 09 - 13 | Z3: 16 - 20 | AA3: 23 - 27 | AB3: 30 - 03 | AC3: 06 - 10 | AD3: 13 - 17 | AE3: 20 - 24 | AF3: 27 - 01 | AG3: 04 - 08 | AH3: 11 - 15 | AI3: 18 - 22 | AJ3: 25 - 29 | BN3: # | BO3: Pestañas | BP3: Layout
A4: Adicionales | B4: Tesorería | C4: Eduardo Cabral | D4: MAPEO | E4: VENC_ANT_REPORTOS | F4: Layout_REPORTOS_MN_ME_V7_2024 -- REPORTOS | G4: Pendiente | H4: Modulo de tesoreria | I4: NTT | K4: US-Mapeo | L4: Ext NTT | M4: Int Tesoreria | N4: Tesoreria | O4: Layout_REPORTOS_MN_ME_V7 -- REPORTOS | P4: modif nomb layout | AM4: 46055 | AN4: 46080 | AO4: 46083 | AP4: 46108 | AQ4: 46111 | AR4: 46129 | AS4: 46128 | AT4: 46129 | AU4: 46132 | AV4: 46150 | AW4: 46153 | AX4: 46171 | AZ4: =+AL4-AK4 -> 0 | BA4: =AN4-AM4 -> 25 | BB4: =AP4-AO4 -> 25 | BC4: =AR4-AQ4 -> 18 | BD4: =AT4-AS4 -> 1 | BE4: =AV4-AU4 -> 18 | BF4: =AX4-AW4 -> 18 | BH4: =AM4-AL4 -> 46055 | BI4: =AO4-AN4 -> 3 | BJ4: =AQ4-AP4 -> 3 | BK4: =AS4-AR4 -> -1 | BL4: =AU4-AT4 -> 3 | BM4: =AW4-AV4 -> 3 | BN4: 1 | BO4: SECCION 2E | BP4: Layouts Garantias de Liquidez -- GL
A5: Adicionales | B5: Captacion | C5: Arturo Angeles | D5: MAPEO | E5: USUARIOS NO CLIENTES BE | F5: R1522_USUARIOS NO CLIENTES BE_V0.4 -- R15 1522 | G5: No mapeado | K5: US-Mapeo | M5: Interno | N5: Finanzas | AM5: 46056 | AN5: 46080 | AO5: 46083 | AP5: 46108 | AQ5: 46111 | AR5: 46122 | AS5: 46121 | AT5: 46122 | AU5: 46125 | AV5: 46143 | AW5: 46146 | AX5: 46157 | AZ5: =+AL5-AK5 -> 0 | BA5: =AN5-AM5 -> 24 | BB5: =AP5-AO5 -> 25 | BC5: =AR5-AQ5 -> 11 | BD5: =AT5-AS5 -> 1 | BE5: =AV5-AU5 -> 18 | BF5: =AX5-AW5 -> 11 | BH5: =AM5-AL5 -> 46056 | BI5: =AO5-AN5 -> 3 | BJ5: =AQ5-AP5 -> 3 | BK5: =AS5-AR5 -> -1 | BL5: =AU5-AT5 -> 3 | BM5: =AW5-AV5 -> 3 | BN5: 2 | BO5: SECCION 2D | BP5: Layouts Garantias de Liquidez -- GL
A6: Operativos | B6: Operaciones Captacion | C6: Luis Alberto | D6: CERRADA | E6: UBICACION DE PUNTOS DE TRANSACC | F6: R2443_Ubicacion - R2443 | G6: No mapeado | H6: NTT | K6: Backlog | L6: NA | M6: NA | N6: NA | O6: Acuerdo con Erika el 18/12/24. No aplica en este momento, porque no tendremos nada de lo que solicita. | Q6: No aplica | R6: Este reporte recaba información respecto a la ubicación geográfica de las sucursales, módulos, cajeros automáticos, terminales punto de venta y comisionistas a través de las cuales los usuarios de los servicios financieros realizan las transacciones. | S6: x | BN6: 3 | BO6: SECCION 2C | BP6: Layouts Garantias de Liquidez -- GL
A7: Operativos | B7: Operaciones Captacion | C7: Luis Alberto | D7: DESARROLLO | E7: TITULARES GARANTIZADOS | F7: R2423_IFRS9_Titulares_Garantizados_V0.4 -- R2423 | G7: No mapeado | H7: NTT | K7: DES-Desarrollo Txt | L7: Ext NTT | M7: Externo | N7: Operaciones | S7: x | AO7: 46056 | AP7: 46073 | AQ7: 46076 | AR7: 46094 | AS7: 46093 | AT7: 46094 | AU7: 46097 | AV7: 46115 | AW7: 46118 | AX7: 46136 | AZ7: =+AL7-AK7 -> 0 | BA7: =AN7-AM7 -> 0 | BB7: =AP7-AO7 -> 17 | BC7: =AR7-AQ7 -> 18 | BD7: =AT7-AS7 -> 1 | BE7: =AV7-AU7 -> 18 | BF7: =AX7-AW7 -> 18 | BH7: =AM7-AL7 -> 0 | BI7: =AO7-AN7 -> 46056 | BJ7: =AQ7-AP7 -> 3 | BK7: =AS7-AR7 -> -1 | BL7: =AU7-AT7 -> 3 | BM7: =AW7-AV7 -> 3 | BN7: 4 | BO7: SECCION 2B | BP7: Layouts Garantias de Liquidez -- GL
A8: Adicionales | B8: Operaciones Captacion | C8: Luis Alberto | E8: TADESCOM_BAJAS | F8: Layout TADESCOM -- TADESCOM | G8: NA | H8: NA | K8: Backlog | L8: NA | M8: NA | N8: NA | BN8: 5 | BO8: SECCION 2A | BP8: Layouts Garantias de Liquidez -- GL
A9: Adicionales | B9: Operaciones Captacion | C9: Luis Alberto | E9: TADESCOM_ALTAS | F9: Layout TADESCOM -- TADESCOM | G9: NA | H9: NA | K9: Backlog | L9: NA | M9: NA | N9: NA | BN9: 6 | BO9: SECCION 1 | BP9: Layouts Garantias de Liquidez -- GL
A10: Adicionales | B10: Tesorería | C10: Eduardo Cabral | D10: MAPEO | E10: SWAPS | F10: Layout_SWAPS_V9 -- SWAPS | G10: Pendiente | H10: Modulo de tesoreria | I10: NTT | K10: US-Mapeo | L10: Ext NTT | M10: Int Tesoreria | N10: Tesoreria | O10: Layout_SWAPS_V9.1 -- SWAPS | P10: modif nomb layout | AM10: 46055 | AN10: 46080 | AO10: 46083 | AP10: 46108 | AQ10: 46111 | AR10: 46129 | AS10: 46128 | AT10: 46129 | AU10: 46132 | AV10: 46150 | AW10: 46153 | AX10: 46171 | AZ10: =+AL10-AK10 -> 0 | BA10: =AN10-AM10 -> 25 | BB10: =AP10-AO10 -> 25 | BC10: =AR10-AQ10 -> 18 | BD10: =AT10-AS10 -> 1 | BE10: =AV10-AU10 -> 18 | BF10: =AX10-AW10 -> 18 | BH10: =AM10-AL10 -> 46055 | BI10: =AO10-AN10 -> 3 | BJ10: =AQ10-AP10 -> 3 | BK10: =AS10-AR10 -> -1 | BL10: =AU10-AT10 -> 3 | BM10: =AW10-AV10 -> 3 | BN10: 7 | BO10: R04A_MOV_419 | BP10: V1.01_Credito_IFRS9_R04A -- A0411 - A0417 - A0419 - A0420 - A0424 - R04A_MOV_419
A11: Adicionales | B11: Tesorería | C11: Eduardo Cabral | D11: MAPEO | E11: SWAP_MEREC_CONVO | F11: Layout_SWAPS_V9 -- SWAPS | G11: Pendiente | H11: Modulo de tesoreria | I11: NTT | K11: US-Mapeo | L11: Ext NTT | M11: Int Tesoreria | N11: Tesoreria | O11: Layout_SWAPS_V9.1 -- SWAPS - 1. ENT_SWAP_MEREC_CONVO | P11: modif nomb layout | AM11: 46055 | AN11: 46080 | AO11: 46083 | AP11: 46108 | AQ11: 46111 | AR11: 46129 | AS11: 46128 | AT11: 46129 | AU11: 46132 | AV11: 46150 | AW11: 46153 | AX11: 46171 | AZ11: =+AL11-AK11 -> 0 | BA11: =AN11-AM11 -> 25 | BB11: =AP11-AO11 -> 25 | BC11: =AR11-AQ11 -> 18 | BD11: =AT11-AS11 -> 1 | BE11: =AV11-AU11 -> 18 | BF11: =AX11-AW11 -> 18 | BH11: =AM11-AL11 -> 46055 | BI11: =AO11-AN11 -> 3 | BJ11: =AQ11-AP11 -> 3 | BK11: =AS11-AR11 -> -1 | BL11: =AU11-AT11 -> 3 | BM11: =AW11-AV11 -> 3 | BN11: 8 | BO11: MERCANCIAS_RC | BP11: LAYOUT MERCANCIAS_RCS -- RC17
A12: Adicionales | B12: Tesorería | C12: Eduardo Cabral | D12: MAPEO | E12: SWAP_IV_COM | F12: Layout_SWAPS_V9 -- SWAPS | G12: Pendiente | H12: Modulo de tesoreria | I12: NTT | K12: US-Mapeo | L12: Ext NTT | M12: Int Tesoreria | N12: Tesoreria | O12: Layout_SWAPS_V9.1 -- SWAPS | P12: modif nomb layout | AM12: 46055 | AN12: 46080 | AO12: 46083 | AP12: 46108 | AQ12: 46111 | AR12: 46129 | AS12: 46128 | AT12: 46129 | AU12: 46132 | AV12: 46150 | AW12: 46153 | AX12: 46171 | AZ12: =+AL12-AK12 -> 0 | BA12: =AN12-AM12 -> 25 | BB12: =AP12-AO12 -> 25 | BC12: =AR12-AQ12 -> 18 | BD12: =AT12-AS12 -> 1 | BE12: =AV12-AU12 -> 18 | BF12: =AX12-AW12 -> 18 | BH12: =AM12-AL12 -> 46055 | BI12: =AO12-AN12 -> 3 | BJ12: =AQ12-AP12 -> 3 | BK12: =AS12-AR12 -> -1 | BL12: =AU12-AT12 -> 3 | BM12: =AW12-AV12 -> 3 | BN12: 9 | BO12: INVERSIONES PERMANENTES | BP12: R1230_Contables_IFRS9_Inversiones_Permanentes_V1
A13: Adicionales | B13: Tesorería | C13: Eduardo Cabral | D13: MAPEO | E13: SWAP_IV | F13: Layout_SWAPS_V9 -- SWAPS | G13: Pendiente | H13: Modulo de tesoreria | I13: NTT | K13: US-Mapeo | L13: Ext NTT | M13: Int Tesoreria | N13: Tesoreria | O13: Layout_SWAPS_V9.1 -- SWAPS | P13: modif nomb layout | AM13: 46055 | AN13: 46080 | AO13: 46083 | AP13: 46108 | AQ13: 46111 | AR13: 46129 | AS13: 46128 | AT13: 46129 | AU13: 46132 | AV13: 46150 | AW13: 46153 | AX13: 46171 | AZ13: =+AL13-AK13 -> 0 | BA13: =AN13-AM13 -> 25 | BB13: =AP13-AO13 -> 25 | BC13: =AR13-AQ13 -> 18 | BD13: =AT13-AS13 -> 1 | BE13: =AV13-AU13 -> 18 | BF13: =AX13-AW13 -> 18 | BH13: =AM13-AL13 -> 46055 | BI13: =AO13-AN13 -> 3 | BJ13: =AQ13-AP13 -> 3 | BK13: =AS13-AR13 -> -1 | BL13: =AU13-AT13 -> 3 | BM13: =AW13-AV13 -> 3 | BN13: 10 | BO13: FILE_TITULOS_DEUDA | BP13: LAYOUTS_RCS_v2 -- RC01 - RC03 - RC04 - RC07 - RC08 - RC02 - RC06A
A14: Adicionales | B14: Tesorería | C14: Eduardo Cabral | D14: MAPEO | E14: SWAP_I | F14: Layout_SWAPS_V9 -- SWAPS | G14: Pendiente | H14: Modulo de tesoreria | I14: NTT | K14: US-Mapeo | L14: Ext NTT | M14: Int Tesoreria | N14: Tesoreria | O14: Layout_SWAPS_V9.1 -- SWAPS | P14: modif nomb layout | AM14: 46055 | AN14: 46080 | AO14: 46083 | AP14: 46108 | AQ14: 46111 | AR14: 46129 | AS14: 46128 | AT14: 46129 | AU14: 46132 | AV14: 46150 | AW14: 46153 | AX14: 46171 | AZ14: =+AL14-AK14 -> 0 | BA14: =AN14-AM14 -> 25 | BB14: =AP14-AO14 -> 25 | BC14: =AR14-AQ14 -> 18 | BD14: =AT14-AS14 -> 1 | BE14: =AV14-AU14 -> 18 | BF14: =AX14-AW14 -> 18 | BH14: =AM14-AL14 -> 46055 | BI14: =AO14-AN14 -> 3 | BJ14: =AQ14-AP14 -> 3 | BK14: =AS14-AR14 -> -1 | BL14: =AU14-AT14 -> 3 | BM14: =AW14-AV14 -> 3 | BN14: 11 | BO14: FILE_RC06A_DERIVADOS_TEMP | BP14: LAYOUTS_RCS_v2 -- RC01 - RC03 - RC04 - RC07 - RC08 - RC02 - RC06A
A15: Adicionales | B15: Tesorería | C15: Eduardo Cabral | D15: MAPEO | E15: SWAP_FLUJOS | F15: Layout_SWAPS_V9 -- SWAPS | G15: Pendiente | H15: Modulo de tesoreria | I15: NTT | K15: US-Mapeo | L15: Ext NTT | M15: Int Tesoreria | N15: Tesoreria | O15: Layout_SWAPS_V9.1 -- SWAPS | P15: modif nomb layout | AM15: 46055 | AN15: 46080 | AO15: 46083 | AP15: 46108 | AQ15: 46111 | AR15: 46129 | AS15: 46128 | AT15: 46129 | AU15: 46132 | AV15: 46150 | AW15: 46153 | AX15: 46171 | AZ15: =+AL15-AK15 -> 0 | BA15: =AN15-AM15 -> 25 | BB15: =AP15-AO15 -> 25 | BC15: =AR15-AQ15 -> 18 | BD15: =AT15-AS15 -> 1 | BE15: =AV15-AU15 -> 18 | BF15: =AX15-AW15 -> 18 | BH15: =AM15-AL15 -> 46055 | BI15: =AO15-AN15 -> 3 | BJ15: =AQ15-AP15 -> 3 | BK15: =AS15-AR15 -> -1 | BL15: =AU15-AT15 -> 3 | BM15: =AW15-AV15 -> 3 | BN15: 12 | BO15: FILE_CONTRAPARTES | BP15: Layout_CONTRAPARTES_v5 -- CONTRAPARTES
A16: Adicionales | B16: Tesorería | C16: Eduardo Cabral | D16: MAPEO | E16: SWAP_CUOTAS_INT | F16: Layout_SWAPS_V9 -- SWAPS | G16: Pendiente | H16: Modulo de tesoreria | I16: NTT | K16: US-Mapeo | L16: Ext NTT | M16: Int Tesoreria | N16: Tesoreria | O16: Layout_SWAPS_V9.1 -- SWAPS | P16: modif nomb layout | AM16: 46055 | AN16: 46080 | AO16: 46083 | AP16: 46108 | AQ16: 46111 | AR16: 46129 | AS16: 46128 | AT16: 46129 | AU16: 46132 | AV16: 46150 | AW16: 46153 | AX16: 46171 | AZ16: =+AL16-AK16 -> 0 | BA16: =AN16-AM16 -> 25 | BB16: =AP16-AO16 -> 25 | BC16: =AR16-AQ16 -> 18 | BD16: =AT16-AS16 -> 1 | BE16: =AV16-AU16 -> 18 | BF16: =AX16-AW16 -> 18 | BH16: =AM16-AL16 -> 46055 | BI16: =AO16-AN16 -> 3 | BJ16: =AQ16-AP16 -> 3 | BK16: =AS16-AR16 -> -1 | BL16: =AU16-AT16 -> 3 | BM16: =AW16-AV16 -> 3 | BN16: 13 | BO16: FILE_CARTERA_LINEA | BP16: LAYOUTS_RCS_v2 -- RC01 - RC03 - RC04 - RC07 - RC08 - RC02 - RC06A
A17: Adicionales | B17: Tesorería | C17: Eduardo Cabral | D17: MAPEO | E17: SWAP_CONVO | F17: Layout_SWAPS_V9 -- SWAPS | G17: Pendiente | H17: Modulo de tesoreria | I17: NTT | K17: US-Mapeo | L17: Ext NTT | M17: Int Tesoreria | N17: Tesoreria | O17: Layout_SWAPS_V9.1 -- SWAPS | P17: modif nomb layout | AM17: 46055 | AN17: 46080 | AO17: 46083 | AP17: 46108 | AQ17: 46111 | AR17: 46129 | AS17: 46128 | AT17: 46129 | AU17: 46132 | AV17: 46150 | AW17: 46153 | AX17: 46171 | AZ17: =+AL17-AK17 -> 0 | BA17: =AN17-AM17 -> 25 | BB17: =AP17-AO17 -> 25 | BC17: =AR17-AQ17 -> 18 | BD17: =AT17-AS17 -> 1 | BE17: =AV17-AU17 -> 18 | BF17: =AX17-AW17 -> 18 | BH17: =AM17-AL17 -> 46055 | BI17: =AO17-AN17 -> 3 | BJ17: =AQ17-AP17 -> 3 | BK17: =AS17-AR17 -> -1 | BL17: =AU17-AT17 -> 3 | BM17: =AW17-AV17 -> 3 | BN17: 14 | BO17: FILE_CARTERA | BP17: LAYOUTS_RCS_v2 -- RC01 - RC03 - RC04 - RC07 - RC08 - RC02 - RC06A
A18: Operativos | B18: Operaciones Captacion | C18: Luis Alberto | D18: CERRADA | E18: SUCURSALES | F18: R2422_Sucursales -- R2422 | G18: No mapeado | H18: NTT | K18: Backlog | L18: NA | M18: NA | N18: NA | O18: Acuerdo con Erika el 18/12/24. No aplica en este momento, porque no tendremos nada de lo que solicita. | Q18: No aplica | R18: Se refiere a tarjetas, ATM, TPVs, y No. de personal, no tenemos esos datos actualmente, por lo que consideramos que no nos aplica actualmente, pero debemos cerrarlo en conjunto. | S18: x | BN18: 15 | BO18: FILE_ACLME_OPE_VIG | BP18: LAYOUTS_RCS_v2 -- RC01 - RC03 - RC04 - RC07 - RC08 - RC02 - RC06A
A19: Operativos | B19: Producto | C19: Claudia Barroso | E19: SEGUROS NOMINA Y PERS | F19: CUP -- CUP | G19: NA | H19: NA | K19: Backlog | L19: NA | M19: NA | N19: NA | BN19: 16 | BO19: CONCILIACIONES | BP19: R32_Conciliaciones -- R3211
A20: Adicionales | B20: Tesorería | C20: Eduardo Cabral | D20: CERRADA | E20: SECCION 2E | F20: Layouts Garantias de Liquidez -- GL | G20: Pendiente | H20: Modulo de tesoreria | I20: NTT | K20: Backlog | L20: NA | M20: NA | N20: Finanzas | O20: Calificaciones Otorgadas (No aplica confirma Denisse) | P20: Modificacion nombre layout | Q20: NO APLICA | R20: Comentario Bajaware: Si no cuentan con las operaciones a las que se refiere ese layout, no es necesario llenarlo. Sin embargo, si Banxico da de alta el producto en el portal de Espifnet, tendrían que enviarlo vacío. | BN20: 17 | BO20: CE_ENG | BP20: Layout CF_V2
A21: Adicionales | B21: Tesorería | C21: Eduardo Cabral | D21: CERRADA | E21: SECCION 2D | F21: Layouts Garantias de Liquidez -- GL | G21: Pendiente | H21: Modulo de tesoreria | I21: NTT | K21: Backlog | L21: NA | M21: NA | N21: Finanzas/Contabilidad/WO | O21: Inmuebles | P21: Modificacion nombre layout | Q21: NO APLICA | R21: Comentario Bajaware: Si no cuentan con las operaciones a las que se refiere ese layout, no es necesario llenarlo. Sin embargo, si Banxico da de alta el producto en el portal de Espifnet, tendrían que enviarlo vacío. | BN21: 18 | BO21: CARTERA_RC_ADIC | BP21: LAYOUT_CARTERA_RC_ADIC --RC01 - RC03 - RC04 - RC08 - RC15
A22: Adicionales | B22: Tesorería | C22: Eduardo Cabral | D22: CERRADA | E22: SECCION 2C | F22: Layouts Garantias de Liquidez -- GL | G22: Pendiente | H22: Modulo de tesoreria | I22: NTT | K22: Backlog | L22: NA | M22: NA | N22: Tesoreria | O22: Acciones | P22: Modificacion nombre layout | Q22: NO APLICA | R22: Comentario Bajaware: Si no cuentan con las operaciones a las que se refiere ese layout, no es necesario llenarlo. Sin embargo, si Banxico da de alta el producto en el portal de Espifnet, tendrían que enviarlo vacío. | BN22: 19 | BO22: BALANZA | BP22: LAYOUTS_RCS_v2 -- RC01 - RC03 - RC04 - RC07 - RC08 - RC02 - RC06A
A23: Adicionales | B23: Tesorería | C23: Eduardo Cabral | D23: CERRADA | E23: SECCION 2B | F23: Layouts Garantias de Liquidez -- GL | G23: Pendiente | H23: Modulo de tesoreria | I23: NTT | K23: Backlog | L23: NA | M23: NA | N23: Operaciones | O23: Cartera de Créditos | P23: Modificacion nombre layout | Q23: NO APLICA | R23: Comentario Bajaware: Si no cuentan con las operaciones a las que se refiere ese layout, no es necesario llenarlo. Sin embargo, si Banxico da de alta el producto en el portal de Espifnet, tendrían que enviarlo vacío. | BN23: 20
A24: Adicionales | B24: Tesorería | C24: Eduardo Cabral | D24: CERRADA | E24: SECCION 2A | F24: Layouts Garantias de Liquidez -- GL | G24: Pendiente | H24: Modulo de tesoreria | I24: NTT | K24: Backlog | L24: NA | M24: NA | N24: Tesoreria | O24: Cartera de Valores | P24: Modificacion nombre layout | Q24: NO APLICA | R24: Comentario Bajaware: Si no cuentan con las operaciones a las que se refiere ese layout, no es necesario llenarlo. Sin embargo, si Banxico da de alta el producto en el portal de Espifnet, tendrían que enviarlo vacío. | BN24: 21
A25: Adicionales | B25: Tesorería | C25: Eduardo Cabral | D25: CERRADA | E25: SECCION 1 | F25: Layouts Garantias de Liquidez -- GL | G25: Pendiente | H25: Modulo de tesoreria | I25: NTT | K25: Backlog | L25: NA | M25: NA | N25: Financiamiento | O25: Layouts Garantias de Liquidez | P25: Modificacion nombre layout | Q25: NO APLICA | R25: Comentario Bajaware: Si no cuentan con las operaciones a las que se refiere ese layout, no es necesario llenarlo. Sin embargo, si Banxico da de alta el producto en el portal de Espifnet, tendrían que enviarlo vacío. | BN25: 22
A26: Adicionales | B26: Tesorería | C26: Eduardo Cabral | D26: MAPEO | E26: REPORTOS_MNME | F26: Layout_REPORTOS_MN_ME_V7_2024 -- REPORTOS | G26: Pendiente | H26: Modulo de tesoreria | I26: NTT | K26: US-Mapeo | L26: Ext NTT | M26: Int Tesoreria | N26: Tesoreria | O26: Layout_REPORTOS_MN_ME_V7 -- REPORTOS | P26: modif nomb layout | AM26: 46055 | AN26: 46080 | AO26: 46083 | AP26: 46108 | AQ26: 46111 | AR26: 46129 | AS26: 46128 | AT26: 46129 | AU26: 46132 | AV26: 46150 | AW26: 46153 | AX26: 46171 | AZ26: =+AL26-AK26 -> 0 | BA26: =AN26-AM26 -> 25 | BB26: =AP26-AO26 -> 25 | BC26: =AR26-AQ26 -> 18 | BD26: =AT26-AS26 -> 1 | BE26: =AV26-AU26 -> 18 | BF26: =AX26-AW26 -> 18 | BH26: =AM26-AL26 -> 46055 | BI26: =AO26-AN26 -> 3 | BJ26: =AQ26-AP26 -> 3 | BK26: =AS26-AR26 -> -1 | BL26: =AU26-AT26 -> 3 | BM26: =AW26-AV26 -> 3 | BN26: 23
A27: Cartera | B27: Operaciones Credito | C27: Luis Alberto | E27: REL_CONSUMO_GARANTIA | F27: V1.05_Credito_IFRS9_Consumo_Completo VF (2) | G27: NA | H27: NA | K27: Backlog | L27: NA | M27: NA | N27: NA | BN27: 24
A28: Operativos | B28: Producto | C28: Claudia Barroso | D28: VOBO US | E28: Registro Gral Prd | F28: CUP -- CUP | G28: Listo | H28: VoBo Dado por el usuario (No se cuenta con informacion) | I28: Estructura | K28: US-VoBo | M28: Interno | N28: Producto | AU28: 46076 | AV28: 46101 | AW28: 46104 | AX28: 46129 | AZ28: =+AL28-AK28 -> 0 | BA28: =AN28-AM28 -> 0 | BB28: =AP28-AO28 -> 0 | BC28: =AR28-AQ28 -> 0 | BD28: =AT28-AS28 -> 0 | BE28: =AV28-AU28 -> 25 | BF28: =AX28-AW28 -> 25 | BH28: =AM28-AL28 -> 0 | BI28: =AO28-AN28 -> 0 | BJ28: =AQ28-AP28 -> 0 | BK28: =AS28-AR28 -> 0 | BL28: =AU28-AT28 -> 46076 | BM28: =AW28-AV28 -> 3 | BN28: 25
A29: Captacion | B29: Producto | C29: Claudia Barroso | D29: DESARROLLO | E29: RECO | F29: Layout RECO BW -- RECO | G29: Listo | H29: Ntt, ya se reviso txt por usuario VoBo | I29: Estructura y universo | J29: Se reasignó a Prodcuto | estaba identificado como VoBo Usuario | K29: DES-Desarrollo Txt | M29: Interno | N29: TI | O29: Se menciona a NTT | P29: Validar la parte de captación NTT para integrar en un solo reporte | S29: x | AO29: 46056 | AP29: 46080 | AQ29: 46083 | AR29: 46108 | AS29: 46107 | AT29: 46108 | AU29: 46111 | AV29: 46136 | AW29: 46139 | AX29: 46164 | AZ29: =+AL29-AK29 -> 0 | BA29: =AN29-AM29 -> 0 | BB29: =AP29-AO29 -> 24 | BC29: =AR29-AQ29 -> 25 | BD29: =AT29-AS29 -> 1 | BE29: =AV29-AU29 -> 25 | BF29: =AX29-AW29 -> 25 | BH29: =AM29-AL29 -> 0 | BI29: =AO29-AN29 -> 46056 | BJ29: =AQ29-AP29 -> 3 | BK29: =AS29-AR29 -> -1 | BL29: =AU29-AT29 -> 3 | BM29: =AW29-AV29 -> 3 | BN29: 26
A30: Situacion Finaciera | B30: Contabilidad | C30: Ramon Jaimes | D30: VOBO US | E30: RECLASIFICACIONES | F30: R10_RECLASIFICACIONES -- R10 | G30: Listo | H30: Revision de txt por parte del usuario | I30: Estructura y universo | J30: Duda US ¿Cuál sería la mecánica para la generación de este reporte? | K30: US-VoBo | M30: Interno | N30: Contabilidad | AU30: 46076 | AV30: 46101 | AW30: 46104 | AX30: 46129 | AZ30: =+AL30-AK30 -> 0 | BA30: =AN30-AM30 -> 0 | BB30: =AP30-AO30 -> 0 | BC30: =AR30-AQ30 -> 0 | BD30: =AT30-AS30 -> 0 | BE30: =AV30-AU30 -> 25 | BF30: =AX30-AW30 -> 25 | BH30: =AM30-AL30 -> 0 | BI30: =AO30-AN30 -> 0 | BJ30: =AQ30-AP30 -> 0 | BK30: =AS30-AR30 -> 0 | BL30: =AU30-AT30 -> 46076 | BM30: =AW30-AV30 -> 3 | BN30: 27
A31: Operativos | B31: Operaciones Captacion | C31: Luis Alberto | D31: CERRADA | E31: RECLAMACIONES BURSATILES BM | F31: R2711_ReclamacionesB_V0.4 | G31: NA | H31: NA | K31: Backlog | L31: NA | M31: NA | N31: NA | O31: Estaba asiugnado a NTT | S31: x | BN31: 28
A32: Adicionales | B32: UNE | C32: Martin Roman | D32: MAPEO | E32: RECLAMACIONES | F32: LAYOUT R27_V1 -- R27 - 2701 | G32: No mapeado | K32: US-Mapeo | M32: Interno | N32: UNE | AM32: 46056 | AN32: 46094 | AO32: 46097 | AP32: 46115 | AQ32: 46118 | AR32: 46129 | AS32: 46128 | AT32: 46129 | AU32: 46132 | AV32: 46150 | AW32: 46153 | AX32: 46171 | AZ32: =+AL32-AK32 -> 0 | BA32: =AN32-AM32 -> 38 | BB32: =AP32-AO32 -> 18 | BC32: =AR32-AQ32 -> 11 | BD32: =AT32-AS32 -> 1 | BE32: =AV32-AU32 -> 18 | BF32: =AX32-AW32 -> 18 | BH32: =AM32-AL32 -> 46056 | BI32: =AO32-AN32 -> 3 | BJ32: =AQ32-AP32 -> 3 | BK32: =AS32-AR32 -> -1 | BL32: =AU32-AT32 -> 3 | BM32: =AW32-AV32 -> 3 | BN32: 29
A33: Adicionales | B33: Contabilidad | C33: Ramon Jaimes | D33: VOBO US | E33: R36_PAGOS_ANT_CARGOS_DIF | F33: V1.00_R3601_CARGOS_DIF_PAGOS_ANTICIPADOS -- R36 3601 | G33: Por iniciar | H33: Se requiere recepcion de requerimiento y Excel. (Usuario) | K33: US-VoBo | M33: Interno | N33: Contabilidad | AU33: 46076 | AV33: 46101 | AW33: 46104 | AX33: 46129 | AZ33: =+AL33-AK33 -> 0 | BA33: =AN33-AM33 -> 0 | BB33: =AP33-AO33 -> 0 | BC33: =AR33-AQ33 -> 0 | BD33: =AT33-AS33 -> 0 | BE33: =AV33-AU33 -> 25 | BF33: =AX33-AW33 -> 25 | BH33: =AM33-AL33 -> 0 | BI33: =AO33-AN33 -> 0 | BJ33: =AQ33-AP33 -> 0 | BK33: =AS33-AR33 -> 0 | BL33: =AU33-AT33 -> 46076 | BM33: =AW33-AV33 -> 3 | BN33: 30
A34: Adicionales | B34: Riesgos | C34: Homero Sanchez | D34: MAPEO | E34: R35_1 | F34: Layout R35_1 -- R35 | G34: No mapeado | H34: Se tiene que realizar una vez migrado a Banco | se puede mapear la cartera de creditos -- Riesgos / Exp Valores Transac -- Tesoreria | I34: Estructura y universo | K34: US-Mapeo | M34: Interno | N34: Riesgos | AU34: 46111 | AV34: 46136 | AW34: 46139 | AX34: 46157 | AZ34: =+AL34-AK34 -> 0 | BA34: =AN34-AM34 -> 0 | BB34: =AP34-AO34 -> 0 | BC34: =AR34-AQ34 -> 0 | BD34: =AT34-AS34 -> 0 | BE34: =AV34-AU34 -> 25 | BF34: =AX34-AW34 -> 18 | BH34: =AM34-AL34 -> 0 | BI34: =AO34-AN34 -> 0 | BJ34: =AQ34-AP34 -> 0 | BK34: =AS34-AR34 -> 0 | BL34: =AU34-AT34 -> 46111 | BM34: =AW34-AV34 -> 3 | BN34: 31
A35: Adicionales | B35: Operaciones Captacion | C35: Luis Alberto | D35: CERRADA | E35: R26OPE | F35: R26 Comisionistas -- R26 2610 2611 2612 2616 | G35: No mapeado | H35: NTT | K35: Backlog | L35: NA | M35: NA | N35: NA | O35: Acuerdo con Erika el 18/12/24. No aplica en este momento, porque no tendremos nada de lo que solicita. | Q35: No aplica | R35: Actualmente no tenemos comisionistas, esta información no se puede generar por el momento, nosotros decimos que no nos aplica, pero debemos cerrarlo en conjunto. | S35: x | BN35: 32
A36: Adicionales | B36: Operaciones Captacion | C36: Luis Alberto | D36: CERRADA | E36: R26_MODULO | F36: R26 Comisionistas -- R26 2610 2611 2612 2615 | G36: No mapeado | H36: NTT | K36: Backlog | L36: NA | M36: NA | N36: NA | O36: Acuerdo con Erika el 18/12/24. No aplica en este momento, porque no tendremos nada de lo que solicita. | Q36: No aplica | R36: Actualmente no tenemos comisionistas, esta información no se puede generar por el momento, nosotros decimos que no nos aplica, pero debemos cerrarlo en conjunto. | S36: x | BN36: 33
A37: Adicionales | B37: Operaciones Captacion | C37: Luis Alberto | D37: CERRADA | E37: R26_COMISIONISTA | F37: R26 Comisionistas -- R26 2610 2611 2612 2614 | G37: No mapeado | H37: NTT | K37: Backlog | L37: NA | M37: NA | N37: NA | O37: Acuerdo con Erika el 18/12/24. No aplica en este momento, porque no tendremos nada de lo que solicita. | Q37: No aplica | R37: Actualmente no tenemos comisionistas, esta información no se puede generar por el momento, nosotros decimos que no nos aplica, pero debemos cerrarlo en conjunto. | S37: x | BN37: 34
A38: Adicionales | B38: Operaciones Captacion | C38: Luis Alberto | D38: CERRADA | E38: R26_ADMINISTRADOR | F38: R26 Comisionistas -- R26 2610 2611 2612 2613 | G38: No mapeado | H38: NTT | K38: Backlog | L38: NA | M38: NA | N38: NA | O38: Acuerdo con Erika el 18/12/24. No aplica en este momento, porque no tendremos nada de lo que solicita. | Q38: No aplica | R38: Actualmente no tenemos comisionistas, esta información no se puede generar por el momento, nosotros decimos que no nos aplica, pero debemos cerrarlo en conjunto. | S38: x | BN38: 35
A39: Operativos | B39: Operaciones Captacion | C39: Luis Alberto | D39: DESARROLLO | E39: R2441_42 | F39: Layout R2441_42_V2 --R2441 - R2442 | G39: No mapeado | H39: NTT | K39: DES-Desarrollo Txt | L39: Ext NTT | M39: Externo | N39: Operaciones | O39: Este TXT ya fue entregado por NTT el 16/06 y te pase la guía para bajarlo de Transat el 27/10/25. Aún no lo conectan a ATOM. | S39: x | AO39: 46056 | AP39: 46073 | AQ39: 46076 | AR39: 46094 | AS39: 46093 | AT39: 46094 | AU39: 46097 | AV39: 46115 | AW39: 46118 | AX39: 46136 | AZ39: =+AL39-AK39 -> 0 | BA39: =AN39-AM39 -> 0 | BB39: =AP39-AO39 -> 17 | BC39: =AR39-AQ39 -> 18 | BD39: =AT39-AS39 -> 1 | BE39: =AV39-AU39 -> 18 | BF39: =AX39-AW39 -> 18 | BH39: =AM39-AL39 -> 0 | BI39: =AO39-AN39 -> 46056 | BJ39: =AQ39-AP39 -> 3 | BK39: =AS39-AR39 -> -1 | BL39: =AU39-AT39 -> 3 | BM39: =AW39-AV39 -> 3 | BN39: 36
A40: Operativos | B40: Operaciones Captacion | C40: Arturo Angeles | D40: MAPEO | E40: R2431 | F40: Layout R2431_V4 -- R24 C2431 | G40: No mapeado | H40: NTT | J40: • El 18/12/24 le indicamos al PMO que este Layout no correspondía a Operaciones. • Nuevamente en la reunión del 23/07/25 volvimos a pedir que lo asignaran y el acuerdo fue el siguiente: "Contabilidad se lleva a revisar el Layout y si hacen faltan campos se investiga lo que hace falta. Tanto crédito como captación", Sharon le iba a dar seguimiento. • Es urgente que lo asignen, anexo minuta del 23/07/25. | K40: US-Mapeo | L40: Ext NTT | M40: Externo | N40: Finanzas | O40: Asignado a Captación | P40: El Layout R24 Serie C, no le corresponde a Operaciones, solicita información de partes relacionadas que nosotros no tenemos, favor de revisar a fondo y determinar qué área lo debe llenar. | S40: x | AM40: 46055 | AN40: 46073 | AO40: 46076 | AP40: 46094 | AQ40: 46097 | AR40: 46101 | AS40: 46100 | AT40: 46101 | AU40: 46104 | AV40: 46122 | AW40: 46125 | AX40: 46143 | AZ40: =+AL40-AK40 -> 0 | BA40: =AN40-AM40 -> 18 | BB40: =AP40-AO40 -> 18 | BC40: =AR40-AQ40 -> 4 | BD40: =AT40-AS40 -> 1 | BE40: =AV40-AU40 -> 18 | BF40: =AX40-AW40 -> 18 | BH40: =AM40-AL40 -> 46055 | BI40: =AO40-AN40 -> 3 | BJ40: =AQ40-AP40 -> 3 | BK40: =AS40-AR40 -> -1 | BL40: =AU40-AT40 -> 3 | BM40: =AW40-AV40 -> 3 | BN40: 37
A41: Cartera | B41: Operaciones Credito | C41: Luis Alberto | D41: DESARROLLO | E41: R04A_SALDOS | F41: V1.01_Credito_IFRS9_R04A -- A0411 - A0417 - A0419 - A0420 - A0424 | G41: Listo | H41: Se tiene la estructura construida y se integraron los datos con los que se cuenta, aun no se cuenta con todo el universo(Fuentes externas | I41: Estructura | K41: DES-Desarrollo Txt | M41: Interno | N41: TI | AO41: 46056 | AP41: 46080 | AQ41: 46083 | AR41: 46108 | AS41: 46107 | AT41: 46108 | AU41: 46111 | AV41: 46136 | AW41: 46139 | AX41: 46164 | AZ41: =+AL41-AK41 -> 0 | BA41: =AN41-AM41 -> 0 | BB41: =AP41-AO41 -> 24 | BC41: =AR41-AQ41 -> 25 | BD41: =AT41-AS41 -> 1 | BE41: =AV41-AU41 -> 25 | BF41: =AX41-AW41 -> 25 | BH41: =AM41-AL41 -> 0 | BI41: =AO41-AN41 -> 46056 | BJ41: =AQ41-AP41 -> 3 | BK41: =AS41-AR41 -> -1 | BL41: =AU41-AT41 -> 3 | BM41: =AW41-AV41 -> 3 | BN41: 38
A42: Cartera | B42: Operaciones Captacion y credito | C42: Luis Alberto | D42: MAPEO | E42: R04A_MOV_420_24 | F42: V1.01_Credito_IFRS9_R04A -- A0411 - A0417 - A0419 - A0420 - A0424 - R04A_MOV_420_24 | G42: Mapeado incompleto | I42: Estructura y universo | J42: Falta info de Contabilidad | K42: US-Mapeo | M42: Interno | N42: Contabilidad | AM42: 46062 | AN42: 46080 | AO42: 46083 | AP42: 46101 | AQ42: 46104 | AR42: 46108 | AS42: 46107 | AT42: 46108 | AU42: 46111 | AV42: 46129 | AW42: 46132 | AX42: 46143 | AZ42: =+AL42-AK42 -> 0 | BA42: =AN42-AM42 -> 18 | BB42: =AP42-AO42 -> 18 | BC42: =AR42-AQ42 -> 4 | BD42: =AT42-AS42 -> 1 | BE42: =AV42-AU42 -> 18 | BF42: =AX42-AW42 -> 11 | BH42: =AM42-AL42 -> 46062 | BI42: =AO42-AN42 -> 3 | BJ42: =AQ42-AP42 -> 3 | BK42: =AS42-AR42 -> -1 | BL42: =AU42-AT42 -> 3 | BM42: =AW42-AV42 -> 3 | BN42: 39
A43: Cartera | B43: Contabilidad | C43: Ramon Jaimes | D43: DESARROLLO | E43: R04A_MOV_419 | F43: V1.01_Credito_IFRS9_R04A -- A0411 - A0417 - A0419 - A0420 - A0424 - R04A_MOV_419 | G43: Mapeado incompleto | I43: Estructura y universo | J43: Reasignado a Contabilidad | K43: DES-Desarrollo Txt | M43: Interno | N43: Contabilidad | AO43: 46056 | AP43: 46080 | AQ43: 46083 | AR43: 46108 | AS43: 46107 | AT43: 46108 | AU43: 46111 | AV43: 46136 | AW43: 46139 | AX43: 46164 | AZ43: =+AL43-AK43 -> 0 | BA43: =AN43-AM43 -> 0 | BB43: =AP43-AO43 -> 24 | BC43: =AR43-AQ43 -> 25 | BD43: =AT43-AS43 -> 1 | BE43: =AV43-AU43 -> 25 | BF43: =AX43-AW43 -> 25 | BH43: =AM43-AL43 -> 0 | BI43: =AO43-AN43 -> 46056 | BJ43: =AQ43-AP43 -> 3 | BK43: =AS43-AR43 -> -1 | BL43: =AU43-AT43 -> 3 | BM43: =AW43-AV43 -> 3 | BN43: 40
A44: Adicionales | B44: Tesorería | C44: Eduardo Cabral | D44: CERRADA | E44: R03 E-0305 ÓRDENES | F44: layout R03-0304-0305 E BM -- R04 | G44: Pendiente | H44: Modulo de tesoreria | I44: NTT | K44: Backlog | L44: NA | M44: NA | N44: NA | Q44: No aplica | R44: Hace referencia a operaciones con clientes, las cuales no se llevarán a cabo | BN44: 41
A45: Adicionales | B45: Tesorería | C45: Eduardo Cabral | D45: CERRADA | E45: R03 E-0304 ASIGNACIONES BM | F45: layout R03-0304-0305 E BM -- R03 | G45: Pendiente | H45: Modulo de tesoreria | I45: NTT | K45: Backlog | L45: NA | M45: NA | N45: NA | Q45: No aplica | R45: Hace referencia a operaciones con clientes, las cuales no se llevarán a cabo | BN45: 42
A46: Operativos | B46: Operaciones Captacion | C46: Luis Alberto | D46: DESARROLLO | E46: PRODUCTOS CAPTACION CNBV | F46: R2421_Prod Cap -- R2421 | G46: No mapeado | H46: NTT | K46: DES-Desarrollo Txt | L46: Ext NTT | M46: Externo | N46: Operaciones | O46: Este TXT ya fue entregado por NTT el 28/05 y te pase la guía para bajarlo de Transat el 27/10/25. Aún no lo conectan a ATOM. | S46: x | AO46: 46056 | AP46: 46073 | AQ46: 46076 | AR46: 46094 | AS46: 46093 | AT46: 46094 | AU46: 46097 | AV46: 46115 | AW46: 46118 | AX46: 46136 | AZ46: =+AL46-AK46 -> 0 | BA46: =AN46-AM46 -> 0 | BB46: =AP46-AO46 -> 17 | BC46: =AR46-AQ46 -> 18 | BD46: =AT46-AS46 -> 1 | BE46: =AV46-AU46 -> 18 | BF46: =AX46-AW46 -> 18 | BH46: =AM46-AL46 -> 0 | BI46: =AO46-AN46 -> 46056 | BJ46: =AQ46-AP46 -> 3 | BK46: =AS46-AR46 -> -1 | BL46: =AU46-AT46 -> 3 | BM46: =AW46-AV46 -> 3 | BN46: 43
A47: Adicionales | B47: Tesorería | C47: Eduardo Cabral | D47: CERRADA | E47: PRESTAMO DE VALORES | F47: PRESTAMO DE VALORES_V0.1 -- PRESTAMOS | G47: Pendiente | H47: Modulo de tesoreria | I47: NTT | K47: Backlog | L47: NA | M47: NA | N47: NA | Q47: No aplica | R47: No habrá Prestamos en Valores | BN47: 44
A48: Cartera | B48: Operaciones Credito | C48: Luis Alberto | D48: DESARROLLO | E48: PERSONA | F48: V1.05_Layouts CREDITO Bancos IFRS (Comercial) (1) | G48: Listo | H48: Se tiene la estructura construida y se integraron los datos con los que se cuenta, aun no se cuenta con todo el universo(Fuentes externas Pantalla comercial y cualitativa individual) | I48: Estructura | K48: DES-Desarrollo Txt | M48: Interno | N48: TI | AO48: 46056 | AP48: 46080 | AQ48: 46083 | AR48: 46108 | AS48: 46107 | AT48: 46108 | AU48: 46111 | AV48: 46136 | AW48: 46139 | AX48: 46164 | AZ48: =+AL48-AK48 -> 0 | BA48: =AN48-AM48 -> 0 | BB48: =AP48-AO48 -> 24 | BC48: =AR48-AQ48 -> 25 | BD48: =AT48-AS48 -> 1 | BE48: =AV48-AU48 -> 25 | BF48: =AX48-AW48 -> 25 | BH48: =AM48-AL48 -> 0 | BI48: =AO48-AN48 -> 46056 | BJ48: =AQ48-AP48 -> 3 | BK48: =AS48-AR48 -> -1 | BL48: =AU48-AT48 -> 3 | BM48: =AW48-AV48 -> 3 | BN48: 45
A49: Operativos | B49: Producto | C49: Claudia Barroso | E49: PENALIZACIONES NOMINA Y PERS | F49: CUP -- CUP | G49: NA | H49: NA | K49: Backlog | L49: NA | M49: NA | N49: NA | BN49: 46
A50: Cartera | B50: Operaciones Credito | C50: Luis Alberto | D50: DESARROLLO | E50: PAGOS_EXIGIBLES | F50: V1.05_Credito_IFRS9_Consumo_Completo VF (2) | G50: Listo | H50: Se tiene la estructura construida y se integraron los datos con los que se cuenta, aun no se cuenta con todo el universo(Fuentes externas | I50: Estructura | K50: DES-Desarrollo Txt | M50: Interno | N50: TI | AO50: 46056 | AP50: 46080 | AQ50: 46083 | AR50: 46108 | AS50: 46107 | AT50: 46108 | AU50: 46111 | AV50: 46136 | AW50: 46139 | AX50: 46164 | AZ50: =+AL50-AK50 -> 0 | BA50: =AN50-AM50 -> 0 | BB50: =AP50-AO50 -> 24 | BC50: =AR50-AQ50 -> 25 | BD50: =AT50-AS50 -> 1 | BE50: =AV50-AU50 -> 25 | BF50: =AX50-AW50 -> 25 | BH50: =AM50-AL50 -> 0 | BI50: =AO50-AN50 -> 46056 | BJ50: =AQ50-AP50 -> 3 | BK50: =AS50-AR50 -> -1 | BL50: =AU50-AT50 -> 3 | BM50: =AW50-AV50 -> 3 | BN50: 47
A51: Captacion | B51: Operaciones Captacion | C51: Arturo Angeles | D51: MAPEO | E51: OperacionesOEMN | F51: LayoutOEMN_v3 | G51: No mapeado | H51: NTT | J51: No lo tenemos asignado a Operaciones en la matriz inicial de regulatorios del 05/09/24. | K51: US-Mapeo | L51: Ext NTT | M51: Externo | N51: Finanzas | O51: No se realizaran operaciones en efectivo vañidar si aplica | S51: x | AM51: 46055 | AN51: 46073 | AO51: 46076 | AP51: 46094 | AQ51: 46097 | AR51: 46101 | AS51: 46100 | AT51: 46101 | AU51: 46104 | AV51: 46122 | AW51: 46125 | AX51: 46143 | AZ51: =+AL51-AK51 -> 0 | BA51: =AN51-AM51 -> 18 | BB51: =AP51-AO51 -> 18 | BC51: =AR51-AQ51 -> 4 | BD51: =AT51-AS51 -> 1 | BE51: =AV51-AU51 -> 18 | BF51: =AX51-AW51 -> 18 | BH51: =AM51-AL51 -> 46055 | BI51: =AO51-AN51 -> 3 | BJ51: =AQ51-AP51 -> 3 | BK51: =AS51-AR51 -> -1 | BL51: =AU51-AT51 -> 3 | BM51: =AW51-AV51 -> 3 | BN51: 48
A52: Adicionales | B52: Captacion | C52: Arturo Angeles | D52: MAPEO | E52: OPERACIONES DE CLIENTES BE | F52: R1523_24_OPERACIONES DE CLIENTES BE_V0.4 -- R15 1523 1524 | G52: No mapeado | K52: US-Mapeo | M52: Interno | N52: Finanzas | AM52: 46056 | AN52: 46080 | AO52: 46083 | AP52: 46108 | AQ52: 46111 | AR52: 46122 | AS52: 46121 | AT52: 46122 | AU52: 46125 | AV52: 46143 | AW52: 46146 | AX52: 46157 | AZ52: =+AL52-AK52 -> 0 | BA52: =AN52-AM52 -> 24 | BB52: =AP52-AO52 -> 25 | BC52: =AR52-AQ52 -> 11 | BD52: =AT52-AS52 -> 1 | BE52: =AV52-AU52 -> 18 | BF52: =AX52-AW52 -> 11 | BH52: =AM52-AL52 -> 46056 | BI52: =AO52-AN52 -> 3 | BJ52: =AQ52-AP52 -> 3 | BK52: =AS52-AR52 -> -1 | BL52: =AU52-AT52 -> 3 | BM52: =AW52-AV52 -> 3 | BN52: 49
A53: Operativos | B53: Producto | C53: Claudia Barroso | E53: Moratoria CNR | F53: CUP -- CUP | G53: NA | H53: NA | K53: Backlog | L53: NA | M53: NA | N53: NA | BN53: 50
A54: Adicionales | B54: Tesorería | C54: Eduardo Cabral | D54: MAPEO | E54: MODIF_TASAPREMIO | F54: Layout_REPORTOS_MN_ME_V7_2024 -- REPORTOS | G54: Pendiente | H54: Modulo de tesoreria | I54: NTT | K54: US-Mapeo | L54: Ext NTT | M54: Int Tesoreria | N54: Tesoreria | O54: Layout_REPORTOS_MN_ME_V7 -- REPORTOS | P54: modif nomb layout | AM54: 46055 | AN54: 46080 | AO54: 46083 | AP54: 46108 | AQ54: 46111 | AR54: 46129 | AS54: 46128 | AT54: 46129 | AU54: 46132 | AV54: 46150 | AW54: 46153 | AX54: 46171 | AZ54: =+AL54-AK54 -> 0 | BA54: =AN54-AM54 -> 25 | BB54: =AP54-AO54 -> 25 | BC54: =AR54-AQ54 -> 18 | BD54: =AT54-AS54 -> 1 | BE54: =AV54-AU54 -> 18 | BF54: =AX54-AW54 -> 18 | BH54: =AM54-AL54 -> 46055 | BI54: =AO54-AN54 -> 3 | BJ54: =AQ54-AP54 -> 3 | BK54: =AS54-AR54 -> -1 | BL54: =AU54-AT54 -> 3 | BM54: =AW54-AV54 -> 3 | BN54: 51
A55: Adicionales | B55: Riesgos y tesoreria | C55: Homero Sanchez | D55: BW-EJECUCION | E55: MERCANCIAS_RC | F55: LAYOUT MERCANCIAS_RCS -- RC17 | G55: No mapeado | H55: Lo trabaja Bajaware | K55: BW-Ejecucion | L55: Ext Bajaware | M55: Externo | N55: BajaWare | AU55: 46076 | AV55: 46094 | AW55: 46097 | AX55: 46115 | AZ55: =+AL55-AK55 -> 0 | BA55: =AN55-AM55 -> 0 | BB55: =AP55-AO55 -> 0 | BC55: =AR55-AQ55 -> 0 | BD55: =AT55-AS55 -> 0 | BE55: =AV55-AU55 -> 18 | BF55: =AX55-AW55 -> 18 | BH55: =AM55-AL55 -> 0 | BI55: =AO55-AN55 -> 0 | BJ55: =AQ55-AP55 -> 0 | BK55: =AS55-AR55 -> 0 | BL55: =AU55-AT55 -> 46076 | BM55: =AW55-AV55 -> 3 | BN55: 52
A56: Captacion | B56: Producto | C56: Claudia Barroso | D56: VOBO US | E56: MDEF_SUC Y CAJAS GRALES | F56: Layouts MDEF -- MDEF | G56: Listo | H56: VoBo Dado por el usuario (No se cuenta con informacion) | I56: Estructura | K56: US-VoBo | M56: Interno | N56: Producto | AU56: 46076 | AV56: 46101 | AW56: 46104 | AX56: 46129 | AZ56: =+AL56-AK56 -> 0 | BA56: =AN56-AM56 -> 0 | BB56: =AP56-AO56 -> 0 | BC56: =AR56-AQ56 -> 0 | BD56: =AT56-AS56 -> 0 | BE56: =AV56-AU56 -> 25 | BF56: =AX56-AW56 -> 25 | BH56: =AM56-AL56 -> 0 | BI56: =AO56-AN56 -> 0 | BJ56: =AQ56-AP56 -> 0 | BK56: =AS56-AR56 -> 0 | BL56: =AU56-AT56 -> 46076 | BM56: =AW56-AV56 -> 3 | BN56: 53
A57: Captacion | B57: Producto | C57: Claudia Barroso | E57: MDEF_CAJEROS PROPIOS | F57: Layouts MDEF -- MDEF | G57: NA | H57: NA | K57: Backlog | L57: NA | M57: NA | N57: NA | BN57: 54
A58: Captacion | B58: Producto | C58: Claudia Barroso | E58: MDEF_CAJEROS EXTERNOS | F58: Layouts MDEF -- MDEF | G58: NA | H58: NA | K58: Backlog | L58: NA | M58: NA | N58: NA | BN58: 55
A59: Captacion | B59: Producto | C59: Claudia Barroso | E59: MDEF_BOVEDAS PROPIAS | F59: Layouts MDEF -- MDEF | G59: NA | H59: NA | K59: Backlog | L59: NA | M59: NA | N59: NA | BN59: 56
A60: Captacion | B60: Producto | C60: Claudia Barroso | E60: MDEF_BOVEDAS EXTERNAS | F60: Layouts MDEF -- MDEF | G60: NA | H60: NA | K60: Backlog | L60: NA | M60: NA | N60: NA | BN60: 57
A61: Cartera | B61: Operaciones Credito | C61: Luis Alberto | D61: DESARROLLO | E61: LINEA CREDITO | F61: V1.05_Layouts CREDITO Bancos IFRS (Comercial) (1) | G61: Listo | H61: Se tiene la estructura construida y se integraron los datos con los que se cuenta, aun no se cuenta con todo el universo(Fuentes externas Pantalla comercial) | I61: Estructura | K61: DES-Desarrollo Txt | M61: Interno | N61: TI | AO61: 46056 | AP61: 46080 | AQ61: 46083 | AR61: 46108 | AS61: 46107 | AT61: 46108 | AU61: 46111 | AV61: 46136 | AW61: 46139 | AX61: 46164 | AZ61: =+AL61-AK61 -> 0 | BA61: =AN61-AM61 -> 0 | BB61: =AP61-AO61 -> 24 | BC61: =AR61-AQ61 -> 25 | BD61: =AT61-AS61 -> 1 | BE61: =AV61-AU61 -> 25 | BF61: =AX61-AW61 -> 25 | BH61: =AM61-AL61 -> 0 | BI61: =AO61-AN61 -> 46056 | BJ61: =AQ61-AP61 -> 3 | BK61: =AS61-AR61 -> -1 | BL61: =AU61-AT61 -> 3 | BM61: =AW61-AV61 -> 3 | BN61: 58
A62: Situacion Finaciera | B62: Contabilidad | C62: Ramon Jaimes | D62: VOBO US | E62: INVERSIONES PERMANENTES | F62: R1230_Contables_IFRS9_Inversiones_Permanentes_V1 | G62: Por iniciar | H62: Se requiere recepcion de requerimiento y Excel. (Usuario) | J62: Excel confirmado como fuente | K62: US-VoBo | M62: Interno | N62: Contabilidad | O62: Validar estructura de archivos Excel para que sea igual a columnas tablas destino | P62: Complementar archivo cofiguracion Lambda con estructura tablas | AU62: 46076 | AV62: 46094 | AW62: 46097 | AX62: 46115 | AZ62: =+AL62-AK62 -> 0 | BA62: =AN62-AM62 -> 0 | BB62: =AP62-AO62 -> 0 | BC62: =AR62-AQ62 -> 0 | BD62: =AT62-AS62 -> 0 | BE62: =AV62-AU62 -> 18 | BF62: =AX62-AW62 -> 18 | BH62: =AM62-AL62 -> 0 | BI62: =AO62-AN62 -> 0 | BJ62: =AQ62-AP62 -> 0 | BK62: =AS62-AR62 -> 0 | BL62: =AU62-AT62 -> 46076 | BM62: =AW62-AV62 -> 3 | BN62: 59
A63: Situacion Finaciera | B63: Contabilidad | C63: Ramon Jaimes | D63: VOBO US | E63: INTEGRACION ACCIONARIA | F63: R1411_INT. ACC -- R1411 | G63: Listo | H63: Revision de txt por parte del usuario | I63: Estructura y universo | J63: Falta VoBo ultima Modif decimales col 13 | K63: US-VoBo | M63: Interno | N63: Contabilidad | AU63: 46076 | AV63: 46101 | AW63: 46104 | AX63: 46129 | AZ63: =+AL63-AK63 -> 0 | BA63: =AN63-AM63 -> 0 | BB63: =AP63-AO63 -> 0 | BC63: =AR63-AQ63 -> 0 | BD63: =AT63-AS63 -> 0 | BE63: =AV63-AU63 -> 25 | BF63: =AX63-AW63 -> 25 | BH63: =AM63-AL63 -> 0 | BI63: =AO63-AN63 -> 0 | BJ63: =AQ63-AP63 -> 0 | BK63: =AS63-AR63 -> 0 | BL63: =AU63-AT63 -> 46076 | BM63: =AW63-AV63 -> 3 | BN63: 60
A64: Adicionales | B64: Operaciones Captacion | C64: Luis Alberto | E64: INFIMP | F64: Layout INFIMP -- INFIMP | G64: NA | H64: NA | K64: Backlog | L64: NA | M64: NA | N64: NA | BN64: 61
A65: Situacion Finaciera | B65: Contabilidad | C65: Ramon Jaimes | D65: VOBO US | E65: IMPUESTOS | F65: R07_Imp Dif -- R07 | G65: Listo | H65: Se requiere recepcion de requerimiento y Excel. (Usuario) | J65: Duda US ¿Cuál sería la mecánica para la generación de este reporte? | K65: US-VoBo | M65: Interno | N65: Contabilidad | AU65: 46076 | AV65: 46101 | AW65: 46104 | AX65: 46129 | AZ65: =+AL65-AK65 -> 0 | BA65: =AN65-AM65 -> 0 | BB65: =AP65-AO65 -> 0 | BC65: =AR65-AQ65 -> 0 | BD65: =AT65-AS65 -> 0 | BE65: =AV65-AU65 -> 25 | BF65: =AX65-AW65 -> 25 | BH65: =AM65-AL65 -> 0 | BI65: =AO65-AN65 -> 0 | BJ65: =AQ65-AP65 -> 0 | BK65: =AS65-AR65 -> 0 | BL65: =AU65-AT65 -> 46076 | BM65: =AW65-AV65 -> 3 | BN65: 62
A66: Cartera | B66: Operaciones Credito | C66: Luis Alberto | D66: DESARROLLO | E66: HIPOTECARIO | F66: V1.05_Layouts CREDITO Bancos IFRS (Hipotecario Simplificado) (1)- HIPOTECARIO | G66: Listo | H66: Se tiene la estructura construida y se integraron los datos con los que se cuenta, aun no se cuenta con todo el universo(Fuentes externas | I66: Estructura | K66: DES-Desarrollo Txt | M66: Interno | N66: TI | AO66: 46056 | AP66: 46080 | AQ66: 46083 | AR66: 46108 | AS66: 46107 | AT66: 46108 | AU66: 46111 | AV66: 46136 | AW66: 46139 | AX66: 46164 | AZ66: =+AL66-AK66 -> 0 | BA66: =AN66-AM66 -> 0 | BB66: =AP66-AO66 -> 24 | BC66: =AR66-AQ66 -> 25 | BD66: =AT66-AS66 -> 1 | BE66: =AV66-AU66 -> 25 | BF66: =AX66-AW66 -> 25 | BH66: =AM66-AL66 -> 0 | BI66: =AO66-AN66 -> 46056 | BJ66: =AQ66-AP66 -> 3 | BK66: =AS66-AR66 -> -1 | BL66: =AU66-AT66 -> 3 | BM66: =AW66-AV66 -> 3 | BN66: 63
A67: Cartera | B67: Operaciones Credito | C67: Luis Alberto | E67: GARANTIA_CONSUMO | F67: V1.05_Credito_IFRS9_Consumo_Completo VF (2) | G67: NA | H67: NA | K67: Backlog | L67: NA | M67: NA | N67: NA | BN67: 64
A68: Cartera | B68: Operaciones Credito | C68: Luis Alberto | D68: DESARROLLO | E68: GARANTIA | F68: V1.05_Layouts CREDITO Bancos IFRS (Comercial) (1) | G68: Listo | H68: Se tiene la estructura construida y se integraron los datos con los que se cuenta, aun no se cuenta con todo el universo(Fuentes externas Pantalla comercial) | I68: Estructura | J68: PRELACION_GAR campo pendiente MAPEO | US revisa info restante | K68: DES-Desarrollo Txt | M68: Interno | N68: Riesgos | AO68: 46062 | AP68: 46073 | AQ68: 46076 | AR68: 46087 | AS68: 46086 | AT68: 46087 | AU68: 46090 | AV68: 46108 | AW68: 46111 | AX68: 46129 | AZ68: =+AL68-AK68 -> 0 | BA68: =AN68-AM68 -> 0 | BB68: =AP68-AO68 -> 11 | BC68: =AR68-AQ68 -> 11 | BD68: =AT68-AS68 -> 1 | BE68: =AV68-AU68 -> 18 | BF68: =AX68-AW68 -> 18 | BH68: =AM68-AL68 -> 0 | BI68: =AO68-AN68 -> 46062 | BJ68: =AQ68-AP68 -> 3 | BK68: =AS68-AR68 -> -1 | BL68: =AU68-AT68 -> 3 | BM68: =AW68-AV68 -> 3 | BN68: 65
A69: Adicionales | B69: Riesgos y tesoreria | C69: Homero Sanchez | D69: ASIGNA | E69: GAMMA_VEGA | F69: LAYOUT GAMMA_VEGA_V2 -- RC18 | G69: No mapeado | H69: Lo trabaja Bajaware | K69: Valida Areas | L69: Ext Bajaware | M69: Interno | N69: Riesgos | AK69: 46056 | AL69: 46066 | AM69: 46069 | AN69: 46087 | AO69: 46090 | AP69: 46108 | AQ69: 46111 | AR69: 46129 | AS69: 46128 | AT69: 46129 | AU69: 46132 | AV69: 46150 | AW69: 46153 | AX69: 46171 | AZ69: =+AL69-AK69 -> 10 | BA69: =AN69-AM69 -> 18 | BB69: =AP69-AO69 -> 18 | BC69: =AR69-AQ69 -> 18 | BD69: =AT69-AS69 -> 1 | BE69: =AV69-AU69 -> 18 | BF69: =AX69-AW69 -> 18 | BH69: =AM69-AL69 -> 3 | BI69: =AO69-AN69 -> 3 | BJ69: =AQ69-AP69 -> 3 | BK69: =AS69-AR69 -> -1 | BL69: =AU69-AT69 -> 3 | BM69: =AW69-AV69 -> 3 | BN69: 66
A70: Captacion | B70: Operaciones Captacion | C70: Luis Alberto | D70: DESARROLLO | E70: FT_TPA | F70: Layout TPA BW_v2 -- TPA | G70: Pendiente | H70: Modulo de tesoreria | I70: Estructura | J70: VoBo sobre estructura | K70: DES-Desarrollo Txt | L70: Ext NTT | M70: Interno | N70: TI | S70: x | AO70: 46056 | AP70: 46073 | AQ70: 46076 | AR70: 46094 | AS70: 46093 | AT70: 46094 | AU70: 46097 | AV70: 46115 | AW70: 46118 | AX70: 46136 | AZ70: =+AL70-AK70 -> 0 | BA70: =AN70-AM70 -> 0 | BB70: =AP70-AO70 -> 17 | BC70: =AR70-AQ70 -> 18 | BD70: =AT70-AS70 -> 1 | BE70: =AV70-AU70 -> 18 | BF70: =AX70-AW70 -> 18 | BH70: =AM70-AL70 -> 0 | BI70: =AO70-AN70 -> 46056 | BJ70: =AQ70-AP70 -> 3 | BK70: =AS70-AR70 -> -1 | BL70: =AU70-AT70 -> 3 | BM70: =AW70-AV70 -> 3 | BN70: 67
A71: Mercados | B71: Tesorería | C71: Eduardo Cabral | D71: MAPEO | E71: FT_TENENCIA | F71: LayoutTenencia_V2 -- TENENCIA - REPORTOS | G71: Pendiente | H71: Modulo de tesoreria | I71: NTT | K71: US-Mapeo | L71: Ext NTT | M71: Int Tesoreria | N71: Tesoreria | AM71: 46055 | AN71: 46080 | AO71: 46083 | AP71: 46108 | AQ71: 46111 | AR71: 46129 | AS71: 46128 | AT71: 46129 | AU71: 46132 | AV71: 46150 | AW71: 46153 | AX71: 46171 | AZ71: =+AL71-AK71 -> 0 | BA71: =AN71-AM71 -> 25 | BB71: =AP71-AO71 -> 25 | BC71: =AR71-AQ71 -> 18 | BD71: =AT71-AS71 -> 1 | BE71: =AV71-AU71 -> 18 | BF71: =AX71-AW71 -> 18 | BH71: =AM71-AL71 -> 46055 | BI71: =AO71-AN71 -> 3 | BJ71: =AQ71-AP71 -> 3 | BK71: =AS71-AR71 -> -1 | BL71: =AU71-AT71 -> 3 | BM71: =AW71-AV71 -> 3 | BN71: 68
A72: Mercados | B72: Tesorería | C72: Eduardo Cabral | D72: MAPEO | E72: FT_REPORTOS_CDA | F72: Layout_REPORTOS_CDA -- REPORTOS | G72: Pendiente | H72: Modulo de tesoreria | I72: NTT | J72: Marcados originalmente como NA | K72: US-Mapeo | L72: Ext NTT | M72: Int Tesoreria | N72: Tesoreria | AM72: 46055 | AN72: 46080 | AO72: 46083 | AP72: 46108 | AQ72: 46111 | AR72: 46129 | AS72: 46128 | AT72: 46129 | AU72: 46132 | AV72: 46150 | AW72: 46153 | AX72: 46171 | AZ72: =+AL72-AK72 -> 0 | BA72: =AN72-AM72 -> 25 | BB72: =AP72-AO72 -> 25 | BC72: =AR72-AQ72 -> 18 | BD72: =AT72-AS72 -> 1 | BE72: =AV72-AU72 -> 18 | BF72: =AX72-AW72 -> 18 | BH72: =AM72-AL72 -> 46055 | BI72: =AO72-AN72 -> 3 | BJ72: =AQ72-AP72 -> 3 | BK72: =AS72-AR72 -> -1 | BL72: =AU72-AT72 -> 3 | BM72: =AW72-AV72 -> 3 | BN72: 69
A73: Mercados | B73: Tesorería | C73: Eduardo Cabral | D73: MAPEO | E73: FT_REPORTOS | F73: Layout_REPORTOS_MN_ME_V3 | G73: Pendiente | H73: Modulo de tesoreria | I73: NTT | K73: US-Mapeo | L73: Ext NTT | M73: Int Tesoreria | N73: Tesoreria | AM73: 46055 | AN73: 46080 | AO73: 46083 | AP73: 46108 | AQ73: 46111 | AR73: 46129 | AS73: 46128 | AT73: 46129 | AU73: 46132 | AV73: 46150 | AW73: 46153 | AX73: 46171 | AZ73: =+AL73-AK73 -> 0 | BA73: =AN73-AM73 -> 25 | BB73: =AP73-AO73 -> 25 | BC73: =AR73-AQ73 -> 18 | BD73: =AT73-AS73 -> 1 | BE73: =AV73-AU73 -> 18 | BF73: =AX73-AW73 -> 18 | BH73: =AM73-AL73 -> 46055 | BI73: =AO73-AN73 -> 3 | BJ73: =AQ73-AP73 -> 3 | BK73: =AS73-AR73 -> -1 | BL73: =AU73-AT73 -> 3 | BM73: =AW73-AV73 -> 3 | BN73: 70
A74: Operativos | B74: Operaciones Captacion | C74: Luis Alberto | D74: CERRADA | E74: FT_R2911 | F74: Layout R29 V2 -- R2911 | G74: No mapeado | H74: NTT | K74: Backlog | L74: NA | M74: NA | N74: NA | O74: Acuerdo con Erika el 18/12/24. No aplica en este momento por que este Layout es a la medida, por cada caso, con información de contraloría, en Transact no tendremos nada. | Q74: No aplica | R74: Operaciones señala que este Layout es exclusivo de captación, no entendemos porque lo marcan que aplica para crédito //No trabajado por NTT. No vemos de donde obtener esta información del sistema actual ni futuro. El reporte nos pide la información de requerimientos de aseguramientos solicitados por la autoridad ministerial, hacendaria, fiscal, judicial o laboral; así como los datos del titular y cotitular a quién se aplicará el requerimiento y de la cuenta de nómina, mercado abierto u otra modalidad. Debemos ver en conjunto primero que área tiene los datos y segundo si nos aplicará o no. | S74: x | BN74: 71
A75: Mercados | B75: Tesorería | C75: Eduardo Cabral | D75: CERRADA | E75: FT_PAC_II | F75: Layout_PACII_V1 -- PAC | G75: NA | H75: Modulo de tesoreria | I75: NTT | K75: Backlog | L75: NA | M75: NA | N75: NA | O75: Layout_PACII_V1 -- PAC RC05 | P75: nombre layout modifcado | Q75: No Aplica | BN75: 72
A76: Mercados | B76: Tesorería | C76: Eduardo Cabral | D76: MAPEO | E76: FT_CVT_TR | F76: Layout_CVT_TR_V2 | G76: Pendiente | H76: Modulo de tesoreria | I76: NTT | K76: US-Mapeo | L76: Ext NTT | M76: Int Tesoreria | N76: Tesoreria | AM76: 46055 | AN76: 46080 | AO76: 46083 | AP76: 46108 | AQ76: 46111 | AR76: 46129 | AS76: 46128 | AT76: 46129 | AU76: 46132 | AV76: 46150 | AW76: 46153 | AX76: 46171 | AZ76: =+AL76-AK76 -> 0 | BA76: =AN76-AM76 -> 25 | BB76: =AP76-AO76 -> 25 | BC76: =AR76-AQ76 -> 18 | BD76: =AT76-AS76 -> 1 | BE76: =AV76-AU76 -> 18 | BF76: =AX76-AW76 -> 18 | BH76: =AM76-AL76 -> 46055 | BI76: =AO76-AN76 -> 3 | BJ76: =AQ76-AP76 -> 3 | BK76: =AS76-AR76 -> -1 | BL76: =AU76-AT76 -> 3 | BM76: =AW76-AV76 -> 3 | BN76: 73
A77: Mercados | B77: Tesorería | C77: Eduardo Cabral | D77: MAPEO | E77: FT_CVT_IN | F77: Layout_CVT_IN_V2 -- CVT | G77: Pendiente | H77: Modulo de tesoreria | I77: NTT | K77: US-Mapeo | L77: Ext NTT | M77: Int Tesoreria | N77: Tesoreria | AM77: 46055 | AN77: 46080 | AO77: 46083 | AP77: 46108 | AQ77: 46111 | AR77: 46129 | AS77: 46128 | AT77: 46129 | AU77: 46132 | AV77: 46150 | AW77: 46153 | AX77: 46171 | AZ77: =+AL77-AK77 -> 0 | BA77: =AN77-AM77 -> 25 | BB77: =AP77-AO77 -> 25 | BC77: =AR77-AQ77 -> 18 | BD77: =AT77-AS77 -> 1 | BE77: =AV77-AU77 -> 18 | BF77: =AX77-AW77 -> 18 | BH77: =AM77-AL77 -> 46055 | BI77: =AO77-AN77 -> 3 | BJ77: =AQ77-AP77 -> 3 | BK77: =AS77-AR77 -> -1 | BL77: =AU77-AT77 -> 3 | BM77: =AW77-AV77 -> 3 | BN77: 74
A78: Mercados | B78: Tesorería | C78: Eduardo Cabral | D78: MAPEO | E78: FT_CVT | F78: Layout_CVT_MN_ME_V3 -- CVT - RCs - TENENCIA | G78: Pendiente | H78: Modulo de tesoreria | I78: NTT | K78: US-Mapeo | L78: Ext NTT | M78: Int Tesoreria | N78: Tesoreria | AM78: 46055 | AN78: 46080 | AO78: 46083 | AP78: 46108 | AQ78: 46111 | AR78: 46129 | AS78: 46128 | AT78: 46129 | AU78: 46132 | AV78: 46150 | AW78: 46153 | AX78: 46171 | AZ78: =+AL78-AK78 -> 0 | BA78: =AN78-AM78 -> 25 | BB78: =AP78-AO78 -> 25 | BC78: =AR78-AQ78 -> 18 | BD78: =AT78-AS78 -> 1 | BE78: =AV78-AU78 -> 18 | BF78: =AX78-AW78 -> 18 | BH78: =AM78-AL78 -> 46055 | BI78: =AO78-AN78 -> 3 | BJ78: =AQ78-AP78 -> 3 | BK78: =AS78-AR78 -> -1 | BL78: =AU78-AT78 -> 3 | BM78: =AW78-AV78 -> 3 | BN78: 75
A79: Adicionales | B79: Finanzas | C79: Arturo Angeles | D79: MAPEO | E79: FT_ACLME_X | F79: Layout ACLME_X_V1 -- ACLME | G79: Pendiente | H79: Modulo de tesoreria | I79: NTT | K79: US-Mapeo | L79: Ext NTT | M79: Int Tesoreria Add | N79: Finanzas | AM79: 46055 | AN79: 46094 | AO79: 46097 | AP79: 46122 | AQ79: 46125 | AR79: 46136 | AS79: 46135 | AT79: 46136 | AU79: 46139 | AV79: 46157 | AW79: 46160 | AX79: 46171 | AZ79: =+AL79-AK79 -> 0 | BA79: =AN79-AM79 -> 39 | BB79: =AP79-AO79 -> 25 | BC79: =AR79-AQ79 -> 11 | BD79: =AT79-AS79 -> 1 | BE79: =AV79-AU79 -> 18 | BF79: =AX79-AW79 -> 11 | BH79: =AM79-AL79 -> 46055 | BI79: =AO79-AN79 -> 3 | BJ79: =AQ79-AP79 -> 3 | BK79: =AS79-AR79 -> -1 | BL79: =AU79-AT79 -> 3 | BM79: =AW79-AV79 -> 3 | BN79: 76
A80: Situacion Finaciera | B80: Contabilidad | C80: Ramon Jaimes | D80: VOBO US | E80: FLUJOS Y VARIACIONES | F80: R13A_FLUJOS Y VARIACIONES -- R13A | G80: Por iniciar | H80: Se requiere recepcion de requerimiento y Excel. (Usuario) | J80: US envía Difs 20250901 | K80: US-VoBo | M80: Interno | N80: Contabilidad | AU80: 46076 | AV80: 46101 | AW80: 46104 | AX80: 46129 | AZ80: =+AL80-AK80 -> 0 | BA80: =AN80-AM80 -> 0 | BB80: =AP80-AO80 -> 0 | BC80: =AR80-AQ80 -> 0 | BD80: =AT80-AS80 -> 0 | BE80: =AV80-AU80 -> 25 | BF80: =AX80-AW80 -> 25 | BH80: =AM80-AL80 -> 0 | BI80: =AO80-AN80 -> 0 | BJ80: =AQ80-AP80 -> 0 | BK80: =AS80-AR80 -> 0 | BL80: =AU80-AT80 -> 46076 | BM80: =AW80-AV80 -> 3 | BN80: 77
A81: Riesgos | B81: Riesgos | C81: Homero Sanchez | D81: BW-EJECUCION | E81: FILE_TITULOS_DEUDA | F81: LAYOUTS_RCS_v2 -- RC01 - RC03 - RC04 - RC07 - RC08 - RC02 - RC06A | G81: No mapeado | H81: Lo trabaja Bajaware | K81: BW-Ejecucion | L81: Ext Bajaware | M81: Externo | N81: BajaWare | AU81: 46076 | AV81: 46094 | AW81: 46097 | AX81: 46115 | AZ81: =+AL81-AK81 -> 0 | BA81: =AN81-AM81 -> 0 | BB81: =AP81-AO81 -> 0 | BC81: =AR81-AQ81 -> 0 | BD81: =AT81-AS81 -> 0 | BE81: =AV81-AU81 -> 18 | BF81: =AX81-AW81 -> 18 | BH81: =AM81-AL81 -> 0 | BI81: =AO81-AN81 -> 0 | BJ81: =AQ81-AP81 -> 0 | BK81: =AS81-AR81 -> 0 | BL81: =AU81-AT81 -> 46076 | BM81: =AW81-AV81 -> 3 | BN81: 78
A82: Adicionales | B82: Finanzas | C82: Arturo Angeles | D82: MAPEO | E82: FILE_TIPOCAMBIO_DIARIO | F82: Layout_Tipos de Cambio Diario_v2 -- ACLME | G82: Pendiente | H82: Modulo de tesoreria | I82: NTT | K82: US-Mapeo | L82: Ext NTT | M82: Int Tesoreria Add | N82: Finanzas | AM82: 46055 | AN82: 46094 | AO82: 46097 | AP82: 46122 | AQ82: 46125 | AR82: 46136 | AS82: 46135 | AT82: 46136 | AU82: 46139 | AV82: 46157 | AW82: 46160 | AX82: 46171 | AZ82: =+AL82-AK82 -> 0 | BA82: =AN82-AM82 -> 39 | BB82: =AP82-AO82 -> 25 | BC82: =AR82-AQ82 -> 11 | BD82: =AT82-AS82 -> 1 | BE82: =AV82-AU82 -> 18 | BF82: =AX82-AW82 -> 11 | BH82: =AM82-AL82 -> 46055 | BI82: =AO82-AN82 -> 3 | BJ82: =AQ82-AP82 -> 3 | BK82: =AS82-AR82 -> -1 | BL82: =AU82-AT82 -> 3 | BM82: =AW82-AV82 -> 3 | BN82: 79
A83: Mercados | B83: Tesorería | C83: Eduardo Cabral | D83: MAPEO | E83: FILE_TENENCIA_PRECIO | F83: CORE_LayoutTenenciaAdicional_v3.2 -- TENENCIA | G83: Pendiente | H83: Modulo de tesoreria | I83: NTT | K83: US-Mapeo | L83: Ext NTT | M83: Int Tesoreria | N83: Tesoreria | AM83: 46055 | AN83: 46080 | AO83: 46083 | AP83: 46108 | AQ83: 46111 | AR83: 46129 | AS83: 46128 | AT83: 46129 | AU83: 46132 | AV83: 46150 | AW83: 46153 | AX83: 46171 | AZ83: =+AL83-AK83 -> 0 | BA83: =AN83-AM83 -> 25 | BB83: =AP83-AO83 -> 25 | BC83: =AR83-AQ83 -> 18 | BD83: =AT83-AS83 -> 1 | BE83: =AV83-AU83 -> 18 | BF83: =AX83-AW83 -> 18 | BH83: =AM83-AL83 -> 46055 | BI83: =AO83-AN83 -> 3 | BJ83: =AQ83-AP83 -> 3 | BK83: =AS83-AR83 -> -1 | BL83: =AU83-AT83 -> 3 | BM83: =AW83-AV83 -> 3 | BN83: 80
A84: Captacion | B84: Operaciones Captacion | C84: Luis Alberto | D84: DESARROLLO | E84: FILE_SISPAGOS | F84: Layout SISPAGOS BW -- SISPAGOS | G84: Listo | H84: Ntt, ya se reviso txt por usuario VoBo Estructura | I84: Estructura y universo | K84: DES-Desarrollo Txt | L84: Ext NTT | M84: Interno | N84: TI | O84: Se requiera info actualizada congelando sistema para validacion | S84: x | AO84: 46056 | AP84: 46073 | AQ84: 46076 | AR84: 46094 | AS84: 46093 | AT84: 46094 | AU84: 46097 | AV84: 46115 | AW84: 46118 | AX84: 46136 | AZ84: =+AL84-AK84 -> 0 | BA84: =AN84-AM84 -> 0 | BB84: =AP84-AO84 -> 17 | BC84: =AR84-AQ84 -> 18 | BD84: =AT84-AS84 -> 1 | BE84: =AV84-AU84 -> 18 | BF84: =AX84-AW84 -> 18 | BH84: =AM84-AL84 -> 0 | BI84: =AO84-AN84 -> 46056 | BJ84: =AQ84-AP84 -> 3 | BK84: =AS84-AR84 -> -1 | BL84: =AU84-AT84 -> 3 | BM84: =AW84-AV84 -> 3 | BN84: 81
A85: Riesgos | B85: Riesgos | C85: Homero Sanchez | D85: ASIGNA | E85: FILE_RC19_INSUMO | F85: LAYOUTS_RCS_v2 -- RC01 - RC03 - RC04 - RC07 - RC08 - RC02 - RC06A | G85: No mapeado | H85: Lo trabaja Bajaware | K85: Valida Areas | L85: Ext Bajaware | M85: Interno | N85: Riesgos | AK85: 46056 | AL85: 46066 | AM85: 46069 | AN85: 46087 | AO85: 46090 | AP85: 46108 | AQ85: 46111 | AR85: 46129 | AS85: 46128 | AT85: 46129 | AU85: 46132 | AV85: 46150 | AW85: 46153 | AX85: 46171 | AZ85: =+AL85-AK85 -> 10 | BA85: =AN85-AM85 -> 18 | BB85: =AP85-AO85 -> 18 | BC85: =AR85-AQ85 -> 18 | BD85: =AT85-AS85 -> 1 | BE85: =AV85-AU85 -> 18 | BF85: =AX85-AW85 -> 18 | BH85: =AM85-AL85 -> 3 | BI85: =AO85-AN85 -> 3 | BJ85: =AQ85-AP85 -> 3 | BK85: =AS85-AR85 -> -1 | BL85: =AU85-AT85 -> 3 | BM85: =AW85-AV85 -> 3 | BN85: 82
A86: Riesgos | B86: Riesgos | C86: Homero Sanchez | D86: ASIGNA | E86: FILE_RC08_INT_ACC | F86: LAYOUTS_RCS_v2 -- RC01 - RC03 - RC04 - RC07 - RC08 - RC02 - RC06A | G86: No mapeado | H86: Lo trabaja Bajaware | K86: Valida Areas | L86: Ext Bajaware | M86: Interno | N86: Riesgos | AK86: 46056 | AL86: 46066 | AM86: 46069 | AN86: 46087 | AO86: 46090 | AP86: 46108 | AQ86: 46111 | AR86: 46129 | AS86: 46128 | AT86: 46129 | AU86: 46132 | AV86: 46150 | AW86: 46153 | AX86: 46171 | AZ86: =+AL86-AK86 -> 10 | BA86: =AN86-AM86 -> 18 | BB86: =AP86-AO86 -> 18 | BC86: =AR86-AQ86 -> 18 | BD86: =AT86-AS86 -> 1 | BE86: =AV86-AU86 -> 18 | BF86: =AX86-AW86 -> 18 | BH86: =AM86-AL86 -> 3 | BI86: =AO86-AN86 -> 3 | BJ86: =AQ86-AP86 -> 3 | BK86: =AS86-AR86 -> -1 | BL86: =AU86-AT86 -> 3 | BM86: =AW86-AV86 -> 3 | BN86: 83
A87: Riesgos | B87: Riesgos | C87: Homero Sanchez | D87: BW-EJECUCION | E87: FILE_RC06A_DERIVADOS_TEMP | F87: LAYOUTS_RCS_v2 -- RC01 - RC03 - RC04 - RC07 - RC08 - RC02 - RC06A | G87: No mapeado | H87: Lo trabaja Bajaware | K87: BW-Ejecucion | L87: Ext Bajaware | M87: Externo | N87: BajaWare | AU87: 46076 | AV87: 46094 | AW87: 46097 | AX87: 46115 | AZ87: =+AL87-AK87 -> 0 | BA87: =AN87-AM87 -> 0 | BB87: =AP87-AO87 -> 0 | BC87: =AR87-AQ87 -> 0 | BD87: =AT87-AS87 -> 0 | BE87: =AV87-AU87 -> 18 | BF87: =AX87-AW87 -> 18 | BH87: =AM87-AL87 -> 0 | BI87: =AO87-AN87 -> 0 | BJ87: =AQ87-AP87 -> 0 | BK87: =AS87-AR87 -> 0 | BL87: =AU87-AT87 -> 46076 | BM87: =AW87-AV87 -> 3 | BN87: 84
A88: Riesgos | B88: Riesgos | C88: Homero Sanchez | D88: ASIGNA | E88: FILE_RC_CTACOB_INSUMO | F88: LAYOUTS_RCS_v2 -- RC01 - RC03 - RC04 - RC07 - RC08 - RC02 - RC06A | G88: No mapeado | H88: Lo trabaja Bajaware | K88: Valida Areas | L88: Ext Bajaware | M88: Interno | N88: Riesgos | AK88: 46056 | AL88: 46066 | AM88: 46069 | AN88: 46087 | AO88: 46090 | AP88: 46108 | AQ88: 46111 | AR88: 46129 | AS88: 46128 | AT88: 46129 | AU88: 46132 | AV88: 46150 | AW88: 46153 | AX88: 46171 | AZ88: =+AL88-AK88 -> 10 | BA88: =AN88-AM88 -> 18 | BB88: =AP88-AO88 -> 18 | BC88: =AR88-AQ88 -> 18 | BD88: =AT88-AS88 -> 1 | BE88: =AV88-AU88 -> 18 | BF88: =AX88-AW88 -> 18 | BH88: =AM88-AL88 -> 3 | BI88: =AO88-AN88 -> 3 | BJ88: =AQ88-AP88 -> 3 | BK88: =AS88-AR88 -> -1 | BL88: =AU88-AT88 -> 3 | BM88: =AW88-AV88 -> 3 | BN88: 85
A89: Adicionales | B89: Riesgos | C89: Homero Sanchez | D89: ASIGNA | E89: FILE_R01_PAGOS_ANT | F89: LAYOUTS_RCS_v5 | G89: No mapeado | H89: Lo trabaja Bajaware | K89: Valida Areas | L89: Ext Bajaware | M89: Interno | N89: Riesgos | AK89: 46056 | AL89: 46066 | AM89: 46069 | AN89: 46087 | AO89: 46090 | AP89: 46108 | AQ89: 46111 | AR89: 46129 | AS89: 46128 | AT89: 46129 | AU89: 46132 | AV89: 46150 | AW89: 46153 | AX89: 46171 | AZ89: =+AL89-AK89 -> 10 | BA89: =AN89-AM89 -> 18 | BB89: =AP89-AO89 -> 18 | BC89: =AR89-AQ89 -> 18 | BD89: =AT89-AS89 -> 1 | BE89: =AV89-AU89 -> 18 | BF89: =AX89-AW89 -> 18 | BH89: =AM89-AL89 -> 3 | BI89: =AO89-AN89 -> 3 | BJ89: =AQ89-AP89 -> 3 | BK89: =AS89-AR89 -> -1 | BL89: =AU89-AT89 -> 3 | BM89: =AW89-AV89 -> 3 | BN89: 86
A90: Mercados | B90: Tesorería | C90: Eduardo Cabral | D90: CERRADA | E90: FILE_PAC_I | F90: Layout_PACI_V2 -- PAC | G90: NA | H90: Modulo de tesoreria | I90: NTT | K90: Backlog | L90: NA | M90: NA | N90: NA | Q90: No Aplica | BN90: 87
A91: Adicionales | B91: Tesorería | C91: Eduardo Cabral | D91: MAPEO | E91: FILE_OPTO_X | F91: Layout_OPTO_V3 -- OPTO | G91: Pendiente | H91: Modulo de tesoreria | I91: NTT | J91: Marcados originalmente como NA | K91: US-Mapeo | L91: Ext NTT | M91: Int Tesoreria | N91: Tesoreria | AM91: 46055 | AN91: 46080 | AO91: 46083 | AP91: 46108 | AQ91: 46111 | AR91: 46129 | AS91: 46128 | AT91: 46129 | AU91: 46132 | AV91: 46150 | AW91: 46153 | AX91: 46171 | AZ91: =+AL91-AK91 -> 0 | BA91: =AN91-AM91 -> 25 | BB91: =AP91-AO91 -> 25 | BC91: =AR91-AQ91 -> 18 | BD91: =AT91-AS91 -> 1 | BE91: =AV91-AU91 -> 18 | BF91: =AX91-AW91 -> 18 | BH91: =AM91-AL91 -> 46055 | BI91: =AO91-AN91 -> 3 | BJ91: =AQ91-AP91 -> 3 | BK91: =AS91-AR91 -> -1 | BL91: =AU91-AT91 -> 3 | BM91: =AW91-AV91 -> 3 | BN91: 88
A92: Adicionales | B92: Tesorería | C92: Eduardo Cabral | D92: MAPEO | E92: FILE_OPTO_VIII_CONVO | F92: Layout_OPTO_V3 -- OPTO | G92: Pendiente | H92: Modulo de tesoreria | I92: NTT | J92: Marcados originalmente como NA | K92: US-Mapeo | L92: Ext NTT | M92: Int Tesoreria | N92: Tesoreria | AM92: 46055 | AN92: 46080 | AO92: 46083 | AP92: 46108 | AQ92: 46111 | AR92: 46129 | AS92: 46128 | AT92: 46129 | AU92: 46132 | AV92: 46150 | AW92: 46153 | AX92: 46171 | AZ92: =+AL92-AK92 -> 0 | BA92: =AN92-AM92 -> 25 | BB92: =AP92-AO92 -> 25 | BC92: =AR92-AQ92 -> 18 | BD92: =AT92-AS92 -> 1 | BE92: =AV92-AU92 -> 18 | BF92: =AX92-AW92 -> 18 | BH92: =AM92-AL92 -> 46055 | BI92: =AO92-AN92 -> 3 | BJ92: =AQ92-AP92 -> 3 | BK92: =AS92-AR92 -> -1 | BL92: =AU92-AT92 -> 3 | BM92: =AW92-AV92 -> 3 | BN92: 89
A93: Adicionales | B93: Tesorería | C93: Eduardo Cabral | D93: MAPEO | E93: FILE_OPTO_MEREC_CONVO | F93: Layout_OPTO_V3 -- OPTO | G93: Pendiente | H93: Modulo de tesoreria | I93: NTT | K93: US-Mapeo | L93: Ext NTT | M93: Int Tesoreria | N93: Tesoreria | AM93: 46055 | AN93: 46080 | AO93: 46083 | AP93: 46108 | AQ93: 46111 | AR93: 46129 | AS93: 46128 | AT93: 46129 | AU93: 46132 | AV93: 46150 | AW93: 46153 | AX93: 46171 | AZ93: =+AL93-AK93 -> 0 | BA93: =AN93-AM93 -> 25 | BB93: =AP93-AO93 -> 25 | BC93: =AR93-AQ93 -> 18 | BD93: =AT93-AS93 -> 1 | BE93: =AV93-AU93 -> 18 | BF93: =AX93-AW93 -> 18 | BH93: =AM93-AL93 -> 46055 | BI93: =AO93-AN93 -> 3 | BJ93: =AQ93-AP93 -> 3 | BK93: =AS93-AR93 -> -1 | BL93: =AU93-AT93 -> 3 | BM93: =AW93-AV93 -> 3 | BN93: 90
A94: Adicionales | B94: Tesorería | C94: Eduardo Cabral | D94: MAPEO | E94: FILE_OPTO_IX_COM | F94: Layout_OPTO_V3 -- OPTO | G94: Pendiente | H94: Modulo de tesoreria | I94: NTT | J94: Marcados originalmente como NA | K94: US-Mapeo | L94: Ext NTT | M94: Int Tesoreria | N94: Tesoreria | AM94: 46055 | AN94: 46080 | AO94: 46083 | AP94: 46108 | AQ94: 46111 | AR94: 46129 | AS94: 46128 | AT94: 46129 | AU94: 46132 | AV94: 46150 | AW94: 46153 | AX94: 46171 | AZ94: =+AL94-AK94 -> 0 | BA94: =AN94-AM94 -> 25 | BB94: =AP94-AO94 -> 25 | BC94: =AR94-AQ94 -> 18 | BD94: =AT94-AS94 -> 1 | BE94: =AV94-AU94 -> 18 | BF94: =AX94-AW94 -> 18 | BH94: =AM94-AL94 -> 46055 | BI94: =AO94-AN94 -> 3 | BJ94: =AQ94-AP94 -> 3 | BK94: =AS94-AR94 -> -1 | BL94: =AU94-AT94 -> 3 | BM94: =AW94-AV94 -> 3 | BN94: 91
A95: Adicionales | B95: Tesorería | C95: Eduardo Cabral | D95: MAPEO | E95: FILE_OPTO_IX | F95: Layout_OPTO_V3 -- OPTO | G95: Pendiente | H95: Modulo de tesoreria | I95: NTT | J95: Marcados originalmente como NA | K95: US-Mapeo | L95: Ext NTT | M95: Int Tesoreria | N95: Tesoreria | AM95: 46055 | AN95: 46080 | AO95: 46083 | AP95: 46108 | AQ95: 46111 | AR95: 46129 | AS95: 46128 | AT95: 46129 | AU95: 46132 | AV95: 46150 | AW95: 46153 | AX95: 46171 | AZ95: =+AL95-AK95 -> 0 | BA95: =AN95-AM95 -> 25 | BB95: =AP95-AO95 -> 25 | BC95: =AR95-AQ95 -> 18 | BD95: =AT95-AS95 -> 1 | BE95: =AV95-AU95 -> 18 | BF95: =AX95-AW95 -> 18 | BH95: =AM95-AL95 -> 46055 | BI95: =AO95-AN95 -> 3 | BJ95: =AQ95-AP95 -> 3 | BK95: =AS95-AR95 -> -1 | BL95: =AU95-AT95 -> 3 | BM95: =AW95-AV95 -> 3 | BN95: 92
A96: Adicionales | B96: Tesorería | C96: Eduardo Cabral | D96: MAPEO | E96: FILE_OPTO_III | F96: Layout_OPTO_V3 -- OPTO | G96: Pendiente | H96: Modulo de tesoreria | I96: NTT | K96: US-Mapeo | L96: Ext NTT | M96: Int Tesoreria | N96: Tesoreria | AM96: 46055 | AN96: 46080 | AO96: 46083 | AP96: 46108 | AQ96: 46111 | AR96: 46129 | AS96: 46128 | AT96: 46129 | AU96: 46132 | AV96: 46150 | AW96: 46153 | AX96: 46171 | AZ96: =+AL96-AK96 -> 0 | BA96: =AN96-AM96 -> 25 | BB96: =AP96-AO96 -> 25 | BC96: =AR96-AQ96 -> 18 | BD96: =AT96-AS96 -> 1 | BE96: =AV96-AU96 -> 18 | BF96: =AX96-AW96 -> 18 | BH96: =AM96-AL96 -> 46055 | BI96: =AO96-AN96 -> 3 | BJ96: =AQ96-AP96 -> 3 | BK96: =AS96-AR96 -> -1 | BL96: =AU96-AT96 -> 3 | BM96: =AW96-AV96 -> 3 | BN96: 93
A97: Adicionales | B97: Tesorería | C97: Eduardo Cabral | D97: MAPEO | E97: FILE_OPTO_II_COM | F97: Layout_OPTO_V3 -- OPTO | G97: Pendiente | H97: Modulo de tesoreria | I97: NTT | K97: US-Mapeo | L97: Ext NTT | M97: Int Tesoreria | N97: Tesoreria | AM97: 46055 | AN97: 46080 | AO97: 46083 | AP97: 46108 | AQ97: 46111 | AR97: 46129 | AS97: 46128 | AT97: 46129 | AU97: 46132 | AV97: 46150 | AW97: 46153 | AX97: 46171 | AZ97: =+AL97-AK97 -> 0 | BA97: =AN97-AM97 -> 25 | BB97: =AP97-AO97 -> 25 | BC97: =AR97-AQ97 -> 18 | BD97: =AT97-AS97 -> 1 | BE97: =AV97-AU97 -> 18 | BF97: =AX97-AW97 -> 18 | BH97: =AM97-AL97 -> 46055 | BI97: =AO97-AN97 -> 3 | BJ97: =AQ97-AP97 -> 3 | BK97: =AS97-AR97 -> -1 | BL97: =AU97-AT97 -> 3 | BM97: =AW97-AV97 -> 3 | BN97: 94
A98: Adicionales | B98: Tesorería | C98: Eduardo Cabral | D98: MAPEO | E98: FILE_OPTO_II | F98: Layout_OPTO_V3 -- OPTO | G98: Pendiente | H98: Modulo de tesoreria | I98: NTT | K98: US-Mapeo | L98: Ext NTT | M98: Int Tesoreria | N98: Tesoreria | AM98: 46055 | AN98: 46080 | AO98: 46083 | AP98: 46108 | AQ98: 46111 | AR98: 46129 | AS98: 46128 | AT98: 46129 | AU98: 46132 | AV98: 46150 | AW98: 46153 | AX98: 46171 | AZ98: =+AL98-AK98 -> 0 | BA98: =AN98-AM98 -> 25 | BB98: =AP98-AO98 -> 25 | BC98: =AR98-AQ98 -> 18 | BD98: =AT98-AS98 -> 1 | BE98: =AV98-AU98 -> 18 | BF98: =AX98-AW98 -> 18 | BH98: =AM98-AL98 -> 46055 | BI98: =AO98-AN98 -> 3 | BJ98: =AQ98-AP98 -> 3 | BK98: =AS98-AR98 -> -1 | BL98: =AU98-AT98 -> 3 | BM98: =AW98-AV98 -> 3 | BN98: 95
A99: Adicionales | B99: Tesorería | C99: Eduardo Cabral | D99: MAPEO | E99: FILE_OPTO_I | F99: Layout_OPTO_V3 -- OPTO | G99: Pendiente | H99: Modulo de tesoreria | I99: NTT | K99: US-Mapeo | L99: Ext NTT | M99: Int Tesoreria | N99: Tesoreria | AM99: 46055 | AN99: 46080 | AO99: 46083 | AP99: 46108 | AQ99: 46111 | AR99: 46129 | AS99: 46128 | AT99: 46129 | AU99: 46132 | AV99: 46150 | AW99: 46153 | AX99: 46171 | AZ99: =+AL99-AK99 -> 0 | BA99: =AN99-AM99 -> 25 | BB99: =AP99-AO99 -> 25 | BC99: =AR99-AQ99 -> 18 | BD99: =AT99-AS99 -> 1 | BE99: =AV99-AU99 -> 18 | BF99: =AX99-AW99 -> 18 | BH99: =AM99-AL99 -> 46055 | BI99: =AO99-AN99 -> 3 | BJ99: =AQ99-AP99 -> 3 | BK99: =AS99-AR99 -> -1 | BL99: =AU99-AT99 -> 3 | BM99: =AW99-AV99 -> 3 | BN99: 96
A100: Adicionales | B100: Tesorería | C100: Eduardo Cabral | D100: MAPEO | E100: FILE_OPTO_CONVO | F100: Layout_OPTO_V3 -- OPTO | G100: Pendiente | H100: Modulo de tesoreria | I100: NTT | K100: US-Mapeo | L100: Ext NTT | M100: Int Tesoreria | N100: Tesoreria | AM100: 46055 | AN100: 46080 | AO100: 46083 | AP100: 46108 | AQ100: 46111 | AR100: 46129 | AS100: 46128 | AT100: 46129 | AU100: 46132 | AV100: 46150 | AW100: 46153 | AX100: 46171 | AZ100: =+AL100-AK100 -> 0 | BA100: =AN100-AM100 -> 25 | BB100: =AP100-AO100 -> 25 | BC100: =AR100-AQ100 -> 18 | BD100: =AT100-AS100 -> 1 | BE100: =AV100-AU100 -> 18 | BF100: =AX100-AW100 -> 18 | BH100: =AM100-AL100 -> 46055 | BI100: =AO100-AN100 -> 3 | BJ100: =AQ100-AP100 -> 3 | BK100: =AS100-AR100 -> -1 | BL100: =AU100-AT100 -> 3 | BM100: =AW100-AV100 -> 3 | BN100: 97
...

Sheet Relacion 
X1: Bajaware | Negocio | Z1: Negocio | Rocha Mendoza | AB1: Desarrollo (NTT, Lunaro, ION Desarrollo) | AD1: Negocio valida en ATOM | extracciones Transact | AF1: Negocio | AH1: Desarrollo | AJ1: Desarrollo
Z2: 2 semanas | AB2: 2 semanas | AD2: 2 semanas | AF2: 1 semana | AH2: 2 semanas | AJ2: 2 semanas | AL2: 3 días
X3: 01. ASIGNACION AREA | Z3: 02. MAPEO | AB3: 03. DESARROLLO | AD3: 04. VALIDA US | AF3: 05. VOBO US | AH3: 06. BW-EJECUCION | AJ3: 07. VALIDACIÓN BAJAWARE | AL3: 08. CERRADA | AN3: FEBRERO | AR3: MARZO | AV3: ABRIL | BA3: MAYO
A4: Carpeta | B4: Owner | C4: Responsable | D4: Fase | E4: Pestañas | F4: Layout | G4: Nombres en ATOM (No. y nombre que asigno Desarrollo) | H4: Comentarios | I4: Revision VoBo Usuario | J4: Actualizacion | K4: EstatusAct | L4: Sts2 | M4: Desarrollo | N4: AreaApoyo | O4: Obs Add | P4: Obs Add2 | Q4: NO APLICA | R4: MOTIVO | S4: SIGUIENTES PASOS | T4: Paquete Valida Desarrollo en BW | U4: PARTICIPA | V4: # | W4: FECHA ACTUALIZADA | X4: INICIO | Y4: FIN | Z4: INICIO | AA4: FIN | AB4: INICIO | AC4: FIN | AD4: INICIO | AE4: FIN | AF4: INICIO | AG4: FIN | AH4: INICIO | AI4: FIN | AJ4: INICIO | AK4: FIN | AL4: INICIO | AM4: FIN | AN4: 02 - 0 6 | AO4: 09 - 13 | AP4: 16 - 20 | AQ4: 23 - 27 | AR4: 02 - 0 6 | AS4: 09 - 13 | AT4: 16 - 20 | AU4: 23 - 27 | AV4: 30 - 03 | AW4: 06 - 10 | AX4: 13 - 17 | AY4: 20 - 24 | AZ4: 27 - 01 | BA4: 04 - 08 | BB4: 11 - 15 | BC4: 18 - 22 | BD4: 25 - 29
A5: Adicionales | B5: Tesorería | C5: Eduardo Cabral | D5: 04. VALIDA US | E5: VENC_ANT_REPORTOS | F5: Layout_REPORTOS_MN_ME_V7_2024 -- REPORTOS | G5: 123_ENT_REPORTOS_VENC_ANT_Diaria | H5: Modulo de tesoreria | I5: NTT | K5: US-Mapeo | L5: Ext NTT | M5: Int Tesoreria | N5: Tesoreria | O5: Layout_REPORTOS_MN_ME_V7 -- REPORTOS | P5: modif nomb layout | S5: 13Mzo23 Gris manda correo a Ale para que valide sólo estructura irá en vacío 07Abr26 Alejandro R. informó a Gris que este LayOut irá sólo la estructura, gris informa a Erik y Carlos por correo y asigna tarea en Azure y cambia estatus de MAPEO a DESARROLLO 06Abr26 Se envío correo de entrega TXT de NTT, 07Abr26 Alejandro Romero mandó correo que validará se encuentra copiado Ed. 19Feb26 Solicitar VoBo a Usuario, Correo, para que quede autorizado 1. Revisar fecha de entrega de mapeo 2. Solicitar fecha de integración de Reporte de Transacciones | U5: 1. Tesorería (Alejandro) 2. PM (Jennifer) | V5: 1 | W5: X | X5: 46024 | Y5: 46083 | Z5: 46056 | AA5: 46087 | AB5: 46072 | AC5: 46072 | AD5: 46111 | AE5: 46125 | AF5: 46125 | AG5: 46126 | AH5: 46127 | AI5: 46129 | AJ5: 46132 | AK5: 46146 | AL5: =AK5+1 -> 46147 | AM5: =AL5 -> 46147
A6: Adicionales | B6: Captacion | C6: Arturo Angeles | D6: 02. MAPEO | E6: USUARIOS NO CLIENTES BE | F6: R1522_USUARIOS NO CLIENTES BE_V0.4 -- R15 1522 | G6: 114_ENT_R15_1522_Trimestral | I6: NTT | K6: US-Mapeo | M6: Interno | N6: Finanzas | S6: 19Mzo26 Gris manda recordatorio por correo a Arturo de que debe entregar el BRD a Jenny para que NTT genere el reporte, se solicitó fecha de entrega, Desarrollo informa que ya se encuentra la estructura lista. 25/02 Arturo me indico por chat que concluyo el mapeo, Gricelda Manda correo para confirmación y asignación a desarrollo por Azure 1. Revisar mapeo de la información (Usuarios Banca electrónica) | U6: 1. Captacion (Arturo) | V6: 2 | X6: 46024 | Y6: 46083 | Z6: 46056 | AA6: 46080 | AB6: 46083 | AC6: 46108 | AD6: 46111 | AE6: 46122 | AF6: 46121 | AG6: 46122 | AH6: 46125 | AI6: 46143 | AJ6: 46146 | AK6: 46157 | AL6: =AK6+1 -> 46158 | AM6: =AL6 -> 46158
A7: Operativos | B7: Operaciones Captacion | C7: Luis Alberto | D7: 04. VALIDA US | E7: UBICACION DE PUNTOS DE TRANSACC | F7: R2443_Ubicacion - R2443 | G7: 56_ENT_UBICACIÓN_DE_PUNTOS_DE_TRANSACCION_Trimestral | H7: NTT | I7: NTT | K7: Envío Vacio | L7: NA | M7: NA | N7: =#REF! -> #REF! | O7: Acuerdo con Erika el 18/12/24. No aplica en este momento, porque no tendremos nada de lo que solicita. | Q7: No aplica | R7: Este reporte recaba información respecto a la ubicación geográfica de las sucursales, módulos, cajeros automáticos, terminales punto de venta y comisionistas a través de las cuales los usuarios de los servicios financieros realizan las transacciones. | S7: 1. Configurar tablas vacias para envío a Desarrollo 2. Actualmente marcadas como cerradas habilitar en Desarrollo cuando inicie | U7: 1. Desarrollo (Erick/Carlos 2. PM (Gris) | V7: 3 | W7: X | X7: 45659 | Y7: 46083 | Z7: 46084 | AA7: 46084 | AB7: 46085 | AC7: 46098 | AD7: 46099 | AE7: 46119 | AF7: 46119 | AG7: 46120 | AH7: 46121 | AI7: 46125 | AJ7: 46126 | AK7: 46140 | AL7: =AK7+1 -> 46141 | AM7: =AL7 -> 46141
A8: Operativos | B8: Operaciones Captacion | C8: Luis Alberto | D8: 04. VALIDA US | E8: SUCURSALES | F8: R2422_Sucursales -- R2422 | G8: 58_ENT_SUCURSALES_Mensual | H8: NTT | I8: NTT | K8: Envío Vacio | L8: NA | M8: NA | N8: =#REF! -> #REF! | O8: Acuerdo con Erika el 18/12/24. No aplica en este momento, porque no tendremos nada de lo que solicita. | Q8: No aplica | R8: Se refiere a tarjetas, ATM, TPVs, y No. de personal, no tenemos esos datos actualmente, por lo que consideramos que no nos aplica actualmente, pero debemos cerrarlo en conjunto. | S8: 1. Configurar tablas vacias para envío a Desarrollo 2. Actualmente marcadas como cerradas habilitar en Desarrollo cuando inicie | U8: 1. Desarrollo (Erick/Carlos 2. PM (Gris) | V8: 15 | W8: X | X8: 45659 | Y8: 46083 | Z8: 46084 | AA8: 46084 | AB8: 46085 | AC8: 46098 | AD8: 46099 | AE8: 46119 | AF8: 46119 | AG8: 46120 | AH8: 46121 | AI8: 46125 | AJ8: 46126 | AK8: 46140 | AL8: =AK8+1 -> 46141 | AM8: =AL8 -> 46141
A9: Adicionales | B9: Operaciones Captacion | C9: Luis Alberto | D9: 04. VALIDA US | E9: R26OPE | F9: R26 Comisionistas -- R26 2610 2611 2612 2616 | G9: 118_R26_OPERACIONES_Mensual | H9: NTT | I9: NTT | K9: Envío Vacio | L9: NA | M9: NA | N9: =#REF! -> #REF! | O9: Acuerdo con Erika el 18/12/24. No aplica en este momento, porque no tendremos nada de lo que solicita. | Q9: No aplica | R9: Actualmente no tenemos comisionistas, esta información no se puede generar por el momento, nosotros decimos que no nos aplica, pero debemos cerrarlo en conjunto. | S9: 1. Configurar tablas vacias para envío a Desarrollo 2. Actualmente marcadas como cerradas habilitar en Desarrollo cuando inicie | U9: 1. Desarrollo (Erick/Carlos 2. PM (Gris) | V9: 32 | W9: X | X9: 45659 | Y9: 46083 | Z9: 46084 | AA9: 46084 | AB9: 46085 | AC9: 46098 | AD9: 46099 | AE9: 46119 | AF9: 46119 | AG9: 46120 | AH9: 46121 | AI9: 46125 | AJ9: 46126 | AK9: 46140 | AL9: =AK9+1 -> 46141 | AM9: =AL9 -> 46141
A10: Adicionales | B10: Operaciones Captacion | C10: Luis Alberto | D10: 04. VALIDA US | E10: R26_MODULO | F10: R26 Comisionistas -- R26 2610 2611 2612 2615 | G10: 117_R26_MODULO_Mensual | H10: NTT | I10: NTT | K10: Envío Vacio | L10: NA | M10: NA | N10: =#REF! -> #REF! | O10: Acuerdo con Erika el 18/12/24. No aplica en este momento, porque no tendremos nada de lo que solicita. | Q10: No aplica | R10: Actualmente no tenemos comisionistas, esta información no se puede generar por el momento, nosotros decimos que no nos aplica, pero debemos cerrarlo en conjunto. | S10: 1. Configurar tablas vacias para envío a Desarrollo 2. Actualmente marcadas como cerradas habilitar en Desarrollo cuando inicie | U10: 1. Desarrollo (Erick/Carlos 2. PM (Gris) | V10: 33 | W10: X | X10: 45659 | Y10: 46083 | Z10: 46084 | AA10: 46084 | AB10: 46085 | AC10: 46098 | AD10: 46099 | AE10: 46119 | AF10: 46119 | AG10: 46120 | AH10: 46121 | AI10: 46125 | AJ10: 46126 | AK10: 46140 | AL10: =AK10+1 -> 46141 | AM10: =AL10 -> 46141
A11: Adicionales | B11: Tesorería | C11: Eduardo Cabral | D11: 07. VALIDACIÓN BAJAWARE | E11: SWAPS | F11: Layout_SWAPS_V9 -- SWAPS | G11: 154_ENT_SWAPS_Diaria | H11: Modulo de tesoreria | I11: NTT | K11: US-Mapeo | L11: Ext NTT | M11: Int Tesoreria | N11: Tesoreria | O11: Layout_SWAPS_V9.1 -- SWAPS | P11: modif nomb layout | S11: 30Mzo26 Gris mandó mensaje a Eduardo Cabral, Homero y Alex con copia a Eduardo Santiago para preguntar estatus real 1. Revisar mapeo de la informacion 2. Solicitar fecha de integración de Reporte de Transacciones | U11: 1. Tesoreria (Alejandro) 2. PM (Jennifer) | V11: 7 | W11: PENDIENTE | X11: 46024 | Y11: 46083 | Z11: 46056 | AA11: 46087 | AB11: 46083 | AC11: 46122 | AD11: 46111 | AE11: 46136 | AF11: 46118 | AG11: 46136 | AH11: 46125 | AI11: 46150 | AJ11: 46139 | AK11: 46171 | AL11: =AK11+1 -> 46172 | AM11: =AL11 -> 46172
A12: Adicionales | B12: Tesorería | C12: Eduardo Cabral | D12: 04. VALIDA US | E12: SWAP_MEREC_CONVO | F12: Layout_SWAPS_V9 -- SWAPS | G12: 21_ENT_SWAPS_CONVO_Diaria | H12: Modulo de tesoreria | I12: NTT | K12: Envío Vacio | L12: Ext NTT | M12: Int Tesoreria | N12: Tesoreria | O12: Layout_SWAPS_V9.1 -- SWAPS - 1. ENT_SWAP_MEREC_CONVO | P12: modif nomb layout | Q12: No aplica | R12: No se opera en Mercados Reconocidos | S12: 1. Configurar tablas vacias para envío a Desarrollo 2. Actualmente marcadas como cerradas habilitar en Desarrollo cuando inicie | U12: 1. Desarrollo (Erick/Carlos 2. PM (Gris) | V12: 8 | W12: X | X12: 46024 | Y12: 46083 | Z12: 46084 | AA12: 46084 | AB12: 46085 | AC12: 46098 | AD12: 46099 | AE12: 46119 | AF12: 46119 | AG12: 46120 | AH12: 46121 | AI12: 46125 | AJ12: 46126 | AK12: 46140 | AL12: =AK12+1 -> 46141 | AM12: =AL12 -> 46141
A13: Adicionales | B13: Tesorería | C13: Eduardo Cabral | D13: 07. VALIDACIÓN BAJAWARE | E13: SWAP_IV_COM | F13: Layout_SWAPS_V9 -- SWAPS | G13: 156_ENT_SWAP_IV_COM_Diaria | H13: Modulo de tesoreria | I13: NTT | K13: US-Mapeo | L13: Ext NTT | M13: Int Tesoreria | N13: Tesoreria | O13: Layout_SWAPS_V9.1 -- SWAPS | P13: modif nomb layout | Q13: Alex valida con Eduardo | S13: 30Mzo26 Gris mandó mensaje a Eduardo Cabral, Homero y Alex con copia a Eduardo Santiago para preguntar estatus real 1. Revisar mapeo de la informacion 2. Alejandro revisa con Eduardo si aplican estas operación o se manda vacio el reporte | U13: 1. Tesoreria (Alejandro) 2. Tesoreria (Alejandro) | V13: 9 | W13: PENDIENTE | X13: 46024 | Y13: 46083 | Z13: 46056 | AA13: 46087 | AB13: 46083 | AC13: 46122 | AD13: 46111 | AE13: 46136 | AF13: 46118 | AG13: 46136 | AH13: 46125 | AI13: 46150 | AJ13: 46139 | AK13: 46171 | AL13: =AK13+1 -> 46172 | AM13: =AL13 -> 46172
A14: Adicionales | B14: Tesorería | C14: Eduardo Cabral | D14: 07. VALIDACIÓN BAJAWARE | E14: SWAP_IV | F14: Layout_SWAPS_V9 -- SWAPS | G14: 155_ENT_SWAP_IV_Diaria | H14: Modulo de tesoreria | I14: NTT | K14: US-Mapeo | L14: Ext NTT | M14: Int Tesoreria | N14: Tesoreria | O14: Layout_SWAPS_V9.1 -- SWAPS | P14: modif nomb layout | Q14: Alex valida con Eduardo | S14: 30Mzo26 Gris mandó mensaje a Eduardo Cabral, Homero y Alex con copia a Eduardo Santiago para preguntar estatus real 1. Revisar mapeo de la informacion 2. Alejandro revisa con Eduardo si aplican estas operación o se manda vacio el reporte | U14: 1. Tesoreria (Alejandro) 2. Tesoreria (Alejandro) | V14: 10 | W14: PENDIENTE | X14: 46024 | Y14: 46083 | Z14: 46056 | AA14: 46087 | AB14: 46083 | AC14: 46122 | AD14: 46111 | AE14: 46136 | AF14: 46118 | AG14: 46136 | AH14: 46125 | AI14: 46150 | AJ14: 46139 | AK14: 46171 | AL14: =AK14+1 -> 46172 | AM14: =AL14 -> 46172
A15: Adicionales | B15: Tesorería | C15: Eduardo Cabral | D15: 04. VALIDA US | E15: SWAP_I | F15: Layout_SWAPS_V9 -- SWAPS | G15: 153_ENT_SWAP_I_Diaria | H15: Modulo de tesoreria | I15: NTT | K15: Envío Vacio | L15: Ext NTT | M15: Int Tesoreria | N15: Tesoreria | O15: Layout_SWAPS_V9.1 -- SWAPS | P15: modif nomb layout | Q15: No aplica | R15: No se opera en Mercados Reconocidos | S15: 1. Configurar tablas vacias para envío a Desarrollo 2. Actualmente marcadas como cerradas habilitar en Desarrollo cuando inicie | U15: 1. Desarrollo (Erick/Carlos 2. PM (Gris) | V15: 11 | W15: X | X15: 46024 | Y15: 46083 | Z15: 46084 | AA15: 46084 | AB15: 46085 | AC15: 46098 | AD15: 46099 | AE15: 46119 | AF15: 46119 | AG15: 46120 | AH15: 46121 | AI15: 46125 | AJ15: 46126 | AK15: 46140 | AL15: =AK15+1 -> 46141 | AM15: =AL15 -> 46141
A16: Adicionales | B16: Tesorería | C16: Eduardo Cabral | D16: 07. VALIDACIÓN BAJAWARE | E16: SWAP_FLUJOS | F16: Layout_SWAPS_V9 -- SWAPS | G16: 157_ENT_SWAP_FLUJOS_Diaria | H16: Modulo de tesoreria | I16: NTT | K16: US-Mapeo | L16: Ext NTT | M16: Int Tesoreria | N16: Tesoreria | O16: Layout_SWAPS_V9.1 -- SWAPS | P16: modif nomb layout | S16: 30Mzo26 Gris mandó mensaje a Eduardo Cabral, Homero y Alex con copia a Eduardo Santiago para preguntar estatus real 1. Revisar mapeo de la informacion 2. Solicitar fecha de integración de Reporte de Transacciones | U16: 1. Tesoreria (Alejandro) 2. PM (Jennifer) | V16: 12 | W16: PENDIENTE | X16: 46024 | Y16: 46083 | Z16: 46056 | AA16: 46087 | AB16: 46083 | AC16: 46122 | AD16: 46111 | AE16: 46136 | AF16: 46118 | AG16: 46136 | AH16: 46125 | AI16: 46150 | AJ16: 46139 | AK16: 46171 | AL16: =AK16+1 -> 46172 | AM16: =AL16 -> 46172
A17: Adicionales | B17: Tesorería | C17: Eduardo Cabral | D17: 07. VALIDACIÓN BAJAWARE | E17: SWAP_CUOTAS_INT | F17: Layout_SWAPS_V9 -- SWAPS | G17: 24_ENT_SWAP_CUOTAS_INT_Diaria | H17: Modulo de tesoreria | I17: NTT | K17: US-Mapeo | L17: Ext NTT | M17: Int Tesoreria | N17: Tesoreria | O17: Layout_SWAPS_V9.1 -- SWAPS | P17: modif nomb layout | S17: 30Mzo26 Gris mandó mensaje a Eduardo Cabral, Homero y Alex con copia a Eduardo Santiago para preguntar estatus real 1. Revisar mapeo de la informacion 2. Solicitar fecha de integración de Reporte de Transacciones | U17: 1. Tesoreria (Alejandro) 2. PM (Jennifer) | V17: 13 | W17: PENDIENTE | X17: 46024 | Y17: 46083 | Z17: 46056 | AA17: 46087 | AB17: 46083 | AC17: 46122 | AD17: 46111 | AE17: 46136 | AF17: 46118 | AG17: 46136 | AH17: 46125 | AI17: 46150 | AJ17: 46139 | AK17: 46171 | AL17: =AK17+1 -> 46172 | AM17: =AL17 -> 46172
A18: Adicionales | B18: Tesorería | C18: Eduardo Cabral | D18: 02. MAPEO | E18: SWAP_CONVO | F18: Layout_SWAPS_V9 -- SWAPS | G18: 20_ENT_SWAP_MEREC_CONVO_Diaria | H18: Modulo de tesoreria | I18: NTT | K18: US-Mapeo | L18: Ext NTT | M18: Int Tesoreria | N18: Tesoreria | O18: Layout_SWAPS_V9.1 -- SWAPS | P18: modif nomb layout | S18: 06Abr26 Se envío correo de entrega TXT de NTT, 07Abr26 Alejandro Romero mandó correo que validará se encuentra copiado Ed. 1. Revisar mapeo de la informacion 2. Solicitar fecha de integración de Reporte de Transacciones 3. Realizar reunión Tesoreria / Riesgos / TI para el llenado de este reporte | U18: 1. Tesoreria (Alejandro) 2. PM (Jennifer) | V18: 14 | W18: X | X18: 46024 | Y18: 46083 | Z18: 46056 | AA18: 46136 | AB18: 46139 | AC18: 46157 | AD18: 46160 | AE18: 46171 | AF18: 46171 | AG18: 46174 | AH18: 46175 | AI18: 46177 | AJ18: 46178 | AK18: 46192 | AL18: 46195 | AM18: 46196
A19: Adicionales | B19: Operaciones Captacion | C19: Luis Alberto | D19: 04. VALIDA US | E19: R26_COMISIONISTA | F19: R26 Comisionistas -- R26 2610 2611 2612 2614 | G19: 115_R26_COMISIONISTA_Mensual | H19: NTT | I19: NTT | K19: Envío Vacio | L19: NA | M19: NA | N19: =#REF! -> #REF! | O19: Acuerdo con Erika el 18/12/24. No aplica en este momento, porque no tendremos nada de lo que solicita. | Q19: No aplica | R19: Actualmente no tenemos comisionistas, esta información no se puede generar por el momento, nosotros decimos que no nos aplica, pero debemos cerrarlo en conjunto. | S19: 1. Configurar tablas vacias para envío a Desarrollo 2. Actualmente marcadas como cerradas habilitar en Desarrollo cuando inicie | U19: 1. Desarrollo (Erick/Carlos 2. PM (Gris) | V19: 34 | W19: X | X19: 45659 | Y19: 46083 | Z19: 46084 | AA19: 46084 | AB19: 46085 | AC19: 46098 | AD19: 46099 | AE19: 46119 | AF19: 46119 | AG19: 46120 | AH19: 46121 | AI19: 46125 | AJ19: 46126 | AK19: 46140 | AL19: =AK19+1 -> 46141 | AM19: =AL19 -> 46141
A20: Operativos | B20: Producto | C20: Claudia Barroso | D20: 08. CERRADA | E20: SEGUROS NOMINA Y PERS | F20: CUP -- CUP | G20: 72_CUP_PERSONAL_SEG_Solo cuando hay nuevas contrapartes | H20: NA | K20: Backlog | L20: NA | M20: NA | N20: =#REF! -> #REF! | Q20: No Aplica | S20: 1. Solicitar confirmación del Usuarios de que están enterados de que no aplica este reporte | U20: 1. PM (Gricelda) | V20: 16 | W20: NO APLICA | X20: 45659 | Y20: 46083 | Z20: 46108 | AA20: 46108 | AB20: 46108 | AC20: 46108 | AD20: 46108 | AE20: 46108 | AF20: 46108 | AG20: 46108 | AH20: 46108 | AI20: 46108 | AJ20: 46108 | AK20: 46108 | AL20: =AK20 -> 46108 | AM20: =AL20 -> 46108
A21: Adicionales | B21: Tesorería | C21: Eduardo Cabral | D21: 02. MAPEO | E21: SECCION 2E | F21: Layouts Garantias de Liquidez -- GL | G21: 205_ENT_SECCION_2E_Mensual | H21: Modulo de tesoreria | I21: NTT | Rocha | K21: Envío Vacio | L21: NA | M21: NA | N21: =#REF! -> #REF! | O21: Calificaciones Otorgadas (No aplica confirma Denisse) | P21: Finanzas | Q21: No aplica | R21: Comentario Bajaware: Si no cuentan con las operaciones a las que se refiere ese layout, no es necesario llenarlo. Sin embargo, si Banxico da de alta el producto en el portal de Espifnet, tendrían que enviarlo vacío. | S21: 01Abr26 Gris manda correo a Alex y RM para que revisen la actualización de LayOut que mandó BW Gris cambio de sólo estructura Desarrollo a Mapeo, al revisar con usuarios comentaron que sí se tenían que Mapear 1. Configurar tablas vacias para envío a Desarrollo 2. Actualmente marcadas como cerradas habilitar en Desarrollo cuando inicie | U21: 1. Desarrollo (Erick/Carlos 2. PM (Gris) | V21: 17 | W21: X | X21: 46024 | Y21: 46083 | Z21: 46093 | AA21: 46142 | AB21: 46146 | AC21: 46164 | AD21: 46167 | AE21: 46178 | AF21: 46178 | AG21: 46181 | AH21: 46182 | AI21: 46185 | AJ21: 46188 | AK21: 46199 | AL21: 46199 | AM21: 46202 | AN21: 30Mzo2026 Gris subió archivo a repositorio Adiconales y mandó correo a involucrados incluyendo a RMC 27Mzo2026 Gris cambio las fechas de termino de fase de acuerdo a nuevas fechas reestimadas aprobadas en sesión Steerco del 24Mzo26
A22: Adicionales | B22: Tesorería | C22: Eduardo Cabral | D22: 02. MAPEO | E22: SECCION 2D | F22: Layouts Garantias de Liquidez -- GL | G22: 204_ENT_SECCION_2D_Mensual | H22: Modulo de tesoreria | I22: NTT | Rocha | K22: Envío Vacio | L22: NA | M22: NA | N22: =#REF! -> #REF! | O22: Inmuebles | P22: Finanzas/Contabilidad/WO | Q22: No aplica | R22: Comentario Bajaware: Si no cuentan con las operaciones a las que se refiere ese layout, no es necesario llenarlo. Sin embargo, si Banxico da de alta el producto en el portal de Espifnet, tendrían que enviarlo vacío. | S22: 01Abr26 Gris manda correo a Alex y RM para que revisen la actualización de LayOut que mandó BW Gris cambio de sólo estructura Desarrollo a Mapeo, al revisar con usuarios comentaron que sí se tenían que Mapear 1. Configurar tablas vacias para envío a Desarrollo 2. Actualmente marcadas como cerradas habilitar en Desarrollo cuando inicie | U22: 1. Desarrollo (Erick/Carlos 2. PM (Gris) | V22: 18 | W22: X | X22: 46024 | Y22: 46083 | Z22: 46093 | AA22: 46142 | AB22: 46146 | AC22: 46164 | AD22: 46167 | AE22: 46178 | AF22: 46178 | AG22: 46181 | AH22: 46182 | AI22: 46185 | AJ22: 46188 | AK22: 46199 | AL22: 46199 | AM22: 46202 | AN22: 30Mzo2026 Gris subió archivo a repositorio Adiconales y mandó correo a involucrados incluyendo a RMC 27Mzo2026 Gris cambio las fechas de termino de fase de acuerdo a nuevas fechas reestimadas aprobadas en sesión Steerco del 24Mzo26
A23: Adicionales | B23: Tesorería | C23: Eduardo Cabral | D23: 02. MAPEO | E23: SECCION 2C | F23: Layouts Garantias de Liquidez -- GL | G23: 203_ENT_SECCION_2C_Mensual | H23: Modulo de tesoreria | I23: NTT | Rocha | K23: Envío Vacio | L23: NA | M23: NA | N23: =#REF! -> #REF! | O23: Acciones | P23: Tesoreria | Q23: No aplica | R23: Comentario Bajaware: Si no cuentan con las operaciones a las que se refiere ese layout, no es necesario llenarlo. Sin embargo, si Banxico da de alta el producto en el portal de Espifnet, tendrían que enviarlo vacío. | S23: 01Abr26 Gris manda correo a Alex y RM para que revisen la actualización de LayOut que mandó BW Gris cambio de sólo estructura Desarrollo a Mapeo, al revisar con usuarios comentaron que sí se tenían que Mapear 1. Configurar tablas vacias para envío a Desarrollo 2. Actualmente marcadas como cerradas habilitar en Desarrollo cuando inicie | U23: 1. Desarrollo (Erick/Carlos 2. PM (Gris) | V23: 19 | W23: X | X23: 46024 | Y23: 46083 | Z23: 46093 | AA23: 46142 | AB23: 46146 | AC23: 46164 | AD23: 46167 | AE23: 46178 | AF23: 46178 | AG23: 46181 | AH23: 46182 | AI23: 46185 | AJ23: 46188 | AK23: 46199 | AL23: 46199 | AM23: 46202 | AN23: 30Mzo2026 Gris subió archivo a repositorio Adiconales y mandó correo a involucrados incluyendo a RMC 27Mzo2026 Gris cambio las fechas de termino de fase de acuerdo a nuevas fechas reestimadas aprobadas en sesión Steerco del 24Mzo26
A24: Adicionales | B24: Tesorería | C24: Eduardo Cabral | D24: 02. MAPEO | E24: SECCION 2B | F24: Layouts Garantias de Liquidez -- GL | G24: 202_ENT_SECCION_2B_Mensual | H24: Modulo de tesoreria | I24: NTT | Rocha | K24: Envío Vacio | L24: NA | M24: NA | N24: =#REF! -> #REF! | O24: Cartera de Créditos | P24: Operaciones | Q24: No aplica | R24: Comentario Bajaware: Si no cuentan con las operaciones a las que se refiere ese layout, no es necesario llenarlo. Sin embargo, si Banxico da de alta el producto en el portal de Espifnet, tendrían que enviarlo vacío. | S24: 01Abr26 Gris manda correo a Alex y RM para que revisen la actualización de LayOut que mandó BW Gris cambio de sólo estructura Desarrollo a Mapeo, al revisar con usuarios comentaron que sí se tenían que Mapear 1. Configurar tablas vacias para envío a Desarrollo 2. Actualmente marcadas como cerradas habilitar en Desarrollo cuando inicie | U24: 1. Desarrollo (Erick/Carlos 2. PM (Gris) | V24: 20 | W24: X | X24: 46024 | Y24: 46083 | Z24: 46093 | AA24: 46142 | AB24: 46146 | AC24: 46164 | AD24: 46167 | AE24: 46178 | AF24: 46178 | AG24: 46181 | AH24: 46182 | AI24: 46185 | AJ24: 46188 | AK24: 46199 | AL24: 46199 | AM24: 46202 | AN24: 30Mzo2026 Gris subió archivo a repositorio Adiconales y mandó correo a involucrados incluyendo a RMC 27Mzo2026 Gris cambio las fechas de termino de fase de acuerdo a nuevas fechas reestimadas aprobadas en sesión Steerco del 24Mzo26
A25: Adicionales | B25: Tesorería | C25: Eduardo Cabral | D25: 02. MAPEO | E25: SECCION 2A | F25: Layouts Garantias de Liquidez -- GL | G25: 201_ENT_SECCION_2A_Mensual | H25: Modulo de tesoreria | I25: NTT | Rocha | K25: Envío Vacio | L25: NA | M25: NA | N25: =#REF! -> #REF! | O25: Cartera de Valores | P25: Tesoreria | Q25: No aplica | R25: Comentario Bajaware: Si no cuentan con las operaciones a las que se refiere ese layout, no es necesario llenarlo. Sin embargo, si Banxico da de alta el producto en el portal de Espifnet, tendrían que enviarlo vacío. | S25: 01Abr26 Gris manda correo a Alex y RM para que revisen la actualización de LayOut que mandó BW Gris cambio de sólo estructura Desarrollo a Mapeo, al revisar con usuarios comentaron que sí se tenían que Mapear 1. Configurar tablas vacias para envío a Desarrollo 2. Actualmente marcadas como cerradas habilitar en Desarrollo cuando inicie | U25: 1. Desarrollo (Erick/Carlos 2. PM (Gris) | V25: 21 | W25: X | X25: 46024 | Y25: 46083 | Z25: 46093 | AA25: 46142 | AB25: 46146 | AC25: 46164 | AD25: 46167 | AE25: 46178 | AF25: 46178 | AG25: 46181 | AH25: 46182 | AI25: 46185 | AJ25: 46188 | AK25: 46199 | AL25: 46199 | AM25: 46202 | AN25: 30Mzo2026 Gris subió archivo a repositorio Adiconales y mandó correo a involucrados incluyendo a RMC 27Mzo2026 Gris cambio las fechas de termino de fase de acuerdo a nuevas fechas reestimadas aprobadas en sesión Steerco del 24Mzo26
A26: Adicionales | B26: Tesorería | C26: Eduardo Cabral | D26: 02. MAPEO | E26: SECCION 1 | F26: Layouts Garantias de Liquidez -- GL | G26: 200_ENT_SECCION_1_Mensual | H26: Modulo de tesoreria | I26: NTT | Rocha | K26: Envío Vacio | L26: NA | M26: NA | N26: =#REF! -> #REF! | O26: Layouts Garantias de Liquidez | P26: Financiamiento | Q26: No aplica | R26: Comentario Bajaware: Si no cuentan con las operaciones a las que se refiere ese layout, no es necesario llenarlo. Sin embargo, si Banxico da de alta el producto en el portal de Espifnet, tendrían que enviarlo vacío. | S26: 01Abr26 Gris manda correo a Alex y RM para que revisen la actualización de LayOut que mandó BW Gris cambio de sólo estructura Desarrollo a Mapeo, al revisar con usuarios comentaron que sí se tenían que Mapear 1. Configurar tablas vacias para envío a Desarrollo 2. Actualmente marcadas como cerradas habilitar en Desarrollo cuando inicie | U26: 1. Desarrollo (Erick/Carlos 2. PM (Gris) | V26: 22 | W26: X | X26: 45659 | Y26: 46083 | Z26: 46093 | AA26: 46142 | AB26: 46146 | AC26: 46164 | AD26: 46167 | AE26: 46178 | AF26: 46178 | AG26: 46181 | AH26: 46182 | AI26: 46185 | AJ26: 46188 | AK26: 46199 | AL26: 46199 | AM26: 46202 | AN26: 30Mzo2026 Gris subió archivo a repositorio Adiconales y mandó correo a involucrados incluyendo a RMC 27Mzo2026 Gris cambio las fechas de termino de fase de acuerdo a nuevas fechas reestimadas aprobadas en sesión Steerco del 24Mzo26
A27: Adicionales | B27: Tesorería | C27: Eduardo Cabral | D27: 02. MAPEO | E27: REPORTOS_MNME | F27: Layout_REPORTOS_MN_ME_V7_2024 -- REPORTOS | G27: 76_ENT_REPORTOS_MN_ME_Diaria | H27: Modulo de tesoreria | I27: NTT | K27: US-Mapeo | L27: Ext NTT | M27: Int Tesoreria | N27: Tesoreria | O27: Layout_REPORTOS_MN_ME_V7 -- REPORTOS | P27: modif nomb layout | S27: 06Abr26 Se envío correo de entrega TXT de NTT, 07Abr26 Alejandro Romero mandó correo que validará se encuentra copiado Ed. 1. Revisar fecha de entrega de mapeo 2. Solicitar fecha de integración de Reporte de Transacciones 3. Buscar el avance y continuar con el mapeo | U27: 1. Tesorería (Alejandro) 2. PM (Jennifer) | V27: 23 | W27: X | X27: 46024 | Y27: 46083 | Z27: 46056 | AA27: 46136 | AB27: 46139 | AC27: 46157 | AD27: 46160 | AE27: 46171 | AF27: 46171 | AG27: 46174 | AH27: 46175 | AI27: 46177 | AJ27: 46178 | AK27: 46192 | AL27: 46195 | AM27: 46196
A28: Cartera | B28: Operaciones Credito | C28: Luis Alberto | D28: 08. CERRADA | E28: REL_CONSUMO_GARANTIA | F28: V1.05_Credito_IFRS9_Consumo_Completo VF (2) | G28: 3_ENT_REL_CONSUMO_GARANTIA_Mensual | H28: NA | K28: Backlog | L28: NA | M28: NA | N28: =#REF! -> #REF! | Q28: No Aplica | S28: 1. Solicitar confirmación del Usuarios de que están enterados de que no aplica este reporte | U28: 1. PM (Gricelda) | V28: 24 | W28: NO APLICA | X28: 45659 | Y28: 46083 | Z28: 46108 | AA28: 46108 | AB28: 46108 | AC28: 46108 | AD28: 46108 | AE28: 46108 | AF28: 46108 | AG28: 46108 | AH28: 46108 | AI28: 46108 | AJ28: 46108 | AK28: 46108 | AL28: =AK28+1 -> 46109 | AM28: =AL28 -> 46109
A29: Operativos | B29: Producto | C29: Claudia Barroso | D29: 06. BW-EJECUCION | E29: Registro Gral Prd | F29: CUP -- CUP | G29: 63_CUP_REGGRAL_PROD_Solo cuando hay nuevas contrapartes | H29: VoBo Dado por el usuario (No se cuenta con informacion) | I29: Estructura | K29: US-VoBo | M29: Interno | N29: Producto | S29: 1. Ejecutar en Bajaware en cuanto esté habilitado su sistema | T29: Paquete 1 | U29: 1. PM (Gricelda) / Bajaware (Francisco) / Usuarios | V29: 25 | X29: 45659 | Y29: 46031 | Z29: 46034 | AA29: 46038 | AB29: 46041 | AC29: 46045 | AD29: 46048 | AE29: 46052 | AF29: 46055 | AG29: 46062 | AH29: 46076 | AI29: 46101 | AJ29: 46104 | AK29: 46129 | AL29: =AK29+1 -> 46130 | AM29: =AL29 -> 46130
A30: Captacion | B30: Producto | C30: Claudia Barroso | D30: 06. BW-EJECUCION | E30: RECO | F30: Layout RECO BW -- RECO | G30: 106_RECO_Solo cuando hay nuevas contrapartes | H30: Ntt, ya se reviso txt por usuario VoBo | I30: Estructura y universo | J30: Se reasignó a Prodcuto | estaba identificado como VoBo Usuario | K30: DES-Desarrollo Txt | M30: Interno | N30: TI | O30: Se menciona a NTT | P30: Validar la parte de captación NTT para integrar en un solo reporte | S30: 30Mzo26 Gris manda correo a Erik y Carlos Valicación BW 18Mzo26 Gris envía a Claudia por correo solicitud de validación de LayOut 09Mzo26 En espera de archivo de Claudia | Producto, Gris solicito 1. En proceso deDesarrollo validar estatus | T30: Paquete 2 | U30: 1. Desarrollo (Carlos/Erik) | V30: 26 | W30: X | X30: 45659 | Y30: 46038 | Z30: 46041 | AA30: 46052 | AB30: 46056 | AC30: 46080 | AD30: 46083 | AE30: 46105 | AF30: 46105 | AG30: 46106 | AH30: 46111 | AI30: 46113 | AJ30: 46118 | AK30: 46129 | AL30: =AK30+1 -> 46130 | AM30: =AL30 -> 46130
A31: Situación Financiera | B31: Contabilidad | C31: Ramon Jaimes | D31: 06. BW-EJECUCION | E31: RECLASIFICACIONES | F31: R10_RECLASIFICACIONES -- R10 | G31: 32_ENT_R10RECLASIFICACIONES_Mensual | H31: Revision de txt por parte del usuario | I31: Estructura y universo | J31: Duda US ¿Cuál sería la mecánica para la generación de este reporte? | K31: US-VoBo | M31: Interno | N31: Contabilidad | S31: 18Mzo26 Gris cambia estatus a 06. EJECUCIÓN BAJAWARE 1. Ejecutar en Bajaware en cuanto esté habilitado su sistema | T31: Paquete 1 | U31: 1. PM (Gricelda) / Bajaware (Francisco) / Usuarios | V31: 27 | X31: 46024 | Y31: 46083 | Z31: 46041 | AA31: 46052 | AB31: 46056 | AC31: 46069 | AD31: 46070 | AE31: 46072 | AF31: 46073 | AG31: 46073 | AH31: 46076 | AI31: 46101 | AJ31: 46104 | AK31: 46129 | AL31: =AK31+1 -> 46130 | AM31: =AL31 -> 46130
A32: Adicionales | B32: Operaciones Captacion | C32: Luis Alberto | D32: 04. VALIDA US | E32: R26_ADMINISTRADOR | F32: R26 Comisionistas -- R26 2610 2611 2612 2613 | G32: 116_R26_ADMINISTRADOR_Mensual | H32: NTT | I32: NTT | K32: Envío Vacio | L32: NA | M32: NA | N32: =#REF! -> #REF! | O32: Acuerdo con Erika el 18/12/24. No aplica en este momento, porque no tendremos nada de lo que solicita. | Q32: No aplica | R32: Actualmente no tenemos comisionistas, esta información no se puede generar por el momento, nosotros decimos que no nos aplica, pero debemos cerrarlo en conjunto. | S32: 1. Configurar tablas vacias para envío a Desarrollo 2. Actualmente marcadas como cerradas habilitar en Desarrollo cuando inicie | U32: 1. Desarrollo (Erick/Carlos 2. PM (Gris) | V32: 35 | W32: X | X32: 45659 | Y32: 46083 | Z32: 46084 | AA32: 46084 | AB32: 46085 | AC32: 46098 | AD32: 46099 | AE32: 46119 | AF32: 46119 | AG32: 46120 | AH32: 46121 | AI32: 46125 | AJ32: 46126 | AK32: 46140 | AL32: =AK32+1 -> 46141 | AM32: =AL32 -> 46141
A33: Adicionales | B33: UNE | C33: Martin Roman | D33: 02. MAPEO | E33: RECLAMACIONES | F33: LAYOUT R27_V1 -- R27 - 2701 | G33: 128_ENT_RECLAMACIONES_Trimestral | K33: US-Mapeo | M33: Interno | N33: UNE | S33: 10Mzo26 Gris mandó mensaje a Matín Román con nuevo plan de trabajo con fecha término 29Junio, que contempla la selección de proveedor nuevo y la contratación en la fase de Mapeo 01Abr26 Gris recibio mensaje por Teams de que Martín terminó el mapeo con el nuevo LayOut, se cambia a estatus Desarrollo pondré HUBSPOT, sin embargo se comentó que para este tema se debe revisar con Jenny si será Control de Cambios o nuevo Caso de Negocio | BRD 1. Revisar con la UNE fecha de entrega del Control de Cambios a la pantalla de Aclaraciones y reclamaciones | U33: 1. UNE (Matín) | V33: 29 | W33: X | X33: 45659 | Y33: 46052 | Z33: 46056 | AA33: 46142 | AB33: 46146 | AC33: 46185 | AD33: 46188 | AE33: 46191 | AF33: 46192 | AG33: 46195 | AH33: 46196 | AI33: 46167 | AJ33: 46168 | AK33: 46171 | AL33: 46203 | AM33: 46203
A34: Adicionales | B34: Contabilidad | C34: Ramon Jaimes | D34: 06. BW-EJECUCION | E34: R36_PAGOS_ANT_CARGOS_DIF | F34: V1.00_R3601_CARGOS_DIF_PAGOS_ANTICIPADOS -- R36 3601 | G34: 112_CARGOS DIFERIDOS_Mensual | H34: Se requiere recepcion de requerimiento y Excel. (Usuario) | K34: US-VoBo | M34: Interno | N34: Contabilidad | S34: 18Mzo26 Gris cambia estatus a 06. EJECUCIÓN BAJAWARE 1. Ejecutar en Bajaware en cuanto esté habilitado su sistema | T34: Paquete 1 | U34: 1. PM (Gricelda) / Bajaware (Francisco) / Usuarios | V34: 30 | X34: 46024 | Y34: 46083 | Z34: 46041 | AA34: 46052 | AB34: 46056 | AC34: 46069 | AD34: 46070 | AE34: 46072 | AF34: 46073 | AG34: 46073 | AH34: 46076 | AI34: 46101 | AJ34: 46104 | AK34: 46129 | AL34: =AK34+1 -> 46130 | AM34: =AL34 -> 46130
A35: Adicionales | B35: Riesgos | C35: Homero Sanchez | D35: 02. MAPEO | E35: R35_1 | F35: Layout R35_1 -- R35 | G35: 127_ENT_R35_3511_INSUMO_Mensual | H35: Se tiene que realizar una vez migrado a Banco | se puede mapear la cartera de creditos -- Riesgos / Exp Valores Transac -- Tesoreria | I35: Estructura y universo | K35: US-Mapeo | M35: Interno | N35: Riesgos | S35: 1. Validar con Riesgos la entrega hasta la autorizacion de la licencia (36 meses) | U35: 1. Riesgos (Homero / Eduardo) | V35: 31 | W35: X | X35: 46024 | Y35: 46038 | Z35: 46041 | AA35: 46127 | AB35: 46128 | AC35: 46142 | AD35: 46146 | AE35: 46157 | AF35: 46157 | AG35: 46160 | AH35: 46161 | AI35: 46163 | AJ35: 46164 | AK35: 46178 | AL35: 46181 | AM35: 46182 | AN35: 27Mzo2026 Gris cambio las fechas de termino de fase de acuerdo a nuevas fechas reestimadas aprobadas en sesión Steerco del 24Mzo26
A36: Operaciones Captacion | B36: Operaciones Captacion | C36: Arturo Angeles | D36: 04. VALIDA US | E36: OperacionesOEMN | F36: LayoutOEMN_v3 | G36: 197_ENT_OPERACIONESOEMN_Mensual | H36: NTT | I36: NTT | K36: Envío Vacio | L36: NA | M36: NA | N36: =#REF! -> #REF! | O36: No se realizaran operaciones en efectivo | Q36: No aplica | R36: Comentario Bajaware: Con respecto a lo que comentas sobre la falta de operaciones en traslado y manejo de efectivo, no sería necesario enviar el layout; sin embargo, de acuerdo con el artículo 48 de la LIC, éste debe presentarse vacío. | S36: 1. Configurar tablas vacias para envío a Desarrollo 2. Actualmente marcadas como cerradas habilitar en Desarrollo cuando inicie | U36: 1. Desarrollo (Erick/Carlos 2. PM (Gris) | V36: 48 | W36: X | X36: 45659 | Y36: 46083 | Z36: 46084 | AA36: 46084 | AB36: 46085 | AC36: 46098 | AD36: 46099 | AE36: 46119 | AF36: 46119 | AG36: 46120 | AH36: 46121 | AI36: 46125 | AJ36: 46126 | AK36: 46140 | AL36: =AK36+1 -> 46141 | AM36: =AL36 -> 46141
A37: Operativos | B37: Operaciones Captacion | C37: Luis Alberto | D37: 04. VALIDA US | E37: FT_R2911 | F37: Layout R29 V2 -- R2911 | G37: 198_ENT_FT_R2911_Mensual | H37: NTT | I37: NTT | K37: Envío Vacio | L37: NA | M37: NA | N37: =#REF! -> #REF! | O37: Acuerdo con Erika el 18/12/24. No aplica en este momento por que este Layout es a la medida, por cada caso, con información de contraloría, en Transact no tendremos nada. | Q37: No aplica | R37: Operaciones señala que este Layout es exclusivo de captación, no entendemos porque lo marcan que aplica para crédito //No trabajado por NTT. No vemos de donde obtener esta información del sistema actual ni futuro. El reporte nos pide la información de requerimientos de aseguramientos solicitados por la autoridad ministerial, hacendaria, fiscal, judicial o laboral; así como los datos del titular y cotitular a quién se aplicará el requerimiento y de la cuenta de nómina, mercado abierto u otra modalidad. Debemos ver en conjunto primero que área tiene los datos y segundo si nos aplicará o no. | S37: 1. Configurar tablas vacias para envío a Desarrollo 2. Actualmente marcadas como cerradas habilitar en Desarrollo cuando inicie | U37: 1. Desarrollo (Erick/Carlos 2. PM (Gris) | V37: 71 | W37: X | X37: 45659 | Y37: 46083 | Z37: 46084 | AA37: 46084 | AB37: 46085 | AC37: 46098 | AD37: 46099 | AE37: 46119 | AF37: 46119 | AG37: 46120 | AH37: 46121 | AI37: 46125 | AJ37: 46126 | AK37: 46140 | AL37: =AK37+1 -> 46141 | AM37: =AL37 -> 46141
A38: Operativos | B38: Operaciones Captacion | C38: Luis Alberto | D38: 04. VALIDA US | E38: TITULARES GARANTIZADOS | F38: R2423_IFRS9_Titulares_Garantizados_V0.4 -- R2423 | G38: 57_ENT_TITULARES_GARANTIZADOS_Mensual | H38: NTT | I38: NTT | K38: DES-Desarrollo Txt | L38: Ext NTT | M38: Externo | N38: Operaciones | S38: 06Abr26 (Luis comento a Gris NTTData entregó ay se encuentra en estatus VALIDA US 31Mzo26 Gris mandó correo a Luis Alberto para que nos de fecha de término de Aclaraciónes, BW ya contestó 19Mzo26 BW envía correo para aclaración de dudas de Luis Alberto 19Mzo26 Gris pregunta a Jenny cuando tendremos respuesta de NTT Ya se entregó el desarrollo desde Junio 25 | Se requiere poner en ATOM para que usuario los valide | si es en ATOM se requiere que manden el nombre exacto para poder localizarlo para validarlo 1. Revisar el alojamiento de los archivos para subirlos a ATOM, porque no se recibión correo avisando la ejecución | U38: 1. PM (Jennifer) / Desarrollo (Erik/Carlos) | V38: 4 | X38: 45659 | Y38: 46038 | Z38: 46041 | AA38: 46055 | AB38: 46056 | AC38: 46073 | AD38: 46076 | AE38: 46094 | AF38: 46093 | AG38: 46094 | AH38: 46097 | AI38: 46115 | AJ38: 46118 | AK38: 46136 | AL38: =AK38+1 -> 46137 | AM38: =AL38 -> 46137
A39: Adicionales | B39: Operaciones Captacion | C39: Luis Alberto | D39: 08. CERRADA | E39: TADESCOM_BAJAS | F39: Layout TADESCOM -- TADESCOM | G39: 104_ENT_TADESCOM_BAJA_Mensual | H39: NA | K39: Backlog | L39: NA | M39: NA | N39: =#REF! -> #REF! | Q39: No Aplica | S39: 1. Solicitar confirmación del Usuarios de que están enterados de que no aplica este reporte | U39: 1. PM (Gricelda) | V39: 5 | W39: NO APLICA | X39: 45659 | Y39: 46083 | Z39: 46108 | AA39: 46108 | AB39: 46108 | AC39: 46108 | AD39: 46108 | AE39: 46108 | AF39: 46108 | AG39: 46108 | AH39: 46108 | AI39: 46108 | AJ39: 46108 | AK39: 46108 | AL39: =AK39+1 -> 46109 | AM39: =AL39 -> 46109
A40: Adicionales | B40: Operaciones Captacion | C40: Luis Alberto | D40: 08. CERRADA | E40: TADESCOM_ALTAS | F40: Layout TADESCOM -- TADESCOM | G40: 103_ENT_TADESCOM_ALTA_Mensual | H40: NA | K40: Backlog | L40: NA | M40: NA | N40: =#REF! -> #REF! | Q40: No Aplica | S40: 1. Solicitar confirmación del Usuarios de que están enterados de que no aplica este reporte | U40: 1. PM (Gricelda) | V40: 6 | W40: NO APLICA | X40: 45659 | Y40: 46083 | Z40: 46108 | AA40: 46108 | AB40: 46108 | AC40: 46108 | AD40: 46108 | AE40: 46108 | AF40: 46108 | AG40: 46108 | AH40: 46108 | AI40: 46108 | AJ40: 46108 | AK40: 46108 | AL40: =AK40+1 -> 46109 | AM40: =AL40 -> 46109
A41: Operativos | B41: Contabilidad | C41: Ramon Jaimes | D41: 06. BW-EJECUCION | E41: R2431 | F41: Layout R2431_V4 -- R24 C2431 | G41: 62_ENT_PARTES_RELACIONADAS_Mensual | H41: NTT | I41: NTT | J41: • El 18/12/24 le indicamos al PMO que este Layout no correspondía a Operaciones. • Nuevamente en la reunión del 23/07/25 volvimos a pedir que lo asignaran y el acuerdo fue el siguiente: "Contabilidad se lleva a revisar el Layout y si hacen faltan campos se investiga lo que hace falta. Tanto crédito como captación", Sharon le iba a dar seguimiento. • Es urgente que lo asignen, anexo minuta del 23/07/25. | K41: US-Mapeo | L41: Ext NTT | M41: Externo | N41: Finanzas | O41: Asignado a Captación | Contabilidad | Crédito | Riesgo (Definir Owner) | P41: El Layout R24 Serie C, no le corresponde a Operaciones, solicita información de partes relacionadas que nosotros no tenemos, favor de revisar a fondo y determinar qué área lo debe llenar. | S41: 30Mzo26 Gris manda correo a Erik y Carlos Valicación BW 25mZO26 Ramón Jaimes envió VoBo. de TXT por correo el 25Mzo26, Gris registra 06. BW-EJECUCION 09Mzo26 Erik manda correo se liberó el LayOut | Gris manda correo a Ramón para su validación 04Mar26 Gris cambia estado 03. Desarrollo | Ramón entregó Mapeo 1. Revisar mapeo de la información (Partes relacionadas) 2. Revisar integración de información de crédito y captación | T41: Paquete 2 | U41: 1. Captacion (Arturo) 2. Captacion (Arturo) / Operaciones (Luis A.) | V41: 37 | X41: 46024 | Y41: 46083 | Z41: 46056 | AA41: 46080 | AB41: 46083 | AC41: 46108 | AD41: 46111 | AE41: 46122 | AF41: 46121 | AG41: 46122 | AH41: 46125 | AI41: 46143 | AJ41: 46146 | AK41: 46157 | AL41: =AK41+1 -> 46158 | AM41: =AL41 -> 46158
A42: Cartera | B42: Operaciones Credito | C42: Luis Alberto | D42: 04. VALIDA US | E42: R04A_SALDOS | F42: V1.01_Credito_IFRS9_R04A -- A0411 - A0417 - A0419 - A0420 - A0424 | G42: 9_ENT_R04A_SALDOS_Mensual | H42: Se tiene la estructura construida y se integraron los datos con los que se cuenta, aun no se cuenta con todo el universo(Fuentes externas | I42: Estructura | K42: DES-Desarrollo Txt | M42: Interno | N42: TI | S42: 1. Identificar faltantes para liberar reportes | U42: 270226 Gris cambio estatus a Validación por Usuario ya que en correo Erik listado de liberados 1. Desarrollo (Carlos/Erik) | V42: 38 | W42: X | X42: 45659 | Y42: 46038 | Z42: 46041 | AA42: 46052 | AB42: 46056 | AC42: 46080 | AD42: 46099 | AE42: 46113 | AF42: 46113 | AG42: 46118 | AH42: 46119 | AI42: 46121 | AJ42: 46122 | AK42: 46136 | AL42: =AK42+1 -> 46137 | AM42: =AL42 -> 46137
A43: Operativos | B43: Operaciones Captacion | C43: Luis Alberto | D43: 08. CERRADA | E43: RECLAMACIONES BURSATILES BM | F43: R2711_ReclamacionesB_V0.4 | G43: POR DEFINIR | H43: NA | K43: Backlog | L43: NA | M43: NA | N43: =#REF! -> #REF! | O43: Estaba asiugnado a NTT | Q43: No Aplica | S43: 26Feb26 Bajaware | Gris preguntó a Martín quién aprobo que no aplica, la respuesta de Martín a Gricelda por WhatsApp fue que se decidio en una sesión que se tuvo con Captación, producto y operaciones. Gris comento a Luis y contestó que on nosotros no lo vio a ese detalle, pero si el PMO ya determino que no aplica adelante, yo no podría decirte si aplica o no. En su caso quien te lo podría confirmar a detalle sería Bajawar 1. Solicitar confirmación del Usuarios de que están enterados de que no aplica este reporte | U43: 1. PM (Gricelda) | V43: 28 | W43: NO APLICA | X43: 45659 | Y43: 46083 | Z43: 46108 | AA43: 46108 | AB43: 46108 | AC43: 46108 | AD43: 46108 | AE43: 46108 | AF43: 46108 | AG43: 46108 | AH43: 46108 | AI43: 46108 | AJ43: 46108 | AK43: 46108 | AL43: =AK43+1 -> 46109 | AM43: =AL43 -> 46109
A44: Cartera | B44: Contabilidad | C44: Ramon Jaimes | D44: 06. BW-EJECUCION | E44: R04A_MOV_419 | F44: V1.01_Credito_IFRS9_R04A -- A0411 - A0417 - A0419 - A0420 - A0424 - R04A_MOV_419 | G44: 22_ENT_R04A_MOV_419_Mensual | I44: Estructura y universo | J44: Reasignado a Contabilidad | K44: DES-Desarrollo Txt | M44: Interno | N44: Contabilidad | S44: 04Mzo26 Gris manda correo a Ramón para que valide TXT | Correo que mandó Carlos Torres | Se cambia a estatus 04. VALIDA US 1. Reporte en Desarrollo validar fecha de entrega | T44: Paquete 2 | U44: 1. Desarrollo (Erik/Carlos | V44: 40 | W44: X | X44: 46024 | Y44: 46038 | Z44: 46031 | AA44: 46052 | AB44: 46056 | AC44: 46080 | AD44: 46083 | AE44: 46105 | AF44: 46105 | AG44: 46106 | AH44: 46111 | AI44: 46113 | AJ44: 46118 | AK44: 46132 | AL44: =AK44+1 -> 46133 | AM44: =AL44 -> 46133
